[{"a":"@オークロード","m":"待機:revolving_hearts:","t":0},{"a":"@ネクサス-p1h","m":"□□","t":0},{"a":"@あまがいそら","m":"□□□","t":0},{"a":"@96のり茶","m":"高評価&X共有、ポチッとﾆｬ:paw_prints:","t":0},{"a":"@あさあすく","m":"□□□","t":0},{"a":"@fia_osake","m":"□□□結構遅くに枠立てだけど大丈夫かな？□","t":0},{"a":"@fia_osake","m":"！？！？　もうおきてる、、、だと、、、！？:_ぽけぇ:","t":0},{"a":"@いくぽん_ikupon","m":"□□□□","t":0},{"a":"@いくぽん_ikupon","m":"配信開始前の高評価ポチ＆X共有ヨシ:backhand_index_pointing_right:","t":0},{"a":"@どこにでもいるよっちゃん","m":"□□□","t":0},{"a":"@おつかれさま","m":"待機〜□","t":0},{"a":"@96のり茶","m":"もしかして、寝てない説ぅ〜","t":0},{"a":"@96のり茶","m":"これは、はやく寝かせないといけないな","t":0},{"a":"@suzumiya322","m":"もう、SNSで動いてるだと:red_exclamation_mark:？□","t":0},{"a":"@白沼俊コシヒカリ","m":"□□□□□","t":0},{"a":"@天城シナノ","m":"□□□","t":0},{"a":"@お肉焼き職人ミヤビたん-3968","m":"□□□高評価共有完了□□□","t":0},{"a":"@ざらめラスク","m":"待機〜","t":0},{"a":"@ゆめのきし","m":"おは□□、□□□、高評価押しておきますね","t":0},{"a":"@最弱のアテナ","m":"□□□","t":0},{"a":"@高橋伸一-g5j","m":"ミミィちゃん□ひょっとして一睡もしてないんじゃないんですか□大丈夫ですか□","t":0},{"a":"@hiroroろめふれ","m":"□□","t":0},{"a":"@けろにぃ-m9g","m":"□□□","t":0},{"a":"@アストレイ-p01","m":"待機〜","t":0},{"a":"@猫三叉","m":"□□□","t":0},{"a":"@AHEEBIBOYS","m":"□□□","t":17},{"a":"@ほいみ","m":"□□□","t":28},{"a":"@まっつん-UR","m":"□□□","t":36},{"a":"@どこにでもいるよっちゃん","m":"おは□□〜","t":46},{"a":"@そしてこれが...ベジットブルー見守り","m":"おはようございます:sun:","t":58},{"a":"@高橋伸一-g5j","m":"ミミィちゃん□きた～ありがとうございます:smiling_face_with_smiling_eyes:","t":62},{"a":"@ネクサス-p1h","m":"おはろね~","t":70},{"a":"@猫三叉","m":"おは□□□","t":74},{"a":"@ノラネコ生活","m":"□□□","t":86},{"a":"@デューク-c5t","m":"おはろねです〜。雪はほとんど降らなかったけど、めっちゃ寒いです〜。","t":91},{"a":"@にじGTAの光","m":"おはろね","t":94},{"a":"@March649","m":"きちゃ:fish::fishing_pole:","t":102},{"a":"@kh00000-t","m":"おはろねです　がんばってー","t":104},{"a":"@ざらめラスク","m":"おはろね〜","t":110},{"a":"@銀猫のナギ","m":"□□□","t":129},{"a":"@inkringくまりん","m":"おはろね:white_exclamation_mark:","t":130},{"a":"@ネクサス-p1h","m":"1時間30分なんて短かすぎる...","t":164},{"a":"@アストレイ-p01","m":"おはろね〜","t":167},{"a":"@ヨッシー67","m":"□□□","t":168},{"a":"@しゅーくりむ沢山食べたいしゅうたん","m":"おはろね","t":168},{"a":"@猫沢-1","m":"おはろね～","t":175},{"a":"@天城シナノ","m":"おは□□です〜","t":175},{"a":"@米良智史","m":"おはろね","t":176},{"a":"@suzumiya322","m":"おはろね～","t":176},{"a":"@AHEEBIBOYS","m":"おは□□□","t":176},{"a":"@こうpon2865","m":"おは□□〜","t":183},{"a":"@ポケテン","m":"おは□","t":186},{"a":"@かず-b5i","m":"おは□□","t":189},{"a":"@銀輪766","m":"おはろねです〜","t":191},{"a":"@あまがいそら","m":"おは□□□","t":193},{"a":"@ほいみ","m":"おは□□□□□□","t":193},{"a":"@どこにでもいるよっちゃん","m":"□□","t":193},{"a":"@ふぉり-r9l","m":"おはろね～","t":194},{"a":"@あさあすく","m":"おは□□です～□","t":194},{"a":"@fia_osake","m":"おは□〜□","t":195},{"a":"@いはらじゅん","m":"おはろね","t":196},{"a":"@ヨッシー67","m":"おは□□〜","t":200},{"a":"@お肉焼き職人ミヤビたん-3968","m":"おは□□！！可愛い・天使・女神！","t":202},{"a":"@OA_オーエー","m":"おはろねーーーー おはようございます～～～","t":203},{"a":"@けろにぃ-m9g","m":"おは□□～","t":205},{"a":"@クマがクマった球磨熊ーくまくまー","m":"おは□□〜ฅʕ•ᴥ•ʔฅ","t":206},{"a":"@おつかれさま","m":"おは□〜","t":206},{"a":"@ノラネコ生活","m":"おは□","t":207},{"a":"@八神おすず","m":"おはろね～","t":211},{"a":"@まっつん-UR","m":"おは□□□高評価＆共有完了よ□","t":213},{"a":"@ネクサス-p1h","m":"メンバー歷11か月になったよ。来月ついに1年だ〜","t":213},{"a":"@赤いチャッピー","m":"おは□","t":217},{"a":"@サキト_Sakito","m":"おはろね～","t":217},{"a":"@おつかれさま","m":"ないまい！","t":220},{"a":"@けろにぃ-m9g","m":"おお～～～□□□□□","t":221},{"a":"@爽籟そうらいrefreshing-bereeze","m":"おはようございます","t":221},{"a":"@お肉焼き職人ミヤビたん-3968","m":"ないまい","t":224},{"a":"@最弱のアテナ","m":"おは□□","t":225},{"a":"@ヒロキです-k6l","m":"おは□今日も仕事です！","t":226},{"a":"@ねこにゃ-l1s","m":"おはようございます。","t":230},{"a":"@おもちにぃに","m":"ないまい！","t":230},{"a":"@こももん-孫仁こもも","m":"おはようございます　高評価忘れないうちに高評価","t":231},{"a":"@fia_osake","m":"お出かけか！楽しんでくるんやで！","t":232},{"a":"@まっつん-UR","m":"ないまい！","t":233},{"a":"@ざらめラスク","m":"睡眠時間ちゃんととれてる？外の雪は大丈夫？","t":234},{"a":"@riri-hikarigamech.5849","m":"おは□□　久しぶり！","t":235},{"a":"@fia_osake","m":"ないまい！","t":237},{"a":"@お肉焼き職人ミヤビたん-3968","m":"だいぶ元気やねw","t":237},{"a":"@96のり茶","m":"本日は、真白猫健康・美・促進睡眠投資信託さんへ、シャバ代です。ぺっ〜:double_exclamation_mark:","t":238},{"a":"@おつかれさま","m":"本当に〜？w","t":242},{"a":"@windy0910","m":"おはろね～仕事行ってきます。朝活がんばってねq(*･ω･*)pﾌｧｲﾄ!　１日がんば！！！！","t":246},{"a":"@長月重陽sgr","m":"おはよう","t":246},{"a":"@riri-hikarigamech.5849","m":"□□□","t":249},{"a":"@suzumiya322","m":"お友達？自分呼ばれてない！","t":249},{"a":"@寒村サムソン","m":"おはようさん","t":249},{"a":"@suzumiya322","m":"□□□","t":253},{"a":"@銀猫のナギ","m":"おは□□□","t":257},{"a":"@ヒロキです-k6l","m":"今日で1ヵ月経ちました！","t":258},{"a":"@96のり茶","m":"おは□□ﾆｬ〜:paw_prints:","t":258},{"a":"@suzumiya322","m":"ないまい","t":259},{"a":"@fia_osake","m":"□□□","t":270},{"a":"@おもちにぃに","m":"おは□□雪がとんでもないことになってるので職場で一泊しました。今から出勤してきます","t":272},{"a":"@fia_osake","m":"ないまい","t":273},{"a":"@おつかれさま","m":"ないまい！","t":280},{"a":"@長月重陽sgr","m":"猫は炬燵で丸くなるのではないのか？","t":284},{"a":"@天城シナノ","m":"ないまい","t":289},{"a":"@漣-さざなみ-L6n","m":"おは□□！今日は早起きすぎてびっくりした！！","t":290},{"a":"@お肉焼き職人ミヤビたん-3968","m":"いつもの寝起き声じゃないと思ったらそういうことだったのかw寝てないかと思ったw","t":294},{"a":"@ざらめラスク","m":"普段何時間睡眠なの…？:grinning_face_with_sweat:","t":297},{"a":"@お肉焼き職人ミヤビたん-3968","m":"ないまい","t":306},{"a":"@まっつん-UR","m":"3時からずっと起きてるんかｗ","t":308},{"a":"@ポケテン","m":"5時間……言うほど多くなくない？","t":310},{"a":"@天城シナノ","m":"5時間はまだ短い方よ","t":313},{"a":"@suzumiya322","m":"ないまい～","t":319},{"a":"@user-one1one1","m":"おはろね〜","t":320},{"a":"@おもちにぃに","m":"ないまいないすぱ！","t":326},{"a":"@96のり茶","m":"もう、活動時間が、逆転してるのよ","t":332},{"a":"@乂饕餮","m":"おは□□","t":343},{"a":"@洋二-v3e","m":"ないまい:sparkles:","t":343},{"a":"@長月重陽sgr","m":"３時から？","t":351},{"a":"@けろにぃ-m9g","m":"ましろねみみぃさま　もっと寝てくださいね！お死事行ってきますね…お出かけ楽しんできてね～(*´ω｀)","t":354},{"a":"@user-one1one1","m":"お肌に悪いよ","t":367},{"a":"@ざらめラスク","m":"ショートスリーパーかな？","t":368},{"a":"@おつかれさま","m":"□□□","t":370},{"a":"@ぽち884","m":"おはろねー","t":373},{"a":"@ゲーム大好きytk","m":"おはろね","t":377},{"a":"@fia_osake","m":"□□□","t":380},{"a":"@ざらめラスク","m":"極端だね:grinning_face_with_sweat:","t":387},{"a":"@いはらじゅん","m":"あたしは眠剤安定剤使って4時間しか眠れない","t":387},{"a":"@お肉焼き職人ミヤビたん-3968","m":"睡眠時間の振り幅が大きすぎるのよw","t":389},{"a":"@ヒロキです-k6l","m":"□□□","t":393},{"a":"@OKI.オキ","m":"おはようございます:sun:","t":393},{"a":"@飯使いの炉火の昔語","m":"久しぶりでーす元ましろね飼い主のゾンビでーすもー忘れた頃かなー","t":394},{"a":"@おもちにぃに","m":"□□□","t":401},{"a":"@96のり茶","m":"なんか、ミミィちゃんと、活動時間がシンクロして怖いぞ:_パニック:","t":410},{"a":"@かわじ-kawaji","m":"おはろねー","t":413},{"a":"@風衣葉冬優-f9w","m":"おはようございます香風智乃(かふうちの)です 高評価押させていただきました","t":421},{"a":"@ニワマサ","m":"おはろね！ 相変わらず、足の冷えが······。","t":429},{"a":"@おつかれさま","m":"早起きで負けたの初めてじゃないかなw","t":430},{"a":"@ゲーム大好きytk","m":"ましろねがハッピーハッピーハッピーって、猫ミームするの？","t":437},{"a":"@マーくん-v9f","m":"おはようございます:grinning_face_with_big_eyes:寒いですね:cold_face:","t":441},{"a":"@96のり茶","m":"お友達とのお出掛けは、とても大事だ。","t":455},{"a":"@こーじ777","m":"おはろね〜","t":462},{"a":"@お肉焼き職人ミヤビたん-3968","m":"枠ができるのが遅かったのも寝てるからだったのか","t":476},{"a":"@K4nN0-かんの","m":"あれ、お出掛けに俺呼ばれてないんだけど？","t":492},{"a":"@長月重陽sgr","m":"５時前に起きて５時３０分～６時２０くらいまで雪かきしてた・・","t":493},{"a":"@かきみーらorz","m":"おは□□","t":503},{"a":"@天城シナノ","m":"そのまま5時頃まで寝てればよく寝たね！って言えたのに、もちろん布団に入ってねたよね？:_ぽけぇ:","t":526},{"a":"@なだき","m":"ましろねさん！おはろねー！こうひょうかをおしました！","t":535},{"a":"@pale4541","m":"おはようございます","t":542},{"a":"@めるふぁりな-m7","m":"おは□□","t":546},{"a":"@アポーーンス","m":"おは□です","t":551},{"a":"@飯使いの炉火の昔語","m":"初めてきた頃は30人ぐらいだったのに十分足らずで70位、、、漢字が読めない真白猫成長したね、ﾎﾛﾘ","t":571},{"a":"@ネクサス-p1h","m":"早起きは得意だよ。早いときには4時には起きてる","t":577},{"a":"@riri-hikarigamech.5849","m":"□□□","t":584},{"a":"@fia_osake","m":"ましろねの固定コメが3:19にあるからそのあたりだねぇ","t":595},{"a":"@お肉焼き職人ミヤビたん-3968","m":"□□□","t":600},{"a":"@fia_osake","m":"□□□","t":600},{"a":"@ネクサス-p1h","m":"□□□","t":605},{"a":"@おつかれさま","m":"□□□","t":614},{"a":"@96のり茶","m":"今週、突風、爆風やらで、体感−４℃のクソ寒い現場、今日も、寒いのよ。","t":634},{"a":"@銀猫のナギ","m":"□□□","t":640},{"a":"@なか-st","m":"ｵﾊﾛﾈｯ","t":651},{"a":"@長月重陽sgr","m":"除雪は、金にならない労働","t":662},{"a":"@寒村サムソン","m":"ないすぱ！","t":670},{"a":"@96のり茶","m":"同接７６人、増えたねぇ","t":677},{"a":"@ざらめラスク","m":"ナイスパです〜","t":690},{"a":"@96のり茶","m":":cucumber:にゃいすぱ:paw_prints:","t":690},{"a":"@beriri-utmt","m":"おは□□雪が積もりに積もって雪かき地獄に行きそう…□","t":695},{"a":"@ネクサス-p1h","m":"ナイメン","t":716},{"a":"@寒村サムソン","m":"ないめん！","t":723},{"a":"@riri-hikarigamech.5849","m":"□□□","t":727},{"a":"@hiroroろめふれ","m":"おは□□□","t":731},{"a":"@いはらじゅん","m":"メンバーになりました","t":732},{"a":"@beriri-utmt","m":"□□□□","t":735},{"a":"@hiroroろめふれ","m":"ないめん□□","t":744},{"a":"@八神おすず","m":"仕事行ってくる～外がキンキンに冷えてやがるっ","t":749},{"a":"@ライマル-i5w","m":"おはろね","t":749},{"a":"@おもちにぃに","m":"□□□□","t":752},{"a":"@いんぷっぷ","m":"おはろね　雪やべぇ","t":765},{"a":"@黒衣装師-Kuroi-Sousi","m":"おはろね～","t":768},{"a":"@Sandra-v7j5w","m":"おはろねです","t":768},{"a":"@おもちにぃに","m":"□□□□","t":781},{"a":"@いはらじゅん","m":"□□□","t":782},{"a":"@beriri-utmt","m":"□□□□□","t":787},{"a":"@riri-hikarigamech.5849","m":"□□□□□","t":789},{"a":"@お肉焼き職人ミヤビたん-3968","m":"この枠開いたの夢かと思ったら、起きた時もこの枠開いてたから夢じゃなかったと思うと同時に本能的に枠が立ったのに気づいたのかもしれん","t":791},{"a":"@ネクサス-p1h","m":"□□□","t":799},{"a":"@お肉焼き職人ミヤビたん-3968","m":"□□□","t":799},{"a":"@いはらじゅん","m":"□□□□□","t":801},{"a":"@いはらじゅん","m":"昨日京都雪降りました","t":812},{"a":"@御剣晃.Akira.Mitsurugi","m":"おは□","t":827},{"a":"@おつかれさま","m":"お出かけ楽しんでおいでね〜w","t":842},{"a":"@寒村サムソン","m":"ナイメン！","t":847},{"a":"@suzumiya322","m":"□□□","t":848},{"a":"@アメリカ王つっきーかーちす","m":"おはろねー","t":856},{"a":"@あるえふ_jp","m":"おはろねー！","t":859},{"a":"@fia_osake","m":"□□□□","t":860},{"a":"@寒村サムソン","m":"おともだちとおでかけえらい:clapping_hands:","t":860},{"a":"@RexRayEX","m":"おは□□□□","t":873},{"a":"@ざらめラスク","m":"ナイメンです〜","t":879},{"a":"@96のり茶","m":"□□□","t":901},{"a":"@水田敦士","m":"おはようございます。","t":914},{"a":"@飯使いの炉火の昔語","m":"真白猫が漢字を読めた、、、だと？酒代だー","t":929},{"a":"@ネクサス-p1h","m":"今日も全国的に寒いみたいだから防寒対策しっかりね〜","t":939},{"a":"@お肉焼き職人ミヤビたん-3968","m":"□□","t":941},{"a":"@おつかれさま","m":"□□","t":966},{"a":"@ナタ-nat","m":"おはようございます","t":975},{"a":"@riri-hikarigamech.5849","m":"□□□","t":977},{"a":"@なんとか勝-masaru","m":"おは□□□","t":987},{"a":"@96のり茶","m":"ましろねーず『今日、ミミィちゃんの寝顔観てたら、外に締め出されました。もう、中に入れて下さい』","t":989},{"a":"@beriri-utmt","m":"□□□","t":992},{"a":"@おつかれさま","m":"こっちでも珍しく-4℃だ！","t":1006},{"a":"@ざらめラスク","m":"こっちも今朝もドカ雪積もっとった…","t":1013},{"a":"@ネクサス-p1h","m":"高評 価100:clapping_hands::clapping_hands:","t":1013},{"a":"@寒村サムソン","m":"ないすぱ！","t":1015},{"a":"@96のり茶","m":"高評価100:clapping_hands::clapping_hands::clapping_hands:","t":1025},{"a":"@お肉焼き職人ミヤビたん-3968","m":"こたつ必要ないくらいあったかい部屋だもんね","t":1026},{"a":"@長月重陽sgr","m":"炬燵が読めただと！","t":1030},{"a":"@ざらめラスク","m":"早速高評価100:clapping_hands::clapping_hands::clapping_hands:","t":1041},{"a":"@beriri-utmt","m":"高評価100□□□","t":1043},{"a":"@fia_osake","m":"高評価100！□□□","t":1049},{"a":"@96のり茶","m":"炬燵は、読めたのか","t":1050},{"a":"@田中靖章-t6c","m":"おはろね～♪","t":1050},{"a":"@suzumiya322","m":"□□□","t":1059},{"a":"@くりにゃー","m":"おはろね おはよーございますにゃ","t":1060},{"a":"@お肉焼き職人ミヤビたん-3968","m":"高評価100□□□","t":1072},{"a":"@ネクサス-p1h","m":"真白猫さんってたまに難読漢字でも迷うことなく読むことあるよね","t":1091},{"a":"@riri-hikarigamech.5849","m":"高評価100□□□□□","t":1107},{"a":"@すいのみ","m":"おは□俺とのデートが楽しみで遅くまで眠れなかったんですね□","t":1113},{"a":"@96のり茶","m":"いつからだろう、自分もショートスリーパー体質に、かわったよ","t":1117},{"a":"@suzumiya322","m":"今日はお先におつろねです！楽しんでね！","t":1118},{"a":"@moe3979","m":"おはようございます〜頑張る貴方にご挨拶・高評価ポチッ:thumbs_up:","t":1126},{"a":"@うちなえびふらい","m":"おはろね〜","t":1126},{"a":"@おやぢ5963","m":"おはようございます:smiling_face_with_smiling_eyes:","t":1130},{"a":"@fia_osake","m":"毎度お馴染みコメント迷子w","t":1149},{"a":"@Holy792","m":"おはろね","t":1149},{"a":"@お肉焼き職人ミヤビたん-3968","m":"い　つ　も　の　迷　子","t":1149},{"a":"@しょうごレオ党","m":"おは□□〜今日も寒さヤバいね…ましろねちゃんも体調気を付けて！仕事行ってきます！","t":1187},{"a":"@もみじろう-m7i","m":"おはー□□！炬燵が読めて皆がざわついてて草生えますよw","t":1196},{"a":"@chihiro5h","m":"おは□□〜□","t":1197},{"a":"@高橋伸一-g5j","m":"オープニングの窓の外にいるましろねーずが早く、早く遊びに行こう勉強終わらして","t":1217},{"a":"@飯使いの炉火の昔語","m":"懐かしいねーメンバー飼い主特権真白猫顎下ゴロゴロ権、初めて見たVtuberだったのでメンバー即決だったねー","t":1220},{"a":"@おつかれさま","m":"□□□","t":1225},{"a":"@すいのみ","m":"その格好で出ればいいんじゃない？","t":1230},{"a":"@riri-hikarigamech.5849","m":"□□□","t":1232},{"a":"@96のり茶","m":"□□□","t":1261},{"a":"@ネクサス-p1h","m":"セーターたくさん着こんで、カイロをこれでもかってくらい全身に貼りまくるしかない","t":1261},{"a":"@ドラクラ-f7i","m":"おはろねー","t":1271},{"a":"@K4nN0-かんの","m":"そうだね、友達びっくりしちゃうよね。友達とましろねーずのデートにましろねが付いてきちゃうと","t":1274},{"a":"@シン野うさぎ","m":"おは□□","t":1319},{"a":"@箱推しおでん-灼槍熱々おでん","m":"おは□□","t":1356},{"a":"@ハコニワ-m3j","m":"おはろね～","t":1360},{"a":"@けろにぃ-m9g","m":"あ、無料スパチャ忘れてました！！Σ(´∀｀；)　これでお友達とお茶でもしてくださいね～(*´ω｀)　ちなみに僕は毎日２時半に起きてるので、今日の真白根さんより早いですよ！(*´▽｀*)","t":1374},{"a":"@riri-hikarigamech.5849","m":"□□□□","t":1381},{"a":"@飯使いの炉火の昔語","m":"ないないすぱ","t":1393},{"a":"@ネクサス-p1h","m":"□□□","t":1394},{"a":"@お肉焼き職人ミヤビたん-3968","m":"□□□","t":1397},{"a":"@寒村サムソン","m":"ないすぱ！","t":1400},{"a":"@箱推しおでん-灼槍熱々おでん","m":"□□□","t":1402},{"a":"@もみじろう-m7i","m":"□□□","t":1404},{"a":"@hiroroろめふれ","m":"□□","t":1405},{"a":"@ざらめラスク","m":"ナイスパです〜","t":1409},{"a":"@お肉焼き職人ミヤビたん-3968","m":"寒くていまだにベッドから出れません･･･","t":1419},{"a":"@すずめ_free2","m":"□□□","t":1421},{"a":"@よこは","m":"おは□□です〜〜　雪やばいです！","t":1431},{"a":"@いはらじゅん","m":"□□□□□□","t":1441},{"a":"@96のり茶","m":":tangerine:にゃいすぱ:paw_prints:","t":1458},{"a":"@ネクサス-p1h","m":"来週の前半くらいまでは寒いみたいだね","t":1464},{"a":"@K4nN0-かんの","m":"雪は降ってないけどゴッサムすぎるンゴ","t":1464},{"a":"@高橋伸一-g5j","m":"ましろねーずのみんなでミミィちゃんとお出かけの姿です□めちゃくちゃ可愛い姿です□□□□□□□□□□□□□□□","t":1486},{"a":"@insomniwa4519","m":"おはようございます","t":1490},{"a":"@やさおさん","m":"おはようございます！","t":1491},{"a":"@すずめ_free2","m":"おは□□今日もかわいい聲よろしく","t":1497},{"a":"@やさおさん","m":"ないすぱ","t":1502},{"a":"@漣-さざなみ-L6n","m":"そうか、ましろねが珍しい行動したから雪降ってるのか","t":1506},{"a":"@ざらめラスク","m":"いいなぁ、ウチは起きた直後は９℃だったのに:cold_face:エアコン付けて今は12℃(笑)この状態だと＋３℃でも凄く温かく感じてありがたい:smiling_face_with_smiling_eyes:","t":1518},{"a":"@Marshallマーシャル","m":"おは□□　起きて5秒　こんな早いの！？　リスペクトしかない","t":1520},{"a":"@やさおさん","m":"すごくお早いですね","t":1520},{"a":"@三井ひさし14","m":"ミミィちゃん、おはろね〜(=^・^=)","t":1523},{"a":"@飯使いの炉火の昔語","m":"ずっと来てなかったのにスタンプ増えたねーびっくりしたわ〜いつ来てもこのコメ欄はあったけぇな、それじゃ〜頑張ってねバイトにいってきまーす","t":1527},{"a":"@ゲーム大好きytk","m":"雪がやばい","t":1571},{"a":"@米良智史","m":"おはろね","t":1578},{"a":"@katarukazama","m":"おはろねー","t":1584},{"a":"@飯使いの炉火の昔語","m":"ほう、漢字が読めると、（蟋蟀）これなーんだ","t":1595},{"a":"@かんぱら-t1l","m":"おは□","t":1607},{"a":"@お肉焼き職人ミヤビたん-3968","m":"□□","t":1608},{"a":"@飯使いの炉火の昔語","m":"皆真白猫が答えるまで答えなしなー","t":1619},{"a":"@TAKA-t4w","m":"おはろねぃ！！","t":1643},{"a":"@Still_0","m":"hi","t":1664},{"a":"@riri-hikarigamech.5849","m":"□□□","t":1665},{"a":"@ネクサス-p1h","m":"□□","t":1695},{"a":"@寒村サムソン","m":"ないすぱ！","t":1700},{"a":"@喋る羊羹","m":"おは□□です！","t":1703},{"a":"@hiroroろめふれ","m":"□□","t":1721},{"a":"@つぁん-tan","m":"おはろね〜","t":1725},{"a":"@ゲーム大好きytk","m":"炬燵は前から読めたね","t":1741},{"a":"@マルコにゃん","m":"おはろねー","t":1754},{"a":"@ポケテン","m":"ドヤ□","t":1755},{"a":"@お肉焼き職人ミヤビたん-3968","m":"どやろねかわいい///","t":1760},{"a":"@micみっく39","m":"おは□","t":1761},{"a":"@長月重陽sgr","m":"ｗｗｗ","t":1770},{"a":"@ざらめラスク","m":"この漢字でドヤってるの可愛い(笑)","t":1771},{"a":"@おつかれさま","m":"□□□","t":1772},{"a":"@riri-hikarigamech.5849","m":"□□□□□","t":1790},{"a":"@solaSakurazaki","m":"おはろねですー","t":1810},{"a":"@hiroroろめふれ","m":"そんなドヤ顔してるとましろねーず先生が難しい漢字出してきちゃうぞ□□","t":1812},{"a":"@お肉焼き職人ミヤビたん-3968","m":"お腹は俺が巻き付いて暖めてあげるね","t":1814},{"a":"@HALLOKITTY119","m":"ミミィちゃんおはよう、家のミミィがにゃーんにゃーんないてる","t":1821},{"a":"@長月重陽sgr","m":"きぐるみで良いのでは？ｗｗ","t":1844},{"a":"@野良犬屋敷","m":"仕事中におは□□です:smiling_face_with_smiling_eyes:高評価どうぞ:dog2::dog2:外気温マイナス２℃でめちゃくちゃ寒いです:dog2::dog2:","t":1848},{"a":"@yuuki2200","m":"おは□□□～二度寝するからお先におつ□□□","t":1852},{"a":"@大熊祐輔","m":"おはようございます:sparkles:","t":1855},{"a":"@Myocoru_みょこる","m":"おはろね〜","t":1874},{"a":"@Holy792","m":"今日も雪で外がまっしろねなんだが","t":1883},{"a":"@としみん_t","m":"おはろね","t":1897},{"a":"@アポーーンス","m":"挨拶100人□□□","t":1899},{"a":"@お肉焼き職人ミヤビたん-3968","m":"挨拶100人□□□","t":1913},{"a":"@もみじろう-m7i","m":"挨拶100人□□","t":1920},{"a":"@riri-hikarigamech.5849","m":"100人□□□","t":1920},{"a":"@AHEEBIBOYS","m":"無料！？","t":1928},{"a":"@漣-さざなみ-L6n","m":"100人□□□","t":1930},{"a":"@おつかれさま","m":"100人おめっと〜□□","t":1931},{"a":"@おつかれさま","m":"□□□","t":1936},{"a":"@寒村サムソン","m":"ないすぱ！","t":1939},{"a":"@寒村サムソン","m":"100:clapping_hands:","t":1945},{"a":"@かるかる02","m":"おは□□〜","t":1948},{"a":"@すずめ_free2","m":"挨拶100□□□","t":1951},{"a":"@ふぃぐれむ","m":"今月のちびろねーずのお小遣い（出先なのでアーカイブっておきまー。召喚なしでおけー）たぶんおはろねー","t":1979},{"a":"@yuuki2200","m":"□□□□□□","t":1993},{"a":"@おつかれさま","m":"□□□","t":1994},{"a":"@寒村サムソン","m":"ない赤！！","t":1996},{"a":"@hiroroろめふれ","m":"□□","t":1996},{"a":"@もみじろう-m7i","m":"□□□","t":1999},{"a":"@ざらめラスク","m":"挨拶100:clapping_hands::clapping_hands::clapping_hands:","t":2002},{"a":"@Marshallマーシャル","m":"□□","t":2003},{"a":"@fia_osake","m":"□□□","t":2004},{"a":"@ゲーム大好きytk","m":"ないすぱ","t":2007},{"a":"@お肉焼き職人ミヤビたん-3968","m":"□□□","t":2008},{"a":"@fia_osake","m":"100おは！□□□","t":2014},{"a":"@このはひらひら","m":"おはろねです","t":2026},{"a":"@すずめ_free2","m":"ない赤","t":2035},{"a":"@riri-hikarigamech.5849","m":"□□□□□","t":2039},{"a":"@108_ニニス","m":"おはろね～","t":2045},{"a":"@riri-hikarigamech.5849","m":"ナイス赤スパ！","t":2046},{"a":"@はがね-k139g","m":"おは","t":2047},{"a":"@ヒガンバナ-q4z","m":"□□","t":2054},{"a":"@ふぃぐれむ","m":"早いけど、切腹:kitchen_knife:リスポーン場所置いておきますね？","t":2057},{"a":"@漣-さざなみ-L6n","m":"無料なら投げるしかないね！楽しんできてね！！","t":2059},{"a":"@アポーーンス","m":"□□□","t":2065},{"a":"@飯使いの炉火の昔語","m":"やべぇ","t":2068},{"a":"@ヒガンバナ-q4z","m":"ましろねちゃん、おは□□□□","t":2071},{"a":"@fia_osake","m":"□□□□","t":2071},{"a":"@お肉焼き職人ミヤビたん-3968","m":"□□□","t":2074},{"a":"@すずめ_free2","m":"□□□","t":2075},{"a":"@96のり茶","m":"【真白猫無料スパチャ？活性促進委員会より、お知らせです。】 ましろねーず《愛》の皆様、いつもご利用ありがとうございます。 無料スパチャ？のご利用にあたり、良い子のましろねーず様は、よく検討の上、活用してください。 お財布の紐は、ゆるめないでね。","t":2077},{"a":"@おつかれさま","m":"□□□","t":2078},{"a":"@Marshallマーシャル","m":"□□","t":2083},{"a":"@おつかれさま","m":"□□□","t":2086},{"a":"@fia_osake","m":"□□□","t":2086},{"a":"@すずめ_free2","m":"□□□","t":2089},{"a":"@たまもんn","m":"おはろね…:cold_face:","t":2095},{"a":"@yuuki2200","m":"□□□","t":2097},{"a":"@紅茶妖怪","m":"おは□□","t":2097},{"a":"@お肉焼き職人ミヤビたん-3968","m":"気づいてしまったか･･･よし、逃げろ！","t":2098},{"a":"@Marshallマーシャル","m":"ここで 7:15","t":2098},{"a":"@96のり茶","m":":red_apple:にゃいすぱ:paw_prints:","t":2102},{"a":"@hiroroろめふれ","m":"強風で寒いからズボン3枚履きしてる自分は完璧過ぎて恐怖〜でしか無い:_パニック:","t":2105},{"a":"@漣-さざなみ-L6n","m":"□□□","t":2112},{"a":"@もみじろう-m7i","m":"□□□","t":2116},{"a":"@orcinus.orca-6969","m":"おはろねー:sparkles:…","t":2123},{"a":"@飯使いの炉火の昔語","m":"コオロギでーす","t":2130},{"a":"@寒村サムソン","m":"ないすぱ！","t":2140},{"a":"@おつかれさま","m":"炬燵(じゅうたん)とか読んでなかったかなw","t":2144},{"a":"@寒村サムソン","m":"ナイスパ！","t":2154},{"a":"@紅茶妖怪","m":"どや□","t":2155},{"a":"@ほいみ","m":"□□","t":2166},{"a":"@寒村サムソン","m":"ないすぱ！","t":2171},{"a":"@ゲーム大好きytk","m":"無料なのか","t":2175},{"a":"@寒村サムソン","m":"ナイスパ！","t":2187},{"a":"@紅茶妖怪","m":"お外　白銀の世界","t":2187},{"a":"@もみじろう-m7i","m":"□□□","t":2190},{"a":"@小見敏也","m":"おは□","t":2203},{"a":"@yuuki2200","m":"□□□","t":2204},{"a":"@長月重陽sgr","m":"煙が出た方が温かそう（笑）","t":2205},{"a":"@fia_osake","m":"□□□","t":2205},{"a":"@hiroroろめふれ","m":"□□","t":2206},{"a":"@ほいみ","m":"□□","t":2211},{"a":"@もみじろう-m7i","m":"朝活って挨拶じゃなくて漢字テストの事だった…？","t":2237},{"a":"@Kei_通りすがり","m":"おは□□〜","t":2246},{"a":"@ざらめラスク","m":"ミミィちゃんは雪が降るのを知らせに来る猫妖精さんって事？幻想的〜:sparkles::sparkles:","t":2252},{"a":"@な-z","m":"おはろねー！早起きだねー！","t":2282},{"a":"@Paradox-202X","m":"おはろね:chillwcat:寒い寒すぎる","t":2288},{"a":"@大崎丈人oosaki.taketo","m":"おはろねー。仕事なので挨拶だけで。今日もダジャレをアーカイブで確認しておくね。最近少なめよね？","t":2297},{"a":"@おつかれさま","m":"赤スパすごw","t":2304},{"a":"@96のり茶","m":":cucumber:にゃいすぱ:paw_prints:","t":2339},{"a":"@小見敏也","m":"ナイスパー","t":2375},{"a":"@お肉焼き職人ミヤビたん-3968","m":"今からでも僕を連れて行くってお友達に伝えてくれてもいいのよ？□","t":2422},{"a":"@空猫-t4h","m":"おはろね〜","t":2423},{"a":"@ageha1st","m":"おは□□～","t":2438},{"a":"@ニコちゃと","m":"おはろね～","t":2469},{"a":"@ダジャレめちゃウマ寺たん","m":"ましろねさん、おは□～めっちゃ寒いね","t":2471},{"a":"@おつかれさま","m":"きょうふ〜で寒いよね〜w","t":2478},{"a":"@Marshallマーシャル","m":"さて、お仕事行ってきます！　飲み物は、具だくさん豚汁！　ザシュ！　窓の外で１２５番目にリスポン！","t":2481},{"a":"@Holy792","m":"※みんなのスパチャは全額YouTubeが負担してくれます","t":2495},{"a":"@くまさん-キャンプ好き","m":"おはろね〜","t":2498},{"a":"@Kei_通りすがり","m":"□□□","t":2502},{"a":"@hiroroろめふれ","m":"□□","t":2505},{"a":"@もみじろう-m7i","m":"□□□","t":2513},{"a":"@ダジャレめちゃウマ寺たん","m":"またスパチャ無料きたの？","t":2514},{"a":"@銀猫のナギ","m":"□□","t":2514},{"a":"@fia_osake","m":"ヒートテック暑くなりすぎるから苦手〜:_パニック:","t":2517},{"a":"@ほいみ","m":"□□□","t":2520},{"a":"@fia_osake","m":"□□□","t":2523},{"a":"@おつかれさま","m":"□□□","t":2538},{"a":"@寒村サムソン","m":"ないすぱ！","t":2562},{"a":"@永遠の海UMI","m":"おは□□","t":2588},{"a":"@紅茶妖怪","m":"ましろこんこん","t":2589},{"a":"@Rizuki-リズキ_ID-海外だよ","m":"おはろねー","t":2596},{"a":"@永遠の海UMI","m":"寒すぎるよ","t":2600},{"a":"@ざらめラスク","m":"さて、そろそろ朝食と雪かきあるのでちょっと早くて名残惜しいけどここらでおつろねです〜:sweat_droplets:","t":2642},{"a":"@ほいみ","m":"外□□ーずさんへ…ちゃんと今月分のお酒上納したら入れてもらえますよ","t":2644},{"a":"@orion-オリオン-q9p","m":"おはろね〜！","t":2654},{"a":"@お肉焼き職人ミヤビたん-3968","m":"ましろねまっしろね。頭の中もまっしろね","t":2658},{"a":"@樋-口","m":"おはろね〜お仕事行ってきます","t":2663},{"a":"@夜叉-v5v","m":"おはろね〜仕事行ってきます!アーカイブで見るので早いですが全力のチュキお願いします","t":2675},{"a":"@漣-さざなみ-L6n","m":"彼氏として友達に紹介してくれてもええんやで！","t":2675},{"a":"@すずめ_free2","m":"今日は十二単衣着ていくんだよ","t":2698},{"a":"@Ahamessアーメス","m":"おは□□　外はキンキンに冷えてます","t":2717},{"a":"@おつかれさま","m":"初見さん、ゆっくりしていってね！","t":2722},{"a":"@96のり茶","m":"初見さんいらっしゃいませﾆｬ:paw_prints:","t":2729},{"a":"@寒村サムソン","m":"初見さんいらっしゃい！","t":2729},{"a":"@お肉焼き職人ミヤビたん-3968","m":"初見さんいらっしゃい","t":2734},{"a":"@ageha1st","m":"初見さんいらっしゃい","t":2747},{"a":"@長月重陽sgr","m":"そっと出た瞬間終わったわ・・♪","t":2760},{"a":"@ざらめラスク","m":"初見さんいらっしゃいなのです〜","t":2783},{"a":"@fia_osake","m":"初見さんいらっしゃい〜□","t":2786},{"a":"@ageha1st","m":"久しぶりに2桁時間寝れた～寝坊したけどｗ","t":2791},{"a":"@いもきんとき-j2e","m":"おはろね〜!最近布団を着ながら歩きたい時ある","t":2797},{"a":"@ARIAの猫-w5w","m":"おはろね〜","t":2802},{"a":"@96のり茶","m":"つべ君が先日のがびろね&がびろねーずになったお詫びで、無料にしてくれると言ってたような、言ってないような","t":2813},{"a":"@寒村サムソン","m":"朝から雪かきって大変やなぁ……","t":2829},{"a":"@TheTry-mk","m":"おは□□～","t":2831},{"a":"@しろびあ_via","m":"おはろねー♪","t":2851},{"a":"@fia_osake","m":"1日1本飲まないと貯まっていくストゼロ、、、□","t":2860},{"a":"@tamayaさん株","m":"みーちゃん、おは□□！！外に出されてるましろねーずは、私です！！いつも耳食べるからやな。笑","t":2863},{"a":"@おつかれさま","m":"ちょっとよそ見してる感じがいいねw","t":2865},{"a":"@お肉焼き職人ミヤビたん-3968","m":"あ･･･かわいい･･･ちゅき･･･ｸﾞﾊｯ_:(´ཀ`」 ∠):","t":2872},{"a":"@96のり茶","m":"くっ:double_exclamation_mark:【棒】だけど、これが可愛いのよ□□□","t":2912},{"a":"@お肉焼き職人ミヤビたん-3968","m":"でで、ででででい","t":2932},{"a":"@ほいみ","m":"7:17　ちゅき□","t":2941},{"a":"@y夜桜シオン","m":"おは□□","t":2953},{"a":"@風花銀花雪民","m":"おはようございます","t":2962},{"a":"@fia_osake","m":"てててててて〜い","t":2962},{"a":"@三井ひさし14","m":"ジャージのズボンのひざがすれて穴があきそう…","t":3009},{"a":"@ポテトをシェイクに漬け太郎","m":"おはろね","t":3020},{"a":"@ダジャレめちゃウマ寺たん","m":"ちょっと、車の雪降ろししてきやす","t":3025},{"a":"@ヲタク-k1z","m":"おはろね〜","t":3030},{"a":"@おつかれさま","m":"めっちゃ分かる！に気持ちこもってたな〜w","t":3036},{"a":"@お肉焼き職人ミヤビたん-3968","m":"俺は昨日ついに着る毛布を買いました。あったかいです","t":3041},{"a":"@ネクサス-p1h","m":"寒いと思うから寒いなら、暖かいと思えば...やっぱり寒い！","t":3045},{"a":"@もみじろう-m7i","m":"着る毛布はいいぞー暖かいぞー！","t":3088},{"a":"@96のり茶","m":"まだ、降ってないけど、このあと、降るみたいです","t":3097},{"a":"@お肉焼き職人ミヤビたん-3968","m":"太陽さんさん晴れてますね。なお外気温1℃","t":3110},{"a":"@ageha1st","m":"雪は降ってないけど寒い","t":3117},{"a":"@ヲタク-k1z","m":"降ってないよ～","t":3122},{"a":"@ネクサス-p1h","m":"関東に住んでますが晴れてます。雪がすごいところに太陽分けてあげたい","t":3131},{"a":"@ハク-e8h","m":"おは□□眠過ぎ…","t":3133},{"a":"@北原和之","m":"おはろね","t":3141},{"a":"@じょびえもん","m":"ミミィちゃんおはろね！この色のついたコメント無料で挨拶までしてもらえるってホントですか","t":3146},{"a":"@Turkey_Ver.1.02.1","m":"おはろねやで　やばい今日全然動きたくないかもしれない・・・！","t":3147},{"a":"@お肉焼き職人ミヤビたん-3968","m":"□□□","t":3154},{"a":"@もみじろう-m7i","m":"□□□","t":3159},{"a":"@すずめ_free2","m":"□□□","t":3181},{"a":"@おつかれさま","m":"□□□","t":3186},{"a":"@モカ-o9l","m":"おはろね〜","t":3207},{"a":"@ゲーム大好きytk","m":"普通に雪が降ってるよ","t":3215},{"a":"@00arugo00","m":"おはろね!めっちゃ寒い!ましろねのぶちゅちゅで温めてくれ！","t":3218},{"a":"@卵かけご飯ちー","m":"おはよう〜","t":3228},{"a":"@センメルワイス","m":"おはろね","t":3231},{"a":"@touo4679","m":"ヒーター付きジャケットもあるね","t":3259},{"a":"@Turkey_Ver.1.02.1","m":"外気温が気の持ちような訳あるか原始人じゃないんだから・・・","t":3280},{"a":"@お肉焼き職人ミヤビたん-3968","m":"まぁコートと言い張って着る毛布着て外出ても大丈夫な気もするけどｗ","t":3290},{"a":"@ネクサス-p1h","m":"なんて？","t":3292},{"a":"@寒村サムソン","m":"ないすぱ！","t":3301},{"a":"@kozi7268","m":"おはろねです～ 冷えますね～ 体調大丈夫ですか？","t":3303},{"a":"@南海大好き鉄道チャンネル","m":"初見です","t":3309},{"a":"@お肉焼き職人ミヤビたん-3968","m":"初見さんいらっしゃい","t":3320},{"a":"@ageha1st","m":"初見さんいらっしゃい","t":3322},{"a":"@fia_osake","m":"初見さんいらっしゃい〜","t":3330},{"a":"@もみじろう-m7i","m":"初見さんようこそ！","t":3339},{"a":"@ネクサス-p1h","m":"初見さんいらっしゃい","t":3357},{"a":"@96のり茶","m":"初見さんいらっしゃいませﾆｬ:paw_prints:","t":3358},{"a":"@お肉焼き職人ミヤビたん-3968","m":"無料じゃないよ～が毎回恒例になってきたなｗ","t":3363},{"a":"@fia_osake","m":"綺麗に晴れてると余計に寒く感じるのなんでだろね？","t":3370},{"a":"@ageha1st","m":"ハイテンションのフライパンください","t":3384},{"a":"@長月重陽sgr","m":"地球の軸を23.4度傾けてまっすぐにすれば暖かくなるｗ","t":3414},{"a":"@y夜桜シオン","m":"放射冷却現象…","t":3416},{"a":"@Turkey_Ver.1.02.1","m":"お爺さんは山へ芝刈りへ、お婆さんは川へ洗濯へ、スパチャは3割YouTubeへ行きました。","t":3426},{"a":"@お肉焼き職人ミヤビたん-3968","m":"ぶちゅちゅいただきましたぁああああああ！！！！！！","t":3433},{"a":"@アポーーンス","m":"ぶちゅちゅ助かります。","t":3435},{"a":"@寒村サムソン","m":"初見さんいらっしゃい！","t":3442},{"a":"@高橋伸一-g5j","m":"□初見さん□素敵な思い出 作りましょう□いらっしゃい□","t":3460},{"a":"@96のり茶","m":"ぶちゅちゅ:revolving_hearts:エナジーいただきました:sparkling_heart:","t":3464},{"a":"@ネクサス-p1h","m":"ナイステ","t":3482},{"a":"@cdab6040","m":"電熱ベスト:safety_vest:は外作業必須","t":3492},{"a":"@ほいみ","m":"わぁあったかい","t":3496},{"a":"@天城シナノ","m":"凍えそうな季節に□□は　どーしてダジャレを言うの？","t":3515},{"a":"@天城シナノ","m":"初見さんいらっしゃい","t":3529},{"a":"@96のり茶","m":"ヒーターベスト:safety_vest:は、軽いよ。","t":3541},{"a":"@もみじろう-m7i","m":"着る毛布で外出は防御力と引き換えに代償が大きいかなぁ…w","t":3545},{"a":"@touo4679","m":"モバイルバッテリー必要だけど軽いよ","t":3551},{"a":"@ナナト","m":"おはろねー","t":3574},{"a":"@ナナト","m":"放射冷却ってやつですね","t":3587},{"a":"@クロシファー","m":"おはろね","t":3591},{"a":"@かきみーらorz","m":"カンカン助かる","t":3610},{"a":"@もみじろう-m7i","m":"フライパン助かる！","t":3615},{"a":"@お肉焼き職人ミヤビたん-3968","m":"カンカン助かるぅ！！ひゃっほう！","t":3620},{"a":"@じょびえもん","m":"カンカンきちゃー！","t":3629},{"a":"@fia_osake","m":"ないすカンカン！","t":3651},{"a":"@長月重陽sgr","m":"ｗｗｗ","t":3659},{"a":"@寒村サムソン","m":"ナイスパ！","t":3664},{"a":"@黒猫-r4c","m":"おはろねです:sun:","t":3667},{"a":"@96のり茶","m":"今では、ヒーター手袋、ヒーターネックウォーマー等多数の電熱シリーズ出てるよ","t":3677},{"a":"@ツナかん-3.141","m":"おはろね～","t":3681},{"a":"@Sakura-月夜野-桜","m":"おはろね","t":3689},{"a":"@お肉焼き職人ミヤビたん-3968","m":"またネジ飛んじゃうよ？","t":3692},{"a":"@yamada_shobo_n","m":"おはろね〜","t":3692},{"a":"@Turkey_Ver.1.02.1","m":"電熱ベストはいいぞ・・・","t":3696},{"a":"@ゆいふぁ","m":"おはろね","t":3698},{"a":"@96のり茶","m":"今日も、□□してるね","t":3699},{"a":"@十兵衛-10b","m":"おは□です","t":3701},{"a":"@懐中ユイ","m":"おはろね〜","t":3718},{"a":"@fia_osake","m":"ギギギって鳴ったねw物落ちないようにね","t":3719},{"a":"@すずめ_free2","m":"ましろねは力強いんやからゆっくり動かしや","t":3722},{"a":"@銀猫のナギ","m":"そろそろお仕事行ってきます□今日は風が強く体感温度が近畿地方等で-4度ぐらいの予報ですので外に出る時は十分に暖かい格好でお出かけくださいー□","t":3726},{"a":"@ゆんかーす-v4b","m":"おはろねです","t":3733},{"a":"@サユリンさん","m":"おは□□","t":3742},{"a":"@Turkey_Ver.1.02.1","m":"ましろねさんに放射冷却は脳がヒートアップしてしまう！","t":3779},{"a":"@96のり茶","m":"ヒーターベストは、普通のダウンベストの重さだよ。","t":3790},{"a":"@ステンノー徳光","m":"おはようございます:sun:朝活頑張れ〜高評価ポチ〜、寒いですね～","t":3793},{"a":"@宮さん27","m":"おはようございます:sun:","t":3823},{"a":"@miginokutsusita","m":"おはようございます","t":3829},{"a":"@てめぇこの愛おしい豚骨野郎","m":"萌え声の波動を感じたので来ました。対戦よろしくお願いします。","t":3829},{"a":"@Aaronjael270","m":"Hello people","t":3835},{"a":"@Turkey_Ver.1.02.1","m":"モバイルバッテリーであったかくなる電熱ベストは中に着込んどけば外からわからないからね","t":3836},{"a":"@DAIMYOU-x5b","m":"おはろねー！ネジは秀吉が温めておきました！","t":3877},{"a":"@私が大好きなダイボン","m":"おはろね〜","t":3900},{"a":"@cdab6040","m":"神取忍並みのパワーやろ！","t":3913},{"a":"@お肉焼き職人ミヤビたん-3968","m":"破壊神□□□□だもんね□","t":3918},{"a":"@水瀬いのり-j5j","m":"おはろねー元気ですか？(^o^)","t":3922},{"a":"@ageha1st","m":"破壊神ましろね再び？ｗ","t":3924},{"a":"@長月重陽sgr","m":"脳筋補正","t":3928},{"a":"@テキトウ-s5s","m":"おはろねです、晴れのほうが朝は冷え込むのって例えば最高気温と最低気温の差によって寒いと感じるとか？","t":3928},{"a":"@96のり茶","m":"バッテリー消費量は、3段階のMAXで3時間ほどなのよ","t":3959},{"a":"@すずめ_free2","m":"自分を何羽も持てるんやから力持ちやろ","t":3964},{"a":"@hiroroろめふれ","m":"今日みたいに寒い日こそお出かけ前にワンカップいかがですか□","t":3969},{"a":"@96のり茶","m":"もう、8:36:double_exclamation_mark:早いなぁ","t":4025},{"a":"@天城シナノ","m":"ましろねにWhite breathは通じなかったかぁ□","t":4028},{"a":"@つよし-s9z","m":"おは□□〜","t":4053},{"a":"@私が大好きなダイボン","m":"来てくれてありがとうって言われると嬉しいね","t":4057},{"a":"@けんくん-i6p","m":"おはろねです 昨日誕生日迎えて大谷翔平選手と同じと年齢になりました お仕事行ってきます","t":4086},{"a":"@お肉焼き職人ミヤビたん-3968","m":"花粉かぁ大変だねぇ（完全に他人事）","t":4107},{"a":"@藤井八雲-k4s","m":"おは□□□","t":4108},{"a":"@お肉焼き職人ミヤビたん-3968","m":"高評価200□□","t":4147},{"a":"@96のり茶","m":"高評価200□□□","t":4153},{"a":"@れな1225","m":"おはろねです〜よん□！","t":4165},{"a":"@もみじろう-m7i","m":"高評価200□□□","t":4165},{"a":"@cdab6040","m":"かんどりしのぶ→女子プロレスラーでミスター女子プロレスって呼ばれてます","t":4166},{"a":"@藤井八雲-k4s","m":"□□□","t":4170},{"a":"@寒村サムソン","m":"最近は安全w","t":4174},{"a":"@96のり茶","m":"お誕生日おめでとうございますﾆｬ:paw_prints:","t":4182},{"a":"@ネクサス-p1h","m":"高評価200:clapping_hands::clapping_hands:","t":4186},{"a":"@Turkey_Ver.1.02.1","m":"ましろねさんに逆らうと我々も破壊されるんや・・・","t":4189},{"a":"@お肉焼き職人ミヤビたん-3968","m":"破壊神の力を封印してるってコトぉ！？","t":4197},{"a":"@ageha1st","m":"高評価200:clapping_hands::clapping_hands:","t":4199},{"a":"@姫野きさら","m":"ましろねさん〜おはろね〜","t":4202},{"a":"@ageha1st","m":"誕生日おめでとう:party_popper:","t":4218},{"a":"@いもきんとき-j2e","m":"コップを破壊する絵面想像したら草","t":4220},{"a":"@寒村サムソン","m":"お誕生日おめでとう！:clapping_hands:","t":4220},{"a":"@黒猫-r4c","m":"おめでとぉぉぉぉぉ:party_popper::birthday_cake::wrapped_gift:","t":4221},{"a":"@お肉焼き職人ミヤビたん-3968","m":"お誕生日おめでとうございます！","t":4227},{"a":"@おつかれさま","m":"お誕生日おめでとう〜:birthday_cake::party_popper:□□","t":4232},{"a":"@Kei_通りすがり","m":"お誕生日おめでとうございます:party_popper:","t":4233},{"a":"@ネクサス-p1h","m":"お誕生日おめでとうございます:shortcake:","t":4242},{"a":"@もみじろう-m7i","m":"破壊神真白猫の機嫌を損ねると我々も…","t":4246},{"a":"@96のり茶","m":"破壊神□□□□は、足首出すと、鎮まります","t":4246},{"a":"@もみじろう-m7i","m":"ハッピーバースデー！","t":4258},{"a":"@riri-hikarigamech.5849","m":"高評価200＆誕生日の人□□□□□","t":4262},{"a":"@96のり茶","m":"破壊神□□□□は、足首フェチなんです","t":4277},{"a":"@わんぱくタンパク質ぴくぴくたいわん丸","m":"おはよ～ござます。高評価ぽちっと","t":4287},{"a":"@お肉焼き職人ミヤビたん-3968","m":"ホワイトブレスですｗｗｗ","t":4297},{"a":"@AHEEBIBOYS","m":"ホワイトブレスｷﾀ━━━━(ﾟ∀ﾟ)━━━━!!","t":4306},{"a":"@sora_akikaze","m":"おはようございます:sun_with_face:","t":4308},{"a":"@たーたん-g5y","m":"おはろね〜♪って、8時まで？","t":4313},{"a":"@もみじろう-m7i","m":"真白猫さん…ホワイトブレスや…","t":4319},{"a":"@ageha1st","m":"こんな日はスピリタスの出番よｗ","t":4322},{"a":"@Turkey_Ver.1.02.1","m":"最近Xのポスト見てて改めて思ったけどましろねさんのビジュマジで強いな、ガチ美少女じゃん","t":4340},{"a":"@天城シナノ","m":"White breath（ホワイトブレス）です。さっきの、凍えそうな〜の歌詞","t":4340},{"a":"@たーたん-g5y","m":"え？なに？お酒飲むの？","t":4350},{"a":"@寒村サムソン","m":"ﾋｪｯ","t":4367},{"a":"@diechaaaan","m":"おはろねございまーす","t":4383},{"a":"@お肉焼き職人ミヤビたん-3968","m":"や、やばい！フライパンで殴られる！！","t":4386},{"a":"@けろにぃ-m9g","m":"みみぃスパチャは無料と『ましろねみみぃ公式ガイドブック(偽)』に書いてましたよ？:thinking_face:","t":4395},{"a":"@y夜桜シオン","m":"ましろねフラグ建築株式会社","t":4400},{"a":"@お肉焼き職人ミヤビたん-3968","m":"□□□","t":4405},{"a":"@もみじろう-m7i","m":"□□□","t":4406},{"a":"@DAIMYOU-x5b","m":"最近は安全　はリコールが多かった車みたいですき","t":4406},{"a":"@Turkey_Ver.1.02.1","m":"フライパン一つでましろねーずが15人仕留められるんや・・・","t":4410},{"a":"@96のり茶","m":"□□□","t":4414},{"a":"@れな1225","m":"れなも破壊神ってよく言われます(*´ `*)♡","t":4415},{"a":"@レンチ_DX","m":"おはろね〜","t":4418},{"a":"@ネクサス-p1h","m":"□□□","t":4418},{"a":"@寒村サムソン","m":"ましろねはわるくないよ！みのまわりのものがぜいじゃくすぎるだけだよ！","t":4423},{"a":"@96のり茶","m":"現在、8:43です","t":4431},{"a":"@お肉焼き職人ミヤビたん-3968","m":"ホワイトブリーチって洗剤みたいだなｗｗｗ","t":4452},{"a":"@ぴろ-q9p","m":"おはろね〜！今起きた:grinning_face_with_smiling_eyes:","t":4490},{"a":"@長月重陽sgr","m":"漂白剤だったようなｗ","t":4513},{"a":"@cdab6040","m":"夜の8時までですね！夜遊び=飲みに行く:sake:んですね","t":4520},{"a":"@miginokutsusita","m":"あ、そういえば自分今日誕生日だったwカンカンいただけるんですか","t":4520},{"a":"@お肉焼き職人ミヤビたん-3968","m":"今日飲み物クイズじゃなかった、切腹クイズはやる？","t":4522},{"a":"@fia_osake","m":"T.M.Revolutionは分かる、、、？","t":4523},{"a":"@いもきんとき-j2e","m":"フライパン常に出してるの怖い....","t":4550},{"a":"@寒村サムソン","m":"ないすぱ！","t":4552},{"a":"@黒猫-r4c","m":"そろそろお仕事行ってきますね、お先です、おつろねでしたぁ、行ってきますね","t":4558},{"a":"@お肉焼き職人ミヤビたん-3968","m":"フライパンで遊ぶみぃちゃん可愛いなｗ","t":4561},{"a":"@ぴろ-q9p","m":"フライパン爆弾:bomb:炸裂:squinting_face_with_tongue:","t":4590},{"a":"@riri-hikarigamech.5849","m":"□□□","t":4612},{"a":"@バイオ大好き-k8j","m":"おはろねです♪今日も楽しくいきましょう(^o^)","t":4613},{"a":"@marisacarrasco287","m":"hola hola insectos aquí Vegueta veguetin el principe sayajin","t":4617},{"a":"@いはらじゅん","m":"外寒いよ","t":4629},{"a":"@けろにぃ-m9g","m":"以前散歩中にコンビニでお酒買って飲んだらふらふらで川に落ちそうでしたからやめた方が…","t":4654},{"a":"@ズナイ","m":"おはろね〜","t":4663},{"a":"@モルガナ-s3m","m":"おは炉ね～、真白猫建築ってサバイバルクラフトで家建てる?（違）","t":4667},{"a":"@私が大好きなダイボン","m":"331スパチャが無料じゃないってことはこれなら無料だな","t":4678},{"a":"@長月重陽sgr","m":"フライパン・調理・警鐘・打撃と万能ｗ","t":4684},{"a":"@TKCN_たかちゃん","m":"おはろね〜","t":4686},{"a":"@Kei_通りすがり","m":"□□□","t":4689},{"a":"@すずめ_free2","m":"ましろねーずケーキ食べてる場合違うぞ台パンが当たったらペシャンコやで","t":4689},{"a":"@ネクサス-p1h","m":"誰がどんな力を出しても壊れない商品をお願いします","t":4692},{"a":"@96のり茶","m":"現在の時刻は、7:48です","t":4694},{"a":"@ゲーム大好きytk","m":"ましろねがYOASOBIを歌う？","t":4703},{"a":"@おつかれさま","m":"お誕生日おめでとう〜:birthday_cake::party_popper:□□","t":4707},{"a":"@ageha1st","m":"誕生日おめでとう:party_popper:","t":4714},{"a":"@96のり茶","m":"お誕生日おめでとうございますﾆｬ:paw_prints:","t":4715},{"a":"@お肉焼き職人ミヤビたん-3968","m":"お誕生日おめでとうございます！","t":4718},{"a":"@たーたん-g5y","m":"お誕生日おめでとう〜♪:clapping_hands::clapping_hands::clapping_hands::clapping_hands::clapping_hands:","t":4724},{"a":"@96のり茶","m":"□□□","t":4725},{"a":"@Kei_通りすがり","m":"お誕生日おめでとうございます:party_popper:","t":4730},{"a":"@もみじろう-m7i","m":"ハッピーバースデー□□","t":4732},{"a":"@長月重陽sgr","m":"おめ","t":4737},{"a":"@もみじろう-m7i","m":"□□□","t":4739},{"a":"@Kei_通りすがり","m":"□□□","t":4747},{"a":"@寒村サムソン","m":"お誕生日おめでとう！:clapping_hands:","t":4750},{"a":"@96のり茶","m":"つまり、恒例の延長配信やね","t":4761},{"a":"@ノーバディ-s7r","m":"おはろね","t":4768},{"a":"@ネクサス-p1h","m":"飲み物クイズの別名が切腹クイズだよね","t":4771},{"a":"@ちゃんちゃん焼き-ccy","m":"おはろねございます〜","t":4771},{"a":"@AHEEBIBOYS","m":"おうたたすかる","t":4776},{"a":"@たろやん-n4v","m":"おは□です　挨拶のみで失礼します:sweat_droplets:後でアーカイブ見ますね。高評価しておきました□","t":4776},{"a":"@fia_osake","m":"お誕生日おめでと〜□□□","t":4778},{"a":"@たーたん-g5y","m":"正解〜♪","t":4779},{"a":"@お肉焼き職人ミヤビたん-3968","m":"合ってるよ！次の歌枠で歌ってね！","t":4783},{"a":"@ageha1st","m":"あってるよ","t":4783},{"a":"@寒村サムソン","m":"ないすぱ！ないすぱ！","t":4784},{"a":"@miya-t7t","m":"おは□□です","t":4785},{"a":"@Tsuyosi","m":"おはろね:sun:","t":4789},{"a":"@96のり茶","m":"挨拶200□□□","t":4807},{"a":"@おもちにぃに","m":"□時間なので戻ってきたー！挨拶200□□□","t":4813},{"a":"@おつかれさま","m":"□□□","t":4821},{"a":"@Turkey_Ver.1.02.1","m":"仕事行きます！48番ホットモンエナ！おつろね切腹！","t":4823},{"a":"@Tsuyosi","m":"ないすぱx5","t":4827},{"a":"@もみじろう-m7i","m":"HOT　LIMITは分かるんかい！w","t":4830},{"a":"@ひげぱお","m":"おはろねー","t":4831},{"a":"@ageha1st","m":"挨拶200:clapping_hands::clapping_hands:","t":4835},{"a":"@お肉焼き職人ミヤビたん-3968","m":"挨拶200人□□□8時までにいった！すごい！","t":4868},{"a":"@モルガナ-s3m","m":"実際に出来るから真白猫邸なら頑張ればできる＜家建っちゃう、サバクラ","t":4868},{"a":"@Kei_通りすがり","m":"挨拶200人□□□","t":4870},{"a":"@matatabi-hw1xl","m":"おはろね〜","t":4873},{"a":"@fia_osake","m":"生足！魅惑の□□□□メイド！？□□□","t":4874},{"a":"@Tsuyosi","m":":㊗:高評価200:clapping_hands::clapping_hands::clapping_hands:","t":4884},{"a":"@くろ.かぜ","m":"おはろねー","t":4892},{"a":"@高橋伸一-g5j","m":"はい:clapping_hands:お嬢様お呼びですか？アカペラ 歌っていたので？歌枠の準備ですね:magic_wand:東京ドームの予約ですね","t":4896},{"a":"@寒村サムソン","m":"200:clapping_hands:","t":4898},{"a":"@お肉焼き職人ミヤビたん-3968","m":"□□□","t":4904},{"a":"@Tsuyosi","m":"ないすぱ","t":4904},{"a":"@riri-hikarigamech.5849","m":"□□□","t":4905},{"a":"@寒村サムソン","m":"ないすぱ！","t":4905},{"a":"@もみじろう-m7i","m":"□□□","t":4906},{"a":"@Kei_通りすがり","m":"□□□","t":4909},{"a":"@miginokutsusita","m":"みなさんありがとうございます","t":4913},{"a":"@お肉焼き職人ミヤビたん-3968","m":"□□□","t":4920},{"a":"@Kei_通りすがり","m":"□□□","t":4924},{"a":"@fia_osake","m":"□□□","t":4924},{"a":"@Tsuyosi","m":"ないすぱ","t":4927},{"a":"@寒村サムソン","m":"ナイスパ！","t":4927},{"a":"@もみじろう-m7i","m":"□□□","t":4930},{"a":"@お肉焼き職人ミヤビたん-3968","m":"体感30分もないｗｗ","t":4935},{"a":"@marisacarrasco287","m":"la verdad la verdad la verdad me gustaría saber si hablas español","t":4939},{"a":"@たーたん-g5y","m":"□□□","t":4939},{"a":"@もみじろう-m7i","m":"ナイスパ！","t":4943},{"a":"@トミヲ","m":"おは□□です","t":4960},{"a":"@お肉焼き職人ミヤビたん-3968","m":"延長キターーー！！！","t":4964},{"a":"@96のり茶","m":":cucumber:にゃいすぱ:paw_prints:","t":4965},{"a":"@Seir_","m":"oharone~!","t":4967},{"a":"@牟田口廉也中将","m":"おは□","t":4968},{"a":"@天城シナノ","m":"HOT LIMITはわかるのに冬の代表曲のWhite breathは知らないのかぁwさすがましろね□□","t":4971},{"a":"@riri-hikarigamech.5849","m":"□□□□","t":4986},{"a":"@96のり茶","m":"ほなら、1時間延長はいりま〜す","t":4988},{"a":"@ひげぱお","m":"え？ひょっとして早く終わろうとしてる流れ？","t":4991},{"a":"@長月重陽sgr","m":"毛染めにホワイトブリーチがあったｗ","t":5011},{"a":"@マーサロックプール","m":"おは□□","t":5016},{"a":"@おもちにぃに","m":"□□□","t":5016},{"a":"@たらこ-h7m","m":"おは□□～からの□□","t":5017},{"a":"@たかだるゆうや.YUYATAKADARU","m":"おはようございます。","t":5024},{"a":"@おつかれさま","m":"□□□","t":5039},{"a":"@ひげぱお","m":"東京ドームって30万円くらいで借りれるらしいよ","t":5064},{"a":"@たーたん-g5y","m":"まさかのドームで！？","t":5072},{"a":"@fia_osake","m":"HOTLIMIT ＂コーラを振るだけ＂が懐かしい","t":5084},{"a":"@漣-さざなみ-L6n","m":"東京ドームより武道館のが良かったりする！？","t":5084},{"a":"@fia_osake","m":"□□□","t":5088},{"a":"@テキトウ-s5s","m":"汚嬢様？","t":5088},{"a":"@お肉焼き職人ミヤビたん-3968","m":"□□□","t":5090},{"a":"@モルガナ-s3m","m":"うん、出来るよ。段階踏めば。マルチ対応ならましろね～ず召喚して人海戦術も可能＜真白猫さんでも～","t":5090},{"a":"@おもちにぃに","m":"□□□","t":5092},{"a":"@寒村サムソン","m":"ないぎふ！","t":5092},{"a":"@けろにぃ-m9g","m":"じゃあ、みみぃスパチャ、別名『無料スパチャ』ってことですね？会社着いたんで行ってきます～:sparkles:","t":5092},{"a":"@Kei_通りすがり","m":"□□□","t":5095},{"a":"@たらこ-h7m","m":"□□□","t":5104},{"a":"@お肉焼き職人ミヤビたん-3968","m":"聴けば分かる気もするね～","t":5106},{"a":"@Kei_通りすがり","m":"□□□","t":5109},{"a":"@もみじろう-m7i","m":"初公演が東京ドームなんか…武道館も遠くないなぁw","t":5111},{"a":"@天城シナノ","m":"□□□","t":5112},{"a":"@fia_osake","m":"□□□","t":5115},{"a":"@寒村サムソン","m":"ないすぱ！","t":5115},{"a":"@天城シナノ","m":"□□□","t":5119},{"a":"@ネクサス-p1h","m":"まだ7時前か7時ちょっと過ぎたくらいかと思った","t":5120},{"a":"@ageha1st","m":"□","t":5126},{"a":"@けろにぃ-m9g","m":"くつしたさんおめでとうございます:four_leaf_clover:","t":5126},{"a":"@もみじろう-m7i","m":"□□□□□□","t":5131},{"a":"@ひげぱお","m":"定番だけどイマジナリーフレンド？","t":5137},{"a":"@ほいみ","m":"□","t":5138},{"a":"@96のり茶","m":"ドーム公演からの、武道館公演するのか","t":5144},{"a":"@モルガナ-s3m","m":"ないぎふ～、ないすぱ～","t":5149},{"a":"@おもちにぃに","m":"そうだ:musical_notes:おはろねなんだ:musical_notes:おーきるよーろこーび:musical_notes:たとえ:musical_notes:ましろねぽんが:musical_notes:つーづいーてーもー:musical_notes:","t":5159},{"a":"@riri-hikarigamech.5849","m":"□□□□","t":5160},{"a":"@NEO-lis","m":"おは□ですギフトありがとうございます□","t":5160},{"a":"@お肉焼き職人ミヤビたん-3968","m":"30万ならクラファンすれば余裕で溜まりそうねｗ","t":5160},{"a":"@たらこ-h7m","m":"とっても眠いです。時間に余裕があれば、早朝ガンガンゴンゴンしてくれますと幸いです","t":5161},{"a":"@おつかれさま","m":"□□□","t":5167},{"a":"@お肉焼き職人ミヤビたん-3968","m":"□□□","t":5167},{"a":"@ageha1st","m":"□","t":5169},{"a":"@すずめ_free2","m":"□□□","t":5169},{"a":"@寒村サムソン","m":"ないすぱ！","t":5170},{"a":"@たらこ-h7m","m":"□□□","t":5172},{"a":"@Kei_通りすがり","m":"□□□","t":5174},{"a":"@おつかれさま","m":"□□□","t":5177},{"a":"@モルガナ-s3m","m":"ネットミーム＜コーラふる","t":5188},{"a":"@miginokutsusita","m":"遅れてもいいタイプのおともだち？w","t":5189},{"a":"@ほいみ","m":"□","t":5214},{"a":"@ageha1st","m":"さいたまスーパーアリーナでワンマンライブだって！","t":5225},{"a":"@ほいみ","m":"ましろね目の前に有る飲み物はウインナーコーヒー？","t":5298},{"a":"@ジャガタイ_ko1","m":"おはろね","t":5303},{"a":"@シロソラジマ","m":"おはロネェ～","t":5304},{"a":"@お肉焼き職人ミヤビたん-3968","m":"アンパンマンだねｗ","t":5314},{"a":"@おもちにぃに","m":"アンパンマンですw","t":5314},{"a":"@ageha1st","m":"アンパンマン","t":5319},{"a":"@もみじろう-m7i","m":":clapping_hands::clapping_hands::clapping_hands:","t":5322},{"a":"@y夜桜シオン","m":"アンパンマン","t":5328},{"a":"@モルガナ-s3m","m":"真白猫さんが好きそうなタイトルあるけど聞く?＜サバイバルクラフトゲーム","t":5330},{"a":"@fia_osake","m":"アンパンマンやねw","t":5332},{"a":"@カシューナッツy5k","m":"おは□□□","t":5339},{"a":"@おもちにぃに","m":"元楽曲→原曲　げんきょく","t":5341},{"a":"@漣-さざなみ-L6n","m":"じゃUSJ貸切してましろねLIVEする？？","t":5345},{"a":"@いもきんとき-j2e","m":"アンパンマンだね〜","t":5346},{"a":"@天城シナノ","m":"ア、ア、アンパンマン　やーさしい君は　ってやつやね","t":5376},{"a":"@March649","m":"え、8時まで！？","t":5390},{"a":"@たらこ-h7m","m":"ありがとうございます！おかげで綺麗な雪が降ってきました。っていうか目がとっても覚めました！","t":5407},{"a":"@筋肉競馬ニキ","m":"おはようございます♪","t":5421},{"a":"@おもちにぃに","m":"□□□□□","t":5423},{"a":"@たらこ-h7m","m":"□□□","t":5439},{"a":"@March649","m":"ろねパンマン、お腹すいたよ。ミミがたパン頂戴","t":5453},{"a":"@もみじろう-m7i","m":"隙あらば□","t":5459},{"a":"@mik-3369","m":"おはろね！","t":5463},{"a":"@つにのすけ","m":"おはろねー","t":5466},{"a":"@お肉焼き職人ミヤビたん-3968","m":"よし、きたか・・・ﾁｬｷ","t":5478},{"a":"@天城シナノ","m":"切腹クイズだー！□□","t":5479},{"a":"@私が大好きなダイボン","m":"今から飲み物クイズってことは切腹しながら通勤してる人いたらそれはましろねーずってことか","t":5488},{"a":"@ひげぱお","m":"よし，どぶろくだ！！","t":5493},{"a":"@おもちにぃに","m":"7番の□ック□ェイクのミネスト□ー□味！","t":5494},{"a":"@漣-さざなみ-L6n","m":"儀式クイズだー！！","t":5496},{"a":"@y夜桜シオン","m":"1","t":5498},{"a":"@アポーーンス","m":"カフェオレで","t":5507},{"a":"@お肉焼き職人ミヤビたん-3968","m":"カフェオレぇーーーー！！！！","t":5509},{"a":"@モルガナ-s3m","m":"4","t":5509},{"a":"@あさあすく","m":"1のカフェオレ～","t":5510},{"a":"@もみじろう-m7i","m":"どんなに早起きしても3番の白湯や！（白湯過激派）","t":5510},{"a":"@ageha1st","m":"カフェオレで","t":5513},{"a":"@藤井八雲-k4s","m":"2番の味噌汁で","t":5514},{"a":"@天城シナノ","m":"今日も3番白湯で！（白湯推進協会過激派","t":5515},{"a":"@つにのすけ","m":"1でー","t":5519},{"a":"@おもちにぃに","m":"大穴5番！ホットレモン！","t":5520},{"a":"@March649","m":"1:hot_beverage:。:crossed_swords:準備","t":5520},{"a":"@最弱のアテナ","m":"3かな〜","t":5525},{"a":"@Sakura-月夜野-桜","m":"カフェオレ","t":5526},{"a":"@匿名希望-b9o","m":"おはろね","t":5527},{"a":"@Kei_通りすがり","m":"カフェオレで！","t":5532},{"a":"@ゲーム大好きytk","m":"6の熱燗（出かけるからカフェ行くのにどうせカフェオレ飲んでるだろうけど…）","t":5533},{"a":"@riri-hikarigamech.5849","m":"1のカフェオレで！","t":5534},{"a":"@おつかれさま","m":"2の味噌汁！","t":5535},{"a":"@ゆめのきし","m":"1番カフェオレ","t":5536},{"a":"@たらこ-h7m","m":"222番のプロテイン","t":5538},{"a":"@あまがいそら","m":"39番、雪ミク□","t":5538},{"a":"@漣-さざなみ-L6n","m":"今日はたっぷり時間あったからなぁ、白湯の線は薄そうだな、1番のカフェオレで！","t":5538},{"a":"@私が大好きなダイボン","m":"ココアで","t":5540},{"a":"@いもきんとき-j2e","m":"６.ストゼロ","t":5542},{"a":"@白河_ほたる","m":"おはろね〜、出掛けるので挨拶と高評価のみで失礼しますねぇ～　お先におつろね〜","t":5542},{"a":"@miginokutsusita","m":"８番熱燗","t":5544},{"a":"@ほいみ","m":"ホットレモン！友達とのランチに備えてカフェオレよりカロリー抑えようとしてるとみた","t":5548},{"a":"@寒村サムソン","m":"熱燗！熱燗！","t":5552},{"a":"@なんとか勝-masaru","m":"スッポンの血","t":5552},{"a":"@トミヲ","m":"5ホットレモンで","t":5558},{"a":"@March649","m":"間違えたら、ミュート君の近くにリスポーンして使えなくしてくる","t":5558},{"a":"@漣-さざなみ-L6n","m":"ちなみに1種類！！？？","t":5564},{"a":"@たーたん-g5y","m":"うーん……。5で！！！","t":5565},{"a":"@fia_osake","m":"牛乳買ってきた？初選択！ココア！","t":5570},{"a":"@モルガナ-s3m","m":"濁酒（どぶろく）はおさけだね","t":5581},{"a":"@ひげぱお","m":"−3番の赤マムシドリンクで決まりだね","t":5604},{"a":"@AHEEBIBOYS","m":"カフェオレ！","t":5605},{"a":"@椿ーつばき","m":"おはようございます。","t":5606},{"a":"@空猫-t4h","m":"では仕事行ってきます！今日も最強にかわいい配信頑張って:thumbs_up:","t":5607},{"a":"@私が大好きなダイボン","m":"カフェオレが人気でやばいってことはこれ答え出てるよね？","t":5615},{"a":"@ネクサス-p1h","m":"55番の炭酸が抜けたコカコーラゼロ","t":5627},{"a":"@おもちにぃに","m":"もしかしてだけどー:musical_notes:もしかしてだけどー:musical_notes:飲み物クイズでストゼロ梅を:musical_notes:飲んでいるんじゃないのー！？:musical_notes:","t":5634},{"a":"@たらこ-h7m","m":"あ、すみません6番のきのこの山に変更させてください","t":5634},{"a":"@camouflage666","m":"おはいよう(｡･ω･)ﾉﾞ:sun_with_face::duck:666番の梅昆布茶で！","t":5638},{"a":"@ネクサス-p1h","m":"1番しか答える気がありません","t":5667},{"a":"@椿ーつばき","m":"3番","t":5672},{"a":"@蓬莱狐うどん","m":"おはようございますー　それなら日本酒お冷で","t":5687},{"a":"@m猫です","m":"おはろねです。","t":5688},{"a":"@椿ーつばき","m":"10番豆乳","t":5696},{"a":"@洋二-v3e","m":"ましろねちゃん今日も楽しいね:sparkles:","t":5701},{"a":"@ANY-アニー","m":"おはろねー！","t":5722},{"a":"@鍍金_メッキ_の勇者_082","m":"おはようございます。","t":5735},{"a":"@ANY-アニー","m":"カフェオーレ！","t":5746},{"a":"@forli615","m":"【8時過ぎたので名前を呼ばなくてええですよ】おはようございます。【飲み物はカフェオレ】","t":5746},{"a":"@高橋伸一-g5j","m":"ヤバイです:sparkles:アカペラ 2曲歌ってもらいありがとうございます□味噌汁とホットココアでお願いします□ファイナルアンサー□","t":5756},{"a":"@こうへー-p5y","m":"おはろねー!","t":5759},{"a":"@お肉焼き職人ミヤビたん-3968","m":"よかった・・・今日は3種類じゃなかったか・・・","t":5770},{"a":"@miginokutsusita","m":"プロテインだったかなぁ","t":5778},{"a":"@わんぱくタンパク質ぴくぴくたいわん丸","m":"大穴のハブ酒とみた！","t":5793},{"a":"@昭仁-akito","m":"野菜沢山のミネストローネで","t":5814},{"a":"@アポーーンス","m":"カフェオレ、ロングセラーですしね","t":5826},{"a":"@March649","m":"ろねちゃんは、ポーカーとかババヌキ苦手そう","t":5833},{"a":"@天城シナノ","m":"切腹クイズはカフェオレ選んでおけば7割は正解できるからなぁ□","t":5844},{"a":"@ShinKa331","m":"おは□□〜1番のカフェオレ！","t":5854},{"a":"@モルガナ-s3m","m":"777番饂飩のだし汁で","t":5880},{"a":"@かゆ-umasugiru","m":"わたし","t":5881},{"a":"@昭仁-akito","m":"おはよー","t":5898},{"a":"@joelamador8105","m":"Ohayo :sun:","t":5901},{"a":"@おもちにぃに","m":"飲み物クイズで可笑しなお菓子を食べるなんて罪、犯してないよね:_ぽけぇ::_ぽけぇ:","t":5913},{"a":"@ダジャレめちゃウマ寺たん","m":"555生搾りレモン果汁で","t":5926},{"a":"@たーたん-g5y","m":"というか、カフェ行くの？キミ？","t":5930},{"a":"@モルガナ-s3m","m":"うどんであってる","t":5981},{"a":"@寒村サムソン","m":"饂飩　うどん　よめてえらい:clapping_hands:","t":5995},{"a":"@漣-さざなみ-L6n","m":"饂飩（うどん）で合ってる！！すごい！！","t":5996},{"a":"@ネクサス-p1h","m":"なんで読めた","t":6002},{"a":"@もみじろう-m7i","m":"英語が読めない代わりに漢字が読めてる！:clapping_hands::clapping_hands::clapping_hands:","t":6006},{"a":"@fia_osake","m":"饂飩読めるようになってる！？","t":6015},{"a":"@昭仁-akito","m":"アキトッす","t":6025},{"a":"@おもちにぃに","m":"難読文字は読めて常用漢字は読めない真白猫ミミィちゃんでした","t":6028},{"a":"@March649","m":"むしろ、切腹クイズは、外すほうがある意味正解。正解しても、切腹するけど","t":6043},{"a":"@お肉焼き職人ミヤビたん-3968","m":"お！いい表情！いいね！:camera_with_flash::camera_with_flash::camera_with_flash::camera_with_flash:","t":6068},{"a":"@百舌鳥_モズ","m":"おは□□","t":6073},{"a":"@椿ーつばき","m":"メモメモメモレモン","t":6079},{"a":"@March649","m":"ごめん、最初「真白猫」でましろね、読めなかった。Vtuberさんの名前難しい","t":6088},{"a":"@セブンスターj9j","m":"おはよーございます","t":6090},{"a":"@96のり茶","m":"1番のカフェオレだ。ﾁｬｷﾘ:kitchen_knife:","t":6098},{"a":"@天城シナノ","m":"我々は正解したい訳じゃ無いんだ・・・白湯を推進したいだけなんだ！（白湯推進協会過激派","t":6105},{"a":"@ネクサス-p1h","m":"真白猫さんが固まっても隣のましろねーずが動いてくれてるから大丈夫","t":6113},{"a":"@ウッでやんす高橋_33-4","m":"おはろね～！！","t":6122},{"a":"@お肉焼き職人ミヤビたん-3968","m":"漢字が読める・・・？嘘だろ！？","t":6139},{"a":"@たーたん-g5y","m":"なのになんで、カフェオレで動揺したの？w","t":6143},{"a":"@アポーーンス","m":"固まってるうちに、今です←判断がだいぶ遅い","t":6167},{"a":"@gamakitoigak","m":"おはろね～","t":6173},{"a":"@たらこ-h7m","m":"□□□","t":6177},{"a":"@寒村サムソン","m":"ないすぱ！","t":6178},{"a":"@おもちにぃに","m":"□□□","t":6183},{"a":"@つか子__2kacco","m":"おはろね～白湯でお願いします！","t":6184},{"a":"@Kei_通りすがり","m":"□□□","t":6184},{"a":"@ShinKa331","m":"□□□","t":6188},{"a":"@ネクサス-p1h","m":"猫を「ね」って読むことそんなにないもんなあ","t":6191},{"a":"@riri-hikarigamech.5849","m":"仕事行かないとだからここで失礼するね:_ごめん::_ごめん::_ごめん:　おつ□□～～～～～","t":6198},{"a":"@ゆめのきし","m":"30分ほど、買い物に行ってきますね、おつ□□、今日も楽しかったよ","t":6199},{"a":"@モルガナ-s3m","m":"御免、変換が楽だからましろねこッて打ってる<真白猫","t":6201},{"a":"@おもちにぃに","m":"そろそろ仕事出発します。ホットレモンでFAしておつ□だ！","t":6208},{"a":"@jajiAZ","m":"おは□□漢字が読めるって？今日は氷柱あったよ","t":6215},{"a":"@ュュ-o4n","m":":fireworks:おはよ〜:sparkler:かわいい","t":6222},{"a":"@ダジャレめちゃウマ寺たん","m":"漢字が読めるなんて、今日は良い感じだね","t":6237},{"a":"@March649","m":"Obs君の機嫌でラグあるらしいからな","t":6245},{"a":"@昭仁-akito","m":"アイリッシュ珈琲","t":6258},{"a":"@寒村サムソン","m":"でも「人海戦術」の読みに自信のないましろねさんであった","t":6263},{"a":"@fia_osake","m":"油断してると9時になりそうだw","t":6263},{"a":"@椿ーつばき","m":"ピーチティー","t":6265},{"a":"@たらこ-h7m","m":"□□□","t":6273},{"a":"@アポーーンス","m":"□□□","t":6274},{"a":"@ShinKa331","m":"□□□","t":6275},{"a":"@天城シナノ","m":"□□□","t":6276},{"a":"@Kei_通りすがり","m":"□□□","t":6276},{"a":"@寒村サムソン","m":"ないすぱ！","t":6278},{"a":"@おつかれさま","m":"□□□","t":6278},{"a":"@もみじろう-m7i","m":"□□□","t":6279},{"a":"@長月重陽sgr","m":"ムスカ「読める。読めるぞ！」","t":6284},{"a":"@jajiAZ","m":"□□□","t":6286},{"a":"@百舌鳥_モズ","m":"7番の茉莉花茶でお願いします","t":6290},{"a":"@March649","m":"名前難し漢字なのに、普通の漢字読めないろねちゃん、可愛い","t":6292},{"a":"@ageha1st","m":"ましろねことましろねで悩んだけど、語感てきにましろねだとｗ","t":6300},{"a":"@たーたん-g5y","m":"『真白猫(ましろね)』普通は、絶対に読めない。","t":6313},{"a":"@ageha1st","m":"つらら","t":6321},{"a":"@jajiAZ","m":"つらら","t":6324},{"a":"@長月重陽sgr","m":"つらら","t":6325},{"a":"@寒村サムソン","m":"自分の名前やねんからそこは辞書登録しときなさいよ……","t":6326},{"a":"@百舌鳥_モズ","m":"iPhoneだとましろねで真白猫を一発変換できるぞ","t":6326},{"a":"@fia_osake","m":"そんなあなたに辞書登録","t":6331},{"a":"@March649","m":"ないスパ","t":6332},{"a":"@長月重陽sgr","m":"ｗｗｗｗｗ","t":6332},{"a":"@ShinKa331","m":"つららは読めなかったか□","t":6339},{"a":"@たーたん-g5y","m":"つらら、では？","t":6339},{"a":"@もみじろう-m7i","m":"真白猫さん…つららやぞ…漢字も読めんやんけ！","t":6343},{"a":"@お肉焼き職人ミヤビたん-3968","m":"俺はもう「ましろ」まで打てば予測変換に真白猫出てくるから楽ちん","t":6347},{"a":"@長月重陽sgr","m":"つらら一斉突っ込みｗ","t":6350},{"a":"@March649","m":"氷柱つらら","t":6351},{"a":"@つか子__2kacco","m":"氷柱？読めへんけどつららのことかな？","t":6354},{"a":"@お肉焼き職人ミヤビたん-3968","m":"フラグ回収早いなぁ","t":6357},{"a":"@椿ーつばき","m":"鬼滅かな?","t":6361},{"a":"@天城シナノ","m":"ミミィ・アズナブル「読める！私にも漢字が読める！」（直後に被弾","t":6366},{"a":"@miginokutsusita","m":"白湯はパイタンとも読むねぇ","t":6379},{"a":"@たーたん-g5y","m":"おい、話変えたぞ？この猫？","t":6382},{"a":"@山本優幸まさゆき48","m":"おはろね 私は限定クラフトボス悪魔の魅惑ダブルショコララテ飲んでる美味し","t":6396},{"a":"@長月重陽sgr","m":"注意）アーカイブに残りますｗ","t":6402},{"a":"@March649","m":"氷柱の真白猫ミミィ","t":6422},{"a":"@昭仁-akito","m":"ミロ飲んでます","t":6424},{"a":"@お肉焼き職人ミヤビたん-3968","m":"ファイナルニャンサー！！！","t":6437},{"a":"@寒村サムソン","m":"氷柱はちょっとだけ難読やからしかたないね……","t":6445},{"a":"@ネクサス-p1h","m":"FA","t":6448},{"a":"@jajiAZ","m":"1で","t":6448},{"a":"@fia_osake","m":"ＦＡ！","t":6449},{"a":"@ShinKa331","m":"ふぁいなるあんさー□","t":6452},{"a":"@March649","m":":crossed_swords:や:kitchen_knife:の準備","t":6455},{"a":"@天城シナノ","m":"ファイナルカウントダウン","t":6457},{"a":"@モルガナ-s3m","m":"色が白いから氷属性はあってるな","t":6485},{"a":"@fia_osake","m":"どるるるるるるる〜","t":6492},{"a":"@おつかれさま","m":"うわぁぁぁあ！","t":6493},{"a":"@お肉焼き職人ミヤビたん-3968","m":"やったぁぁぁぁぁぁっぁ！！！！","t":6498},{"a":"@ageha1st","m":"当たったー","t":6498},{"a":"@March649","m":"正解だったけど、切腹","t":6500},{"a":"@たらこ-h7m","m":"やったああ、きのこの山であってた！","t":6501},{"a":"@ほいみ","m":"うわぁぁぁーーー!切腹！","t":6506},{"a":"@藤井八雲-k4s","m":"まぁ、そうだよね:grinning_face_with_sweat:","t":6509},{"a":"@Kei_通りすがり","m":"当たった！ｻﾞｼｭｯ:kitchen_knife:","t":6509},{"a":"@ShinKa331","m":"当たった〜□","t":6511},{"a":"@もみじろう-m7i","m":"カフェオレにもお湯使ってるから実質白湯やね！（過激派","t":6512},{"a":"@jajiAZ","m":"切腹回避！","t":6513},{"a":"@ネクサス-p1h","m":"いぇーい久々に当たったー:raising_hands:","t":6515},{"a":"@つか子__2kacco","m":"あぁ切腹が確定しました","t":6515},{"a":"@山本優幸まさゆき48","m":"安定のカフェオレ","t":6515},{"a":"@長月重陽sgr","m":"真白猫の賢さが０．１上がった！","t":6518},{"a":"@miginokutsusita","m":"一瞬映った0なんだ","t":6520},{"a":"@ゲーム大好きytk","m":"外れたので切腹","t":6521},{"a":"@たーたん-g5y","m":"そりゃあそうだよね！？だって、動揺してたし！！！(カフェオレ)","t":6522},{"a":"@fia_osake","m":"ぐわー！！！切腹！！！","t":6522},{"a":"@天城シナノ","m":"やっぱり7割カフェオレ正解じゃないですかー！ｻﾞｼｭ","t":6523},{"a":"@最弱のアテナ","m":"おーん外したー","t":6526},{"a":"@96のり茶","m":"よし、今日も、カフェオレでした。当たるとやはり、嬉しいﾆｬ:paw_prints:ｻﾞｼｭｻﾞｼｭ:kitchen_knife:","t":6530},{"a":"@お肉焼き職人ミヤビたん-3968","m":"正解して嬉しいので切腹するね♪ｻﾞｼｭｯｻﾞｼｭｯ","t":6533},{"a":"@あまがいそら","m":"雪溶かしたカフェオレだよね？□","t":6547},{"a":"@March649","m":"リスポーン。ミュート君おさえておきます","t":6548},{"a":"@ゲーム大好きytk","m":"友達と出かける時はましろね、カフェオレだよね","t":6549},{"a":"@ageha1st","m":"正解したから照れ顔ハート目ガチ恋距離ください","t":6569},{"a":"@寒村サムソン","m":"ｻﾞｼｭｯ　ほなワイは仕事いってくるで　ましろねもお友達と精一杯遊んでくるんやでー","t":6571},{"a":"@天城シナノ","m":"ましろねーずのみんなへ、切腹はよく訓練されたましろねーずが勝手にやってるよ！生暖かい目でエンタメとして見てね！ましろねーず切腹同好会より","t":6577},{"a":"@椿ーつばき","m":"ドッーカーン","t":6592},{"a":"@96のり茶","m":"リスポーン先は、ミミィちゃんのフードの中に","t":6604},{"a":"@ShinKa331","m":"可愛い□□□","t":6626},{"a":"@たらこ-h7m","m":"□□□","t":6629},{"a":"@March649","m":"可愛い:cat2:","t":6630},{"a":"@牟田口廉也中将","m":"ほな:✋🏿:ワイは仕事行ってくるで:woman_biking:ガチ恋距離のミミィ最高やで～","t":6633},{"a":"@Kei_通りすがり","m":"□□□","t":6638},{"a":"@たーたん-g5y","m":"かわゆい","t":6641},{"a":"@おつかれさま","m":"□□□","t":6645},{"a":"@AHEEBIBOYS","m":"ありがとね動いてくれて:_ごめん:","t":6662},{"a":"@たらこ-h7m","m":"ガチ恋距離のあいだコメントが完全に止まっていたんだ□□□","t":6662},{"a":"@山本優幸まさゆき48","m":"ほっぺ突っつきたくなる","t":6666},{"a":"@AHEEBIBOYS","m":"□□□","t":6668},{"a":"@March649","m":"ないステ","t":6669},{"a":"@お肉焼き職人ミヤビたん-3968","m":"可愛すぎて心臓打ち抜かれました。切腹するまでもなかったですね。ｸﾞﾌｫｱ","t":6672},{"a":"@たーたん-g5y","m":"え？なにをした？","t":6676},{"a":"@たらこ-h7m","m":"□□□","t":6680},{"a":"@fia_osake","m":"□□□□","t":6681},{"a":"@kekeの毛っ毛0v0","m":"朝風呂からのおは□","t":6683},{"a":"@ShinKa331","m":"□□□","t":6685},{"a":"@kekeの毛っ毛0v0","m":"□□","t":6686},{"a":"@私が大好きなダイボン","m":"通勤中に切腹したら自宅にリスポーンしてしまった","t":6688},{"a":"@星咲さくら","m":"ましろねちゃん:shelterin:おはろね〜は！ましろねーずが前のケーキ狙ってる！？","t":6692},{"a":"@お肉焼き職人ミヤビたん-3968","m":"ぶつけた？大丈夫？","t":6705},{"a":"@おつかれさま","m":"□□□","t":6709},{"a":"@天城シナノ","m":"□□□","t":6710},{"a":"@長月重陽sgr","m":"ついでに介錯も必要ですか？ｗｗｗ","t":6715},{"a":"@メント_mento","m":"おはろね　今日は久々の休みで配信遅れました。切腹します！！","t":6749},{"a":"@高橋伸一-g5j","m":"飲み物クイズ外れました:_怒ってる:","t":6749},{"a":"@たらこ-h7m","m":"あいさつ250パチパチ□□","t":6767},{"a":"@ShinKa331","m":"250□□□","t":6775},{"a":"@山本優幸まさゆき48","m":"夜勤明けで切腹したらリスポーン地点職場になりそうで怖い","t":6780},{"a":"@星咲さくら","m":"ましろねちゃんのマウスカーソルだっけ？あれめっちゃかわいいかった\"(∩>ω<∩)\"","t":6800},{"a":"@fia_osake","m":"250おは！□□□","t":6800},{"a":"@お肉焼き職人ミヤビたん-3968","m":"挨拶250人□□□","t":6801},{"a":"@ネクサス-p1h","m":"250□□","t":6801},{"a":"@いもきんとき-j2e","m":"新参なのでよくわからないけどとりあえず切腹しとく ｻﾞｼｭｯ","t":6807},{"a":"@おつかれさま","m":"250人おめっと〜□□","t":6808},{"a":"@あまがいそら","m":"□□□","t":6811},{"a":"@たーたん-g5y","m":"□□□","t":6812},{"a":"@Kei_通りすがり","m":"挨拶250人□□□","t":6814},{"a":"@ほいみ","m":"□□□","t":6815},{"a":"@天城シナノ","m":"□□□","t":6822},{"a":"@アポーーンス","m":"挨拶250人□□□","t":6823},{"a":"@お肉焼き職人ミヤビたん-3968","m":"マウスカーソル早速使ってるよ！！かわいい！","t":6843},{"a":"@メント_mento","m":"新米おいしいよね","t":6845},{"a":"@百舌鳥_モズ","m":"新参→しんざん　しんまい→新米","t":6849},{"a":"@れいむニャー","m":"□□□","t":6850},{"a":"@ageha1st","m":"しんざんだね","t":6851},{"a":"@ダジャレめちゃウマ寺たん","m":"配信終わったら、いつもの場所で会おうね。待ってるよ","t":6853},{"a":"@モモリキ","m":"おはろね:sun:","t":6854},{"a":"@kekeの毛っ毛0v0","m":"入会特典？？プランはどこのプランかしら？","t":6856},{"a":"@長月重陽sgr","m":"しんざんｗｗｗ","t":6860},{"a":"@ゴン太-m9q","m":"おはおつ□□今年２回目の出社日で萎えてる□ザシュッ","t":6862},{"a":"@星咲さくら","m":"挨拶250人突破おめでとう(((o(*ﾟ▽ﾟ*)o)))","t":6866},{"a":"@fia_osake","m":"マウスカーソルめっちゃ可愛いけどＰＣ無いんだよな:_ごめん::_ごめん::_ごめん:","t":6874},{"a":"@アポーーンス","m":"任意ですが、希望する方が多い代物（シロモノ）です","t":6886},{"a":"@天城シナノ","m":"切腹は任意で好きなましろねーずが勝手にやってるから無理にしなくても大丈夫だよ、ましろねーず切腹同好会より","t":6896},{"a":"@山本優幸まさゆき48","m":"介錯人(かいしゃくにん)はましろね","t":6900},{"a":"@kekeの毛っ毛0v0","m":"なるほど……□","t":6914},{"a":"@AHEEBIBOYS","m":"やった□","t":6950},{"a":"@たーたん-g5y","m":"たしかに、切腹いつからはじまった？","t":6973},{"a":"@ざらめラスク","m":"ただいまです〜、まだやっててくれた〜:loudly_crying_face:","t":6976},{"a":"@長月重陽sgr","m":"介錯は、切腹した人が苦しまないように止めを刺す役ｗ","t":6984},{"a":"@山本優幸まさゆき48","m":"おつろね","t":6985},{"a":"@あまがいそら","m":"おつ□□","t":6987},{"a":"@最弱のアテナ","m":"おつ□","t":6987},{"a":"@ネクサス-p1h","m":"おつろねー、お友達 と楽しんできてねー","t":6988},{"a":"@藤井八雲-k4s","m":"おつ□□でしたー","t":6990},{"a":"@アポーーンス","m":"おつ□です","t":6993},{"a":"@百舌鳥_モズ","m":"おつ□□□","t":6993},{"a":"@メント_mento","m":"おつろねー","t":6993},{"a":"@ひげぱお","m":"おつろねー","t":6996},{"a":"@chihiro5h","m":"おつろね〜","t":6997},{"a":"@モルガナ-s3m","m":"おつろね～","t":6997},{"a":"@かんぱら-t1l","m":"おつ□","t":6998},{"a":"@ざらめラスク","m":"ギリギリだったのね:grinning_face_with_sweat:おつろね出来て嬉しい〜","t":7001},{"a":"@ShinKa331","m":"おつ□□","t":7003},{"a":"@ANY-アニー","m":"おつろねー！","t":7005},{"a":"@あさあすく","m":"おつ□□でした～□","t":7007},{"a":"@Kei_通りすがり","m":"おつ□□〜","t":7007},{"a":"@クマがクマった球磨熊ーくまくまー","m":"おつ□□〜:bear:ﾉｼ","t":7008},{"a":"@星咲さくら","m":"ましろねちゃん、いつも朝活お疲れ様(((o(*ﾟ▽ﾟ*)o)))おつろね〜:shelterin::chillwcat:","t":7008},{"a":"@たらこ-h7m","m":"おつ□□～ちょっとしか居られませんでしたが、とっても楽しかったです□","t":7010},{"a":"@ageha1st","m":"おつ□□～","t":7011},{"a":"@つか子__2kacco","m":"おつろね～お出かけ楽しんでね～","t":7012},{"a":"@くろ.かぜ","m":"おつろねー","t":7014},{"a":"@たーたん-g5y","m":"おつろね〜♪絶対無事故(ぜったいむじこ)で！！","t":7017},{"a":"@お肉焼き職人ミヤビたん-3968","m":"おつ□□！！短い時間だったけど楽しかったよ！！今日も仕事前に元気チャージできました！！！お出かけ気を付けてね！！","t":7018},{"a":"@kekeの毛っ毛0v0","m":"おつ□おつ□","t":7022},{"a":"@たらこ-h7m","m":"金曜日ですね","t":7023},{"a":"@ざらめラスク","m":"金曜日","t":7023},{"a":"@モルガナ-s3m","m":"明日は金曜日","t":7024},{"a":"@AHEEBIBOYS","m":"仕事行って来ます□きょうはお友達と楽しんで来てね〜□","t":7024},{"a":"@ダジャレめちゃウマ寺たん","m":"おつ□～道が凍って大渋滞。ましろねさんもカフェ楽しんできてね","t":7029},{"a":"@アポーーンス","m":"え、金曜日、あと一日、、","t":7037},{"a":"@Futaba0305","m":"おはろね〜","t":7037},{"a":"@AHEEBIBOYS","m":"おつ□□□","t":7038},{"a":"@もみじろう-m7i","m":"おつ□□今日も見事な□でした！真白猫さんも楽しんで来てねー□","t":7042},{"a":"@fia_osake","m":"おつ□〜いってらっしゃい！","t":7042},{"a":"@なんとか勝-masaru","m":"おつ□□□","t":7055},{"a":"@いもきんとき-j2e","m":"おつろねでした〜","t":7058},{"a":"@山本優幸まさゆき48","m":"明日もハラキリデーか","t":7061},{"a":"@よこは","m":"おつ□□です〜　おでかけ楽しんで〜お気をつけて〜","t":7063},{"a":"@96のり茶","m":"おつろねでしたﾆｬ:paw_prints:","t":7063},{"a":"@micみっく39","m":"おつ□□でした〜","t":7109},{"a":"@たーたん-g5y","m":"安定のコメント迷子wかわいいわぁ〜♪","t":7110},{"a":"@如月ユウト","m":"おは□□！…って、終わりだったか…おつ□□です！","t":7111},{"a":"@March649","m":"おつろね","t":7113},{"a":"@高橋伸一-g5j","m":"ミミィちゃん□最後にチビろねちゃん出せるようだったら□抱っこ お願いします:_ごめん:おつ□□:_ごめん:","t":7115},{"a":"@夜叉-v5v","m":"おつろね〜休憩時間、タイミングばっちりだ！いつもコメント読んでくれてありがとね","t":7127},{"a":"@山本優幸まさゆき48","m":"ましろねのどこだ？どこだ？がディグダの鳴き声に似てるって気がついた","t":7139},{"a":"@長月重陽sgr","m":"おつろね","t":7141},{"a":"@suzumiya322","m":"ただいま、おつろね間に合った！","t":7144},{"a":"@ほいみ","m":"おつ□□","t":7151},{"a":"@天城シナノ","m":"おつ□□です〜寒いからあったかくして行くんだよ〜お土産はドーナツでいいよ□□□","t":7175},{"a":"@銀輪766","m":"おつろねでした、楽しんで来てねー","t":7224},{"a":"@mole-s8r","m":"おは＆おつろね～","t":7268},{"a":"@Paradox-202X","m":"おつろね〜","t":7269},{"a":"@水瀬いのり-j5j","m":"おつろねー","t":7304},{"a":"@ざらめラスク","m":"おぉ〜","t":7325},{"a":"@おつかれさま","m":"おつ□〜","t":7325},{"a":"@お肉焼き職人ミヤビたん-3968","m":"お腹の音聞こえた！！と思ったら自分のお腹の音だったｗｗ","t":7326},{"a":"@suzumiya322","m":"キャーちびろねちゃんキター(ﾟ∀ﾟ 三 ﾟ∀ﾟ)","t":7328},{"a":"@ざらめラスク","m":"ちびろねカワイイ〜:two_hearts:","t":7337},{"a":"@fia_osake","m":"チビろねちゃん□","t":7343},{"a":"@お肉焼き職人ミヤビたん-3968","m":"ぎゃああああああ！？ﾁﾋﾞﾛﾈﾁｬﾝ！！！","t":7351},{"a":"@matagu405","m":"おはようございます","t":7355},{"a":"@ShinKa331","m":"チビ□ちゃん！！おはよ～□","t":7358},{"a":"@水瀬いのり-j5j","m":"今夜は配信ありますか？","t":7364},{"a":"@ざらめラスク","m":"アニメのディグダですね(笑)","t":7372},{"a":"@ふぃぐれむ","m":"着いた…時差３０分…？おつ□","t":7372},{"a":"@お肉焼き職人ミヤビたん-3968","m":"ディグダは思ったｗｗｗ","t":7375},{"a":"@たーたん-g5y","m":"ちびろね〜〜〜♪","t":7376},{"a":"@ほいみ","m":"限界チビろねオタクが騒いじゃうw","t":7387},{"a":"@漣-さざなみ-L6n","m":"おつろね！","t":7414},{"a":"@高橋伸一-g5j","m":"ミミィちゃんありがとうございます:smiling_face_with_smiling_eyes:チビろねちゃんとても喜んでます","t":7417},{"a":"@ShinKa331","m":"□□□","t":7431},{"a":"@ふぃぐれむ","m":"ちびろねーず出勤代（？）","t":7432},{"a":"@ShinKa331","m":"□□□","t":7439},{"a":"@fia_osake","m":"□□□□","t":7441},{"a":"@たらこ-h7m","m":"□□□","t":7443},{"a":"@pikamenzero919","m":"おはよう。。。","t":7444},{"a":"@ERO-GACHAPIN","m":"おはろねー","t":7451},{"a":"@ゆんかーす-v4b","m":"おつろねです。行ってらっしゃいませ。","t":7451},{"a":"@わわんこそば","m":"おはろね＆おつろね～","t":7458},{"a":"@suzumiya322","m":"□□□","t":7462},{"a":"@さと中_あせるな危険","m":"おは□□！二度寝してめちゃくちゃ寝坊した、、、今日、来客あるから急がないと切腹する羽目になる笑","t":7470},{"a":"@会社休み荘843号室","m":"おはようございます","t":7476},{"a":"@FPrimusUnicron","m":":hand-pink-waving::hand-pink-waving:","t":7486},{"a":"@さと中_あせるな危険","m":"おつろね！","t":7508},{"a":"@おつかれさま","m":"□□□","t":7527},{"a":"@ざらめラスク","m":"ナイスパです〜","t":7539},{"a":"@mole-s8r","m":"□□□","t":7577},{"a":"@Seir_","m":"oturone~","t":7586},{"a":"@どこにでもいるよっちゃん","m":"おつろね〜","t":7587},{"a":"@ShinKa331","m":"ばいば～い□□□","t":7589},{"a":"@mole-s8r","m":"ばいば～い□","t":7593},{"a":"@お肉焼き職人ミヤビたん-3968","m":"ばいば～い！！","t":7594},{"a":"@suzumiya322","m":"ばいばいー","t":7595},{"a":"@ひげぱお","m":"ばいばーい","t":7596},{"a":"@Kei_通りすがり","m":"ばいばーい","t":7597},{"a":"@天城シナノ","m":"□□□","t":7602},{"a":"@ageha1st","m":"ばいば～い　□た□～","t":7604},{"a":"@夜叉-v5v","m":"ばいばーい","t":7606},{"a":"@Paradox-202X","m":":hand-pink-waving::hand-pink-waving::hand-pink-waving:","t":7612},{"a":"@fia_osake","m":"ばいばーい","t":7615},{"a":"@いもきんとき-j2e","m":"ばいばい","t":7618},{"a":"@96のり茶","m":"ばいばいﾆｬ:paw_prints:","t":7618},{"a":"@mashi_rone","m":"配信来てくれてありがとう～□いっぱいお話出来て楽しかったよ～！:sparkles:いつもありがとう！今日も無理なくのんびり頑張ろうね□おつ□□□","t":7634},{"a":"@96のり茶","m":"行ってらっしゃ〜い","t":7640},{"a":"@よこは","m":"ばいば〜い","t":7643},{"a":"@高橋伸一-g5j","m":"□ミミィちゃん□バイバイ□","t":7653}]