[{"a":"@椎名音","m":"□こん□〜仕事中□","t":0},{"a":"@まっつん-UR","m":"□□□","t":0},{"a":"@高橋伸一-g5j","m":"ミミィちゃん□□□□□ころ□□□□","t":0},{"a":"@寒村サムソン","m":"|･ω･`)待機","t":0},{"a":"@つばさ箱","m":"こん□□ごめんなさい～夕飯の片づけしたらまた戻ってきます:persevering_face:","t":0},{"a":"@pastel5737","m":"□□□","t":0},{"a":"@かきみーらorz","m":"□□","t":0},{"a":"@fia_osake","m":"□□□","t":0},{"a":"@Kei_通りすがり","m":"□□□","t":0},{"a":"@extえくすと","m":"□□□","t":0},{"a":"@つよし-s9z","m":"□□□","t":0},{"a":"@クマがクマった球磨熊ーくまくまー","m":"□□□","t":0},{"a":"@ハクスタ","m":"□□","t":0},{"a":"@ShinKa331","m":"□□□","t":2},{"a":"@mosamosa-magic","m":"□□□","t":6},{"a":"@どこにでもいるよっちゃん","m":"□□□","t":28},{"a":"@桜イヨツバVTのサブ垢","m":"こんばんは","t":34},{"a":"@おつかれさま","m":"待機〜□","t":43},{"a":"@ふぇいと-n5s","m":"□□□","t":45},{"a":"@lippy_youtube","m":"珍しく□□","t":66},{"a":"@かず-b5i","m":"□□□","t":79},{"a":"@風呂カラ親父44","m":"□□□","t":86},{"a":"@ミサラギの助","m":"□□□","t":122},{"a":"@高橋伸一-g5j","m":"□□□□","t":146},{"a":"@おつかれさま","m":"□！？","t":151},{"a":"@lippy_youtube","m":"□？？","t":157},{"a":"@hiroroろめふれ","m":"□","t":161},{"a":"@extえくすと","m":"□□","t":169},{"a":"@cdab6040","m":"固定コメミスした？","t":169},{"a":"@ぺとらんち","m":"こん□□□","t":172},{"a":"@ryuzakisimms1019竜崎","m":"□□□□","t":173},{"a":"@どこにでもいるよっちゃん","m":"こん□","t":175},{"a":"@extえくすと","m":"こん□□","t":178},{"a":"@Kei_通りすがり","m":"こん□〜","t":179},{"a":"@おつかれさま","m":"こん□〜","t":180},{"a":"@Samidare_Itsuki","m":"こんろねです","t":181},{"a":"@mosamosa-magic","m":"こん□","t":183},{"a":"@hiroroろめふれ","m":"こん□□□","t":184},{"a":"@かきみーらorz","m":"こん□□□","t":184},{"a":"@ryuzakisimms1019竜崎","m":"こん□□","t":186},{"a":"@つよし-s9z","m":"こん□","t":188},{"a":"@クマがクマった球磨熊ーくまくまー","m":"こん□〜","t":192},{"a":"@えぴ-e5h","m":"こん□□□□","t":193},{"a":"@まささま-r2d","m":"こん□","t":193},{"a":"@OA_オーエー","m":"こんろねーーー","t":194},{"a":"@fia_osake","m":"こん□〜！","t":194},{"a":"@ミサラギの助","m":"こん□□なんか見逃した？w","t":195},{"a":"@かず-b5i","m":"こん□","t":195},{"a":"@npc5733","m":"□□□","t":197},{"a":"@Cinis-Eques_Lynx_SX","m":"こん□","t":197},{"a":"@暖簾のれんカツカレー","m":"こん□～","t":198},{"a":"@lippy_youtube","m":"こん□□","t":198},{"a":"@十兵衛-10b","m":"こん□","t":199},{"a":"@まっつん-UR","m":"こん□□","t":199},{"a":"@AyaOhkura","m":"こん□です","t":200},{"a":"@高橋伸一-g5j","m":"□□□□","t":200},{"a":"@pastel5737","m":"こん□□□","t":203},{"a":"@寒村サムソン","m":"ましろねの霊圧が一瞬消えた……？","t":204},{"a":"@ナナシ名前","m":"こんろねー　ましろねさーん","t":207},{"a":"@ブラックギャリア","m":"こんろね","t":208},{"a":"@寒村サムソン","m":"こんろね","t":211},{"a":"@ShinKa331","m":"こん□□","t":217},{"a":"@アポーーンス","m":"こんろねです","t":228},{"a":"@かたっち-h8j","m":"こん□□しんたのか？","t":228},{"a":"@Cinis-Eques_Lynx_SX","m":"やっぱり完璧で究極な□","t":232},{"a":"@ふぇいと-n5s","m":"こん□！！描いてくれたイラスト早速アイコンにしたよー□","t":238},{"a":"@ネクサス-p1h","m":"こんろね〜。","t":238},{"a":"@まささま-r2d","m":"□の子だからだね□","t":240},{"a":"@おつかれさま","m":"のんびり喋ろうと思ってるので良かったくらいまでは読めたw","t":242},{"a":"@ブラックギャリア","m":"それは、ましろねが□だからだよ(笑)","t":246},{"a":"@mashi_rone","m":"配信へ遊びに来てくれてありがとう:cherry_blossom:のんびりお話しようと思っているので、良かったら気軽に話しかけてもらえると嬉しいです:glowing_star:","t":250},{"a":"@fia_osake","m":"開幕□wいつも通りやな□","t":259},{"a":"@クマがクマった球磨熊ーくまくまー","m":"記念配信□お披露目w","t":262},{"a":"@しろぬき_srnk","m":"こん□","t":265},{"a":"@suzumiya322","m":"こん□〜","t":268},{"a":"@バッサー-s9q","m":"こんろね〜","t":269},{"a":"@ぺとらんち","m":"１０か月おめでとー！□□□","t":271},{"a":"@るーんowo","m":"こん□□","t":275},{"a":"@かたっち-h8j","m":"□あるのは真白猫さんらしい","t":276},{"a":"@Cinis-Eques_Lynx_SX","m":"テンプレ作っておいて、コピペするのが賢いのでは？！","t":281},{"a":"@ミサラギの助","m":"□から始まり、□で〆る、、、流石や:thumbs_up:","t":282},{"a":"@hiroroろめふれ","m":"□□","t":284},{"a":"@かきみーらorz","m":"記念配信でも□は欠かせない","t":286},{"a":"@ryuzakisimms1019竜崎","m":"ましろねミミィちゃん可愛い□","t":286},{"a":"@寒村サムソン","m":"思っているので良かった(断定)","t":290},{"a":"@extえくすと","m":"10ヵ月おめだー□□","t":291},{"a":"@まささま-r2d","m":"常に□は固定□","t":291},{"a":"@3106osamu","m":"こん□","t":301},{"a":"@Abby_アビー","m":"こん□","t":302},{"a":"@ryuzakisimms1019竜崎","m":"はーい","t":305},{"a":"@おつかれさま","m":"10か月おめっと〜□□","t":306},{"a":"@寒村サムソン","m":"10ヶ月おめ:clapping_hands:","t":310},{"a":"@ミサラギの助","m":"10ヶ月おめでとう！□□□","t":314},{"a":"@オオスカシバ-y2w","m":"おめこん□~","t":315},{"a":"@fia_osake","m":"10ヶ月おめでとーだ！□□□","t":318},{"a":"@satopika214","m":"こん□！デビュー10ヶ月おめやで！□□□","t":319},{"a":"@ryuzakisimms1019竜崎","m":"たのしい","t":329},{"a":"@かたっち-h8j","m":"真白猫さん10ヶ月おめでとう□□□","t":334},{"a":"@つよし-s9z","m":"デビュー10ヶ月おめでとう〜","t":335},{"a":"@まささま-r2d","m":"１０ヶ月おめ！□□□","t":339},{"a":"@cdab6040","m":"こん□","t":341},{"a":"@風呂カラ親父44","m":"こんばんは〜(^^)ﾉｼ","t":346},{"a":"@ハクスタ","m":"こんろね～ 10ヶ月おめ～:㊗:","t":371},{"a":"@ryuzakisimms1019竜崎","m":"そのいい","t":377},{"a":"@まっつん-UR","m":"デビュー10ヶ月おめでとおおおお:party_popper::party_popper::party_popper:","t":384},{"a":"@ネクサス-p1h","m":"１０ヶ月おめでとうございます〜","t":406},{"a":"@たろやん-n4v","m":"こん□です。10ヶ月おめでとうございます□□□","t":418},{"a":"@Yutanpo510","m":"こんろねー 10ヶ月記念と聞いたぞ！おめでとー","t":424},{"a":"@高橋伸一-g5j","m":"ミミィちゃん:sparkles:デビュー10ヵ月、おめでとう:wrapped_gift::birthday_cake::party_popper:ございます:four_leaf_clover:今後もいろいろよろしくお願いいたします□大好きだよ:sparkles:","t":427},{"a":"@ryuzakisimms1019竜崎","m":"ないめん","t":428},{"a":"@まっつん-UR","m":"高評価＆共有も完了ですぜ:thumbs_up:","t":437},{"a":"@spherer7129","m":"こん□","t":462},{"a":"@ブラックギャリア","m":"おめでとう","t":467},{"a":"@アレン艾倫","m":"晚上好□□□□","t":504},{"a":"@touo4679","m":"こんばんわ","t":506},{"a":"@touo4679","m":"□","t":518},{"a":"@TonKatu","m":"こん□","t":535},{"a":"@るーんowo","m":"10ヶ月おめでとう□","t":548},{"a":"@forli615","m":"こんばんは。デビュー10ヶ月おめでとうございます。","t":561},{"a":"@野良犬屋敷","m":"夜勤休憩中にこん□です:sparkles:１０ヶ月ということでおめでとうございます:smiling_face_with_smiling_eyes::smiling_face:帰宅後アーカイブで視聴させていただきますね、高評価共有置いておきます。配信楽しんで下さい:smiling_face_with_smiling_eyes::smiling_face:","t":574},{"a":"@小野淳-j3b","m":"こん□デビュー10ヶ月おめでとうございます:party_popper::party_popper::party_popper:","t":580},{"a":"@ハクスタ","m":"今日も雑談がメインかな？","t":626},{"a":"@so2_k1","m":"こんばんは〜","t":632},{"a":"@みーや-miya","m":"こんろね〜","t":636},{"a":"@雨ネコ-p4z","m":"こん□□","t":646},{"a":"@カイゼルGK","m":"こんばんわ","t":655},{"a":"@hiroroろめふれ","m":"デビュー10ヶ月□□□□□","t":658},{"a":"@スーパーノヴァブルーベリー朧月DI","m":"こん□","t":659},{"a":"@まささま-r2d","m":"お酒飲むの？ちょうどお酒あるんだけど","t":688},{"a":"@extえくすと","m":"夜配信で朝活レベルの長さはヤバいからな","t":711},{"a":"@アグ-f4j","m":"仕事終わりからのこんろねええ","t":712},{"a":"@shisonoha","m":"こん□","t":724},{"a":"@Cinis-Eques_Lynx_SX","m":"深呼吸しとく？","t":729},{"a":"@おつかれさま","m":"朝活なんじゃないかと錯覚(さっかく)するw","t":738},{"a":"@まっつん-UR","m":"夜の雑談配信初参加かもｗ","t":741},{"a":"@えぴ-e5h","m":"ここだけの話お披露目予想したらタイトルでネタバレされたのは内緒","t":771},{"a":"@shisonoha","m":"泡盛(あわもり)っすか～:sparkles:","t":774},{"a":"@クマがクマった球磨熊ーくまくまー","m":"夜から朝活配信！？","t":775},{"a":"@まささま-r2d","m":"□□□","t":779},{"a":"@寒村サムソン","m":"新背景:clapping_hands:","t":779},{"a":"@高橋伸一-g5j","m":"□□□□□","t":781},{"a":"@spherer7129","m":"開けるの失敗したワンカップどうしたの？","t":781},{"a":"@まっつん-UR","m":"お酒□□□□","t":782},{"a":"@おつかれさま","m":"おおっ！？新しいお部屋！？","t":783},{"a":"@ハクスタ","m":"祝杯！！","t":783},{"a":"@hiroroろめふれ","m":"□□□□□","t":786},{"a":"@hk-ハック","m":"こん□！あと2ヶ月で1周年だね！頑張れ！","t":786},{"a":"@たろやん-n4v","m":"□□□□","t":787},{"a":"@ブラックギャリア","m":"新たなポンを用意しております(笑)","t":790},{"a":"@fia_osake","m":"お酒〜□□□","t":791},{"a":"@えぴ-e5h","m":"ワンカップですか！？","t":795},{"a":"@lippy_youtube","m":"熱燗用意偉い□□□","t":797},{"a":"@3106osamu","m":"酒瓶は・・・ないか","t":801},{"a":"@Kei_通りすがり","m":"□□□□","t":802},{"a":"@おつかれさま","m":"ふぅううん！！","t":803},{"a":"@extえくすと","m":"気合い入れてるんか□□","t":805},{"a":"@npc5733","m":"□□□","t":807},{"a":"@つよし-s9z","m":"□□□","t":807},{"a":"@中野三玖-y3x","m":"眠いけど…来たよ､10ヶ月おめでとう:blue_heart:","t":811},{"a":"@アグ-f4j","m":"酒あるのか、帰りながら酒かってこよ","t":811},{"a":"@ミサラギの助","m":"さすがましろね、、、ブレねぇな:thumbs_up:","t":816},{"a":"@shisonoha","m":"ふー の圧が□","t":817},{"a":"@アグ-f4j","m":"あ、10ヶ月おめでーーとです","t":839},{"a":"@まささま-r2d","m":"あと２ヶ月で１周年□","t":839},{"a":"@HAL_KRPS-13","m":"こんろねさまです","t":845},{"a":"@オオスカシバ-y2w","m":"ふー圧たすかる","t":846},{"a":"@fia_osake","m":"新次元の□もお披露目してくれることでしょう:thumbs_up:","t":850},{"a":"@猫やなぎ_999","m":"こん□10カ月おめでとう:party_popper:","t":859},{"a":"@おつかれさま","m":"新居いいじゃないの〜","t":872},{"a":"@高橋伸一-g5j","m":"ノンアルビールでいいですか□","t":890},{"a":"@ブラックギャリア","m":"ワンカップ","t":893},{"a":"@hiroroろめふれ","m":"ワンカップ□","t":894},{"a":"@spherer7129","m":"重大発表あり　とかで濁すところを□","t":898},{"a":"@藤井八雲-k4s","m":"こんろね。10ヶ月おめでとうございます:㊗:","t":902},{"a":"@fia_osake","m":"ワンカップキター！□","t":911},{"a":"@おつかれさま","m":"□□□","t":914},{"a":"@Kei_通りすがり","m":"□□□□","t":914},{"a":"@ShinKa331","m":"□□□□","t":915},{"a":"@高橋伸一-g5j","m":"□□□□□","t":915},{"a":"@hiroroろめふれ","m":"□□□□□","t":916},{"a":"@shisonoha","m":":clapping_hands::clapping_hands::clapping_hands::clapping_hands::clapping_hands:","t":916},{"a":"@ミサラギの助","m":"ワンカップリベンジ□□□","t":916},{"a":"@OA_オーエー","m":":clapping_hands::clapping_hands::clapping_hands::clapping_hands:","t":917},{"a":"@spherer7129","m":"開いた！","t":917},{"a":"@オオスカシバ-y2w","m":"□□□□□","t":918},{"a":"@8みちゅ_こめっ粉","m":"□□□□□□□□","t":919},{"a":"@まっつん-UR","m":"あいとるｗ","t":920},{"a":"@fia_osake","m":"□□□","t":920},{"a":"@たろやん-n4v","m":"□□□□","t":920},{"a":"@えぴ-e5h","m":"救われたのね...","t":921},{"a":"@アポーーンス","m":"ついにワンカップ君が救われる時が来たんですね:clapping_hands::clapping_hands::clapping_hands:","t":922},{"a":"@spherer7129","m":"□□□","t":922},{"a":"@lippy_youtube","m":"□□□□□□","t":922},{"a":"@OA_オーエー","m":"ワンカップきたー","t":922},{"a":"@まささま-r2d","m":"□□□草","t":923},{"a":"@藤井八雲-k4s","m":"おおーー！ワンカップ空いとる:clapping_hands::clapping_hands::clapping_hands:","t":924},{"a":"@つよし-s9z","m":"□□□","t":927},{"a":"@みーや-miya","m":":clapping_hands::clapping_hands::clapping_hands::clapping_hands::clapping_hands::clapping_hands::clapping_hands::clapping_hands:","t":928},{"a":"@まっつん-UR","m":"□□□□","t":931},{"a":"@extえくすと","m":"□□□","t":931},{"a":"@3106osamu","m":"な、ナンダッテー　□□□□","t":931},{"a":"@暖簾のれんカツカレー","m":"□□□□","t":938},{"a":"@クマがクマった球磨熊ーくまくまー","m":"ワンカップ、無事に開放されたw","t":942},{"a":"@ハクスタ","m":"むしろこっちがメインだった？w","t":942},{"a":"@HAL_KRPS-13","m":"□□□","t":944},{"a":"@shisonoha","m":"熟練のおじいちゃんたちが上手にあけれるやつな","t":947},{"a":"@extえくすと","m":"前に失敗してたのか□","t":947},{"a":"@hiroroろめふれ","m":"必死で開けれて偉い□","t":956},{"a":"@おつかれさま","m":"スプーンGJ","t":959},{"a":"@バニラ-c6l","m":"こんろねー:waving_hand::waving_hand:","t":961},{"a":"@fia_osake","m":"スプーンなら危なくもなかったろうし良かった〜□","t":963},{"a":"@Bettchi005","m":"こんろねです～","t":969},{"a":"@ふぇいと-n5s","m":"□□□","t":972},{"a":"@中野三玖-y3x","m":"偶然だね…私も晩御飯にコロナビール飲んだよ､ミミィさんの誕生日は何月何日かな","t":977},{"a":"@えぴ-e5h","m":"ワンカップ開封祝い","t":979},{"a":"@おつかれさま","m":"ないすぱ！","t":985},{"a":"@寒村サムソン","m":"ワンカップ(ましろねの被害者)ついに開けられておめ:clapping_hands:","t":986},{"a":"@shisonoha","m":"スプーンで行く可愛さ□□","t":988},{"a":"@hiroroろめふれ","m":"ナイスパ","t":988},{"a":"@まささま-r2d","m":"飲んべえやなあ□","t":991},{"a":"@寒村サムソン","m":"ないすぱ！","t":993},{"a":"@中野三玖-y3x","m":"ワンカップ開封おめでとう:green_heart:","t":997},{"a":"@まっつん-UR","m":"ないすぱｗ","t":998},{"a":"@HAL_KRPS-13","m":"ないすぱー","t":998},{"a":"@fia_osake","m":"ないすぱ〜！","t":998},{"a":"@たろやん-n4v","m":"ないすぱ","t":998},{"a":"@たかちゃん兼キャロちゃ","m":"Onecupは草(10ヶ月おめ！","t":999},{"a":"@Kei_通りすがり","m":"ナイスパ！","t":1002},{"a":"@ふぃぐれむ","m":"ワンカップ開封（？）記念おめろねー","t":1007},{"a":"@forli615","m":"ワンカップを開けられる(知恵 or 腕力)を得た","t":1009},{"a":"@おつかれさま","m":"ないすぱ！","t":1013},{"a":"@hiroroろめふれ","m":"ナイスパ","t":1016},{"a":"@spherer7129","m":"重大発表（ワンカップ開いた）","t":1018},{"a":"@fia_osake","m":"ないすぱ〜","t":1021},{"a":"@extえくすと","m":"ないすぱ","t":1021},{"a":"@えぴ-e5h","m":"ないすぱ！","t":1021},{"a":"@まささま-r2d","m":"んないすぱ～□","t":1023},{"a":"@shisonoha","m":"ないすぱ","t":1027},{"a":"@ブラックギャリア","m":"んないすぱ","t":1030},{"a":"@たかちゃん兼キャロちゃ","m":"あ、こん□□□","t":1035},{"a":"@しょぼん-l4c","m":"□□","t":1036},{"a":"@Kei_通りすがり","m":"ナイスパ！","t":1036},{"a":"@suzumiya322","m":"ナイスパ","t":1037},{"a":"@寒村サムソン","m":"ないすぱ！","t":1041},{"a":"@まささま-r2d","m":"安全かどうかは・・・□","t":1041},{"a":"@8みちゅ_こめっ粉","m":"んにゃいすぱぁ！","t":1042},{"a":"@fia_osake","m":"ワンカップ買って帰るか〜","t":1043},{"a":"@かたっち-h8j","m":"真白猫さんワンカップで10ヶ月の祝杯良いのよね:sparkles:","t":1051},{"a":"@青柳春","m":"こんろねー","t":1053},{"a":"@ポン助-q9i","m":"こんろね〜□真白猫さん酒臭いぞ","t":1061},{"a":"@たろやん-n4v","m":"ないすぱ","t":1062},{"a":"@takasa_shin","m":"こんろね□","t":1066},{"a":"@くまさん-キャンプ好き","m":"こん□□","t":1074},{"a":"@ミサラギの助","m":"ないすぱ！","t":1087},{"a":"@HAL_KRPS-13","m":"ビール嫌いやけどドミニクトレットのせいで首掴んで飲みたくなる","t":1106},{"a":"@ブラックギャリア","m":"□","t":1112},{"a":"@ミサラギの助","m":"今から夜勤やから、空気吸っとくw","t":1116},{"a":"@extえくすと","m":"麦茶で乾杯やー","t":1117},{"a":"@takasa_shin","m":"今、会社の飲み会終わって変ええてきたら、配信してた！","t":1119},{"a":"@まささま-r2d","m":"こうやって酒臭くなるんだな～□","t":1120},{"a":"@forli615","m":"今は 自作梅シロップに炭酸入れたのがあります","t":1121},{"a":"@えぴ-e5h","m":"白いコーラあります乾杯いけます","t":1121},{"a":"@mosamosa-magic","m":"今日は酸素で！","t":1124},{"a":"@オオスカシバ-y2w","m":"空気の用意ありです！","t":1126},{"a":"@しょぼん-l4c","m":"酔いろね～","t":1127},{"a":"@おつかれさま","m":"濃いめのレモンサワーで！","t":1128},{"a":"@おつかれさま","m":"ないすぱ！","t":1135},{"a":"@ミサラギの助","m":"ないすぱ！","t":1135},{"a":"@アポーーンス","m":"酸素を吸う　は結構おもろかったです","t":1136},{"a":"@高橋伸一-g5j","m":"□□□□□","t":1136},{"a":"@寒村サムソン","m":"ないすぱ！","t":1140},{"a":"@まささま-r2d","m":"んないすぱ～□","t":1140},{"a":"@ブラックギャリア","m":"んないすぱ","t":1141},{"a":"@中野三玖-y3x","m":"後でワンカップ飲んでみようかな","t":1147},{"a":"@まっつん-UR","m":"水で乾杯するか:clinking_beer_mugs:","t":1149},{"a":"@たろやん-n4v","m":"ないすぱ","t":1149},{"a":"@Kei_通りすがり","m":"ナイスパ！","t":1153},{"a":"@まっつん-UR","m":"ないすぱぁ","t":1157},{"a":"@HAL_KRPS-13","m":"ないすぱー","t":1160},{"a":"@たかちゃん兼キャロちゃ","m":"ブラックニッカで","t":1172},{"a":"@Cinis-Eques_Lynx_SX","m":"開けるとき、ちょっとこぼした？","t":1185},{"a":"@かたっち-h8j","m":"真白猫さんKP準備オーケーよ","t":1192},{"a":"@Natu7214","m":"こんろね！ましろねさん酒飲み？","t":1196},{"a":"@ハクスタ","m":"今お風呂入ってるからひとまず風呂桶で□しとくかあ","t":1199},{"a":"@HAL_KRPS-13","m":"お風呂やから湯船で","t":1218},{"a":"@shisonoha","m":"私はコーヒーだな:hot_beverage:","t":1226},{"a":"@Cinis-Eques_Lynx_SX","m":"なぜバレないと（ていうか、実際そうでもこぼしてないっていえばいいのにｗ","t":1238},{"a":"@たろやん-n4v","m":"お茶:teacup_without_handle:で","t":1242},{"a":"@こうさ-c8l","m":"こんろね□□","t":1249},{"a":"@こうさ-c8l","m":"間に合った！！！！","t":1256},{"a":"@tama11kichi16","m":"こんばんわー！","t":1266},{"a":"@8みちゅ_こめっ粉","m":"そういえば開いた時「ワンカップ開きました〜□」だったのですっかり忘れてました。こん□ですぅ！！","t":1272},{"a":"@えぴ-e5h","m":"記念が多いw（いいこと）","t":1275},{"a":"@まささま-r2d","m":"ましろね部長の話長いんだよなあ□","t":1276},{"a":"@ポン助-q9i","m":"乾杯〜","t":1278},{"a":"@かたっち-h8j","m":"真白猫さんKP:clinking_beer_mugs::clinking_beer_mugs:□:party_popper::㊗::㊗:","t":1279},{"a":"@suzumiya322","m":":clinking_beer_mugs:","t":1280},{"a":"@Holy792","m":"こん□","t":1281},{"a":"@高橋伸一-g5j","m":"ノンアルコールビールで□□□□□","t":1281},{"a":"@おつかれさま","m":"□□□","t":1282},{"a":"@たかちゃん兼キャロちゃ","m":"□□□","t":1282},{"a":"@fia_osake","m":"電車だから酸素で","t":1282},{"a":"@8みちゅ_こめっ粉","m":"□□□","t":1282},{"a":"@Cinis-Eques_Lynx_SX","m":"かんぱーい（こぼさないでね","t":1283},{"a":"@Kei_通りすがり","m":"□□□","t":1283},{"a":"@まっつん-UR","m":"□:clinking_beer_mugs:乾杯:clinking_beer_mugs:□","t":1284},{"a":"@十兵衛-10b","m":"□","t":1284},{"a":"@mosamosa-magic","m":"□□□□","t":1284},{"a":"@hiroroろめふれ","m":"□□□","t":1284},{"a":"@extえくすと","m":"□□□","t":1284},{"a":"@HAL_KRPS-13","m":"kp","t":1285},{"a":"@オオスカシバ-y2w","m":"これからもよろです~□","t":1286},{"a":"@クマがクマった球磨熊ーくまくまー","m":"伊右衛門だけど□","t":1286},{"a":"@3106osamu","m":"□□□□","t":1286},{"a":"@まささま-r2d","m":"□□□□□","t":1287},{"a":"@lippy_youtube","m":"□□□□□","t":1287},{"a":"@たろやん-n4v","m":"□□□","t":1287},{"a":"@spherer7129","m":"□□□","t":1288},{"a":"@shisonoha","m":"KP","t":1290},{"a":"@ミサラギの助","m":"□□□","t":1290},{"a":"@つよし-s9z","m":"□〜","t":1290},{"a":"@えぴ-e5h","m":"□□□","t":1290},{"a":"@寒村サムソン","m":"カンパーイ！:clinking_beer_mugs:","t":1291},{"a":"@AyaOhkura","m":"□□□","t":1293},{"a":"@藤井八雲-k4s","m":"ほろよいで一緒に　カンパーイ！","t":1295},{"a":"@こうさ-c8l","m":"10ヶ月おめでとう□□□□","t":1296},{"a":"@高橋伸一-g5j","m":"□□□□□","t":1297},{"a":"@猫やなぎ_999","m":"□□□","t":1298},{"a":"@ShinKa331","m":"□□□","t":1298},{"a":"@ふぇいと-n5s","m":"１０か月おめでとー□□□","t":1299},{"a":"@アポーーンス","m":"KP","t":1301},{"a":"@Holy792","m":"ワンカップ開いたんだね","t":1301},{"a":"@暖簾のれんカツカレー","m":"□□□□","t":1302},{"a":"@fia_osake","m":"□□□□□","t":1303},{"a":"@オオスカシバ-y2w","m":"wao","t":1305},{"a":"@HAL_KRPS-13","m":"じゃっばーん","t":1307},{"a":"@3106osamu","m":"よし　乾杯したし帰るか(こら)","t":1307},{"a":"@ハクスタ","m":"□:bathtub:","t":1308},{"a":"@おつかれさま","m":":clapping_hands::clapping_hands::clapping_hands::clapping_hands::clapping_hands:","t":1308},{"a":"@ブラックギャリア","m":"□","t":1309},{"a":"@shisonoha","m":"□□□□","t":1314},{"a":"@寒村サムソン","m":"これでましろねもオッサンの仲間入りやな！","t":1315},{"a":"@Holy792","m":"□","t":1318},{"a":"@まささま-r2d","m":"初ワンカップどうよ？□","t":1318},{"a":"@猫やなぎ_999","m":"おっさん用だからねえ","t":1321},{"a":"@HAL_KRPS-13","m":"ワンカップ強そう","t":1324},{"a":"@chinigi_sagiri","m":"おはようございます","t":1325},{"a":"@バニラ-c6l","m":"KP","t":1331},{"a":"@fia_osake","m":"なかなか飲み慣れないとクる味かもね〜","t":1332},{"a":"@高橋伸一-g5j","m":"おめでとうございます","t":1333},{"a":"@まっつん-UR","m":"山田錦のほうがおいしい？","t":1334},{"a":"@OA_オーエー","m":"真白猫おじさん","t":1342},{"a":"@ポン助-q9i","m":"酒カスの世界へようこそ","t":1345},{"a":"@空白kuuhaku","m":"こんろね～","t":1366},{"a":"@ハクスタ","m":"ワンカップ電車でのんでるおじさんがいるイメージやなー","t":1371},{"a":"@shisonoha","m":"ふぅぅぅぅ～の圧よw","t":1382},{"a":"@中野三玖-y3x","m":"何で…お酒飲んでも酔わない私､ちなみに好きなお酒は…｢金麦｣と｢ヱビス｣､お酒美味しい？","t":1384},{"a":"@おつかれさま","m":"日本酒は大体15度くらいじゃないかな","t":1390},{"a":"@まささま-r2d","m":"結構あるやん□","t":1399},{"a":"@ハクスタ","m":"15:exclamation_question_mark:","t":1404},{"a":"@extえくすと","m":"結構度数あるんやね","t":1404},{"a":"@空白kuuhaku","m":"ワンカップってオッサンが飲んでるイメージなんだよな～","t":1406},{"a":"@HAL_KRPS-13","m":"まあまあ強い","t":1407},{"a":"@クマがクマった球磨熊ーくまくまー","m":"ちびちび飲まないとw","t":1409},{"a":"@かたっち-h8j","m":"真白猫さんお酒だけですか？おつまみ準備とか無いのか？","t":1427},{"a":"@fia_osake","m":"そこそこ度数高いけど小さいやつだし大丈夫でしょう","t":1427},{"a":"@extえくすと","m":"ワンカップってそんなに開けるの大変やっけ","t":1431},{"a":"@hiroroろめふれ","m":"呑みやすいでしょ□ワンカップ","t":1432},{"a":"@しょぼん-l4c","m":"今日はウイスキーロックﾃﾞｱﾘﾏｽ","t":1434},{"a":"@おつかれさま","m":"日本酒とワインは一緒くらいの度数だと思う","t":1438},{"a":"@8みちゅ_こめっ粉","m":"#配信背景お披露目 #10ヶ月記念 #ワンカップあきましたぁ□☜音","t":1440},{"a":"@空白kuuhaku","m":"10カッ月おめでとうございます:party_popper:","t":1442},{"a":"@しょぼん-l4c","m":"ワイの家の70のおじいがいつもワンカップ呑んでる","t":1470},{"a":"@空白kuuhaku","m":"ダジャレの時点でオジサンだったか……","t":1478},{"a":"@nuinui-s628","m":"こんろね～10ヶ月おめでとう□□","t":1487},{"a":"@shisonoha","m":"ワンカップを湯せんしてあつかんもありらしいっすね:sake:´-","t":1488},{"a":"@fia_osake","m":"美味しいなら良かった〜□アルコール感はあるよね","t":1498},{"a":"@8みちゅ_こめっ粉","m":"見せたれ、開く前の写真を□□","t":1499},{"a":"@中野三玖-y3x","m":"ちゃんとお水飲んでね…ワンカップって15%もあるんだね:green_heart:","t":1500},{"a":"@えぴ-e5h","m":"あれは嫌な事件だったね...","t":1504},{"a":"@藤井八雲-k4s","m":"おじさんが、もう一杯分おごっちゃる。お祝いだしなぁ:㊗:","t":1505},{"a":"@Natu7214","m":"やっぱり破壊神じゃん","t":1507},{"a":"@しょぼん-l4c","m":"□□","t":1515},{"a":"@まささま-r2d","m":"１周年の頃にはましろねおじさんに・・・□","t":1516},{"a":"@fia_osake","m":"ないすぱ〜","t":1519},{"a":"@Kei_通りすがり","m":"ナイスパ！","t":1523},{"a":"@extえくすと","m":"ないすぱ","t":1527},{"a":"@空白kuuhaku","m":"ナイスパ〜","t":1527},{"a":"@まっつん-UR","m":"ないすぱ","t":1528},{"a":"@hiroroろめふれ","m":"ナイスパ","t":1529},{"a":"@おつかれさま","m":"ないすぱ","t":1531},{"a":"@extえくすと","m":"ましろねの力が暴走しちゃったのか","t":1540},{"a":"@ハクスタ","m":"じゃがりこのフタが薄皮だけ剥がれて開かないみたいな不運ね","t":1544},{"a":"@猫やなぎ_999","m":"取っ手は一度手前に引いてから上に持ち上げると開けやすい","t":1545},{"a":"@こうさ-c8l","m":"ないすぱー","t":1553},{"a":"@かたっち-h8j","m":"ナイスパ","t":1560},{"a":"@オオスカシバ-y2w","m":"ワンカップデストロイヤーまし□","t":1562},{"a":"@寒村サムソン","m":"ないすぱ！","t":1563},{"a":"@たろやん-n4v","m":"ないすぱ","t":1564},{"a":"@thecoolmiregoji784","m":"good evening","t":1568},{"a":"@ポン助-q9i","m":"welcome to酒カス","t":1572},{"a":"@オオスカシバ-y2w","m":"ないすぱ！","t":1574},{"a":"@shisonoha","m":"ないすぱ","t":1579},{"a":"@fia_osake","m":"お手軽日本酒でずっと売れてるやつだからね〜","t":1580},{"a":"@kuro_244","m":"こん□〜祝10ヶ月","t":1590},{"a":"@ごはん処ラピ","m":"［おさけをのみにきたみんなへ］ましろねは、かんじのよめない「ぽんのこ」です。でも、ひといちばいあいきょうのある、とてもかわいいこです。むずかしいかんじには「ふりがな」をふって、よみやすくしてくれるとましろねがよろこびます。これからも、ましろねとなかよくしてあげてね。おめでとうのおいわいも、おまちしてます！きょうはたのしくのもうね！ ましろねあいごきょうかいより","t":1612},{"a":"@8みちゅ_こめっ粉","m":"#潰れたまし□見たい","t":1613},{"a":"@shisonoha","m":"ましろねおいたんは草","t":1617},{"a":"@ゆきりん47","m":"Nani kore Ope cup:grinning_face_with_sweat:","t":1617},{"a":"@ミサラギの助","m":"進化でもしてる？w","t":1617},{"a":"@spherer7129","m":"一周年は大五郎とかになってそう","t":1633},{"a":"@おつかれさま","m":"新しい愛護協会だw","t":1634},{"a":"@extえくすと","m":"おじろねになったら極寒になるな","t":1638},{"a":"@まっつん-UR","m":"定期助かる","t":1639},{"a":"@fia_osake","m":"愛護協会ないす〜□","t":1652},{"a":"@空白kuuhaku","m":"ワンカップ持ちながら破壊してくのか","t":1658},{"a":"@BOTAMOCHISAMA","m":"こんばんわー","t":1658},{"a":"@中野三玖-y3x","m":"ミミィさんのお酒のおつまみにしてるのは何？","t":1676},{"a":"@猫やなぎ_999","m":"パックで売ってる鬼殺しが楽だけどねストローでより酔いやすい","t":1707},{"a":"@まささま-r2d","m":"□□□","t":1719},{"a":"@オオスカシバ-y2w","m":"□□□","t":1721},{"a":"@空白kuuhaku","m":"愛護協会ナイス〜","t":1722},{"a":"@おつかれさま","m":"昔コンビニで買ったワンカップ開けてレンチンしてもらってる女子大生いたな〜","t":1722},{"a":"@ポン助-q9i","m":":㊗:under ground","t":1729},{"a":"@extえくすと","m":"いつも助かる愛護協会","t":1729},{"a":"@たろやん-n4v","m":"□□□","t":1737},{"a":"@spherer7129","m":"平仮名はスラスラ□□","t":1738},{"a":"@風呂カラ親父44","m":"ワンカップまだ飲んだことないな〜どんな味だった?","t":1751},{"a":"@AmahaneSupica","m":"こんろね～！デビュー10ヶ月記念おめでとう～！！","t":1759},{"a":"@spherer7129","m":"大五郎は焼酎かな","t":1764},{"a":"@shisonoha","m":"おつまみなし！？","t":1777},{"a":"@8みちゅ_こめっ粉","m":"おててにワンカップ持たないの〜？","t":1777},{"a":"@fia_osake","m":"大五郎とか大樹氷はアカン！","t":1781},{"a":"@空白kuuhaku","m":"ないのか…大丈夫か？","t":1782},{"a":"@おつかれさま","m":"大五郎は消毒っぽい味の焼酎かな〜","t":1785},{"a":"@えぴ-e5h","m":"？？？？？？","t":1789},{"a":"@藤井八雲-k4s","m":"ワンカップ大関ミニは100mlしか入ってないんだ。次は1合（いちごう）180mlだね。","t":1789},{"a":"@shisonoha","m":"パンパンのパンって新しいなw","t":1805},{"a":"@fia_osake","m":"すでにちゃんと食べてるならOK:woman_gesturing_ok:","t":1805},{"a":"@おつかれさま","m":"ブリの焼きジャケ！？","t":1805},{"a":"@まっつん-UR","m":"お腹がパンパンのパン:bread:","t":1807},{"a":"@BOTAMOCHISAMA","m":"先に胃に入れてるならまぁ大丈夫か","t":1809},{"a":"@ポン助-q9i","m":"酒カスの友達ビッグマンでしょW","t":1809},{"a":"@ごはん処ラピ","m":"「「「ぶりの焼き鮭」」」って言いかけたの、たぶんみんな聞き逃さなかったね:thinking_face:","t":1814},{"a":"@extえくすと","m":"ブリの焼き鮭って言おうとした□","t":1815},{"a":"@るーんowo","m":"ブリの焼き鮭...□□","t":1823},{"a":"@あじもぐら","m":"ぶり　と　焼き魚　と　お肉！？　おかず多くね","t":1828},{"a":"@猫やなぎ_999","m":"大五郎は焼酎だね4リットルペットボトルで買うこともできる","t":1830},{"a":"@オオスカシバ-y2w","m":"ブリの焼き鮭！日本酒と合わせたい夕飯の代表やん！","t":1839},{"a":"@Cinis-Eques_Lynx_SX","m":"大関（おおぜき","t":1841},{"a":"@寒村サムソン","m":"たいせき……？","t":1842},{"a":"@8みちゅ_こめっ粉","m":"焼いたブリで良いのではw","t":1844},{"a":"@fia_osake","m":"スルーしかけたけど鰤の焼き鮭とは、、、？","t":1853},{"a":"@アポーーンス","m":"ブリ良いですな","t":1854},{"a":"@藤井八雲-k4s","m":"おおぜき　って読むよ","t":1857},{"a":"@kuro_244","m":"かまたワンカップ破壊してるのオモロ〜","t":1872},{"a":"@空白kuuhaku","m":"おおぜき","t":1873},{"a":"@えぴ-e5h","m":"ぶりの焼きジャケ（哲学）","t":1875},{"a":"@おつかれさま","m":"うわぁぁぁあ！","t":1887},{"a":"@空白kuuhaku","m":"あれ？今日初配信ですか？よろしくお願いします","t":1896},{"a":"@ごはん処ラピ","m":"しょけんです。わんかっぷのんでるんですね！","t":1896},{"a":"@えぴ-e5h","m":"うわぁぁぁぁぁ","t":1898},{"a":"@ポン助-q9i","m":"初見です。可愛いですね:red_heart:","t":1900},{"a":"@おつかれさま","m":"猫耳可愛いですね！","t":1903},{"a":"@風呂カラ親父44","m":"初見、可愛いですね(^^)ﾉｼ（笑）","t":1903},{"a":"@8みちゅ_こめっ粉","m":"1回で2品食べてるましろね、さすが□□","t":1905},{"a":"@まささま-r2d","m":"野菜も食べなよｗ","t":1908},{"a":"@lippy_youtube","m":"忘れろビームうわぁぁ、、、今日ってましろねさんの初配信日でしたっけ？","t":1914},{"a":"@寒村サムソン","m":"初見ですかね？","t":1914},{"a":"@extえくすと","m":"やらかしの渋滞や","t":1915},{"a":"@Kei_通りすがり","m":"あれ、はじめまして","t":1918},{"a":"@つよし-s9z","m":"初見です","t":1920},{"a":"@藤井八雲-k4s","m":"カップに書いてあるよね…ローマ字で:grinning_face_with_sweat:","t":1924},{"a":"@ハクスタ","m":"初見です、デビュー配信ですか？","t":1925},{"a":"@fia_osake","m":"初見です？よろしくお願いします。","t":1925},{"a":"@こうさ-c8l","m":"初見です。可愛い子猫ちゃんだねー！","t":1925},{"a":"@クマがクマった球磨熊ーくまくまー","m":"書見です。ぶりはさけ_φ(･_･","t":1928},{"a":"@まっつん-UR","m":"初見です！可愛いですね！あれ？チャンネル登録してある...","t":1936},{"a":"@kuro_244","m":"いろいろ誤字ってたな〜ワンカップデストロイヤーましろねスマン！","t":1938},{"a":"@るーんowo","m":"初見です！ めちゃくちゃかわいいですね！","t":1939},{"a":"@spherer7129","m":"初見です声可愛いですね","t":1940},{"a":"@えぴ-e5h","m":"しょけんです。ワンカップおいしそうですね","t":1941},{"a":"@おつかれさま","m":"ないすぱ！","t":1951},{"a":"@ふぃぐれむ","m":"今週のちびろね代なげたっけ、、、？（もういい","t":1951},{"a":"@オオスカシバ-y2w","m":"ｱﾚﾏｼﾛﾈｯﾃﾀﾞﾚ?","t":1952},{"a":"@こうさ-c8l","m":"ないすぱ〜","t":1954},{"a":"@hiroroろめふれ","m":"ナイスパ","t":1956},{"a":"@空白kuuhaku","m":"ナイスパ〜","t":1958},{"a":"@lippy_youtube","m":"しょけんさんないすぱ！","t":1958},{"a":"@fia_osake","m":"ないすぱ〜","t":1959},{"a":"@まささま-r2d","m":"んないすぱ～□","t":1959},{"a":"@たろやん-n4v","m":"ないすぱ","t":1961},{"a":"@ミサラギの助","m":"助言です。","t":1962},{"a":"@Kei_通りすがり","m":"ナイスパ！","t":1964},{"a":"@kawa7521","m":"こんばんは！Vtuberデビュー10ヶ月おめでとうございます:confetti_ball:","t":1967},{"a":"@まっつん-UR","m":"ないすぱ","t":1969},{"a":"@Seir_","m":"halo ~ !","t":1971},{"a":"@るーんowo","m":"ないすぱ！","t":1971},{"a":"@高橋伸一-g5j","m":"鰤の照り焼き？","t":1972},{"a":"@しょぼん-l4c","m":"？？？","t":1973},{"a":"@風呂カラ親父44","m":"( ﾟдﾟ)ﾊｯ!","t":1975},{"a":"@Cinis-Eques_Lynx_SX","m":"っは、鰤の焼き鮭！","t":1976},{"a":"@Seir_","m":"□□□","t":1977},{"a":"@おつかれさま","m":"はっ･･･あびんかびん･･･","t":1980},{"a":"@のざわ豆アジ","m":"こん□□","t":1981},{"a":"@ほいみ","m":"あれ？初めまして…かな？可愛いですね登録…既にしてただと！？","t":1981},{"a":"@ポン助-q9i","m":"酒カスが:red_exclamation_mark:W","t":1982},{"a":"@クマがクマった球磨熊ーくまくまー","m":"は！たんあし、なまれい…","t":1984},{"a":"@るーんowo","m":"ハッ","t":1985},{"a":"@オオスカシバ-y2w","m":"ハッ鰤の焼き鮭ェ！","t":1985},{"a":"@extえくすと","m":"ないすぱ","t":1985},{"a":"@かきみーらorz","m":"っは！呼吸忘れてた","t":1987},{"a":"@中野三玖-y3x","m":"ミミィさん…私､ちょっとお花畑行ってくるから､また戻って来るよ","t":1988},{"a":"@lippy_youtube","m":"思い出せビームうわぁぁぁ、、、今日って5周年&100万人記念日でしたっけ？おめでとうございます","t":1988},{"a":"@OA_オーエー","m":"初見で... ( ﾟдﾟ)ﾊｯ! 一体なんだったのか・・・","t":1990},{"a":"@ごはん処ラピ","m":"まったく、ましろねは…ブリの焼き鮭とか言うから…(しっかり記憶復元)","t":1991},{"a":"@まっつん-UR","m":"( ﾟдﾟ)ﾊｯ!　俺は今まで何を...","t":1994},{"a":"@おつかれさま","m":"ないまい！","t":1998},{"a":"@ハクスタ","m":"弓矢(やいば)って言った？","t":1999},{"a":"@fia_osake","m":"はっ！？","t":2001},{"a":"@こうさ-c8l","m":"ないめん〜","t":2005},{"a":"@まささま-r2d","m":"ブリの焼き鮭さん、こん□","t":2006},{"a":"@かたっち-h8j","m":"ないまい","t":2008},{"a":"@spherer7129","m":"思い・・・出した！","t":2012},{"a":"@Kei_通りすがり","m":"ないまい！","t":2015},{"a":"@寒村サムソン","m":"ないまい！","t":2016},{"a":"@hiroroろめふれ","m":"ないまい","t":2016},{"a":"@ミサラギの助","m":"ワンカップデストロイヤー、、なにそれ怖いw","t":2018},{"a":"@Seir_","m":"□□□","t":2023},{"a":"@fia_osake","m":"うえかるび〜□","t":2024},{"a":"@extえくすと","m":"ないまい","t":2025},{"a":"@るーんowo","m":"ないまーい！","t":2028},{"a":"@ミサラギの助","m":"ないまい！","t":2029},{"a":"@ブラックギャリア","m":"ぶりの焼き鮭","t":2041},{"a":"@つよし-s9z","m":"思い出した！","t":2042},{"a":"@るーんowo","m":"破壊神ましろねちゃん..","t":2044},{"a":"@まっつん-UR","m":"思い...出した！","t":2046},{"a":"@シリル正宗","m":"こんばんは～","t":2052},{"a":"@extえくすと","m":"おー","t":2053},{"a":"@shisonoha","m":"おーメンギフとな:sparkles:","t":2054},{"a":"@ブラックギャリア","m":"щ(ﾟдﾟщ)ｶﾓｰﾝ","t":2055},{"a":"@3106osamu","m":"おう　思い出した","t":2062},{"a":"@寒村サムソン","m":"花粉症でくしゃみハクショウ……うぅ……頭が……","t":2063},{"a":"@Kei_通りすがり","m":"ん？思い出した〜","t":2091},{"a":"@ハクスタ","m":"コメ欄既にもうほぼ緑で埋まってるけども□","t":2093},{"a":"@takuroghost","m":"こんろね、いつも朝活ありがとうございます。いつも明るい笑顔も声に救われてます","t":2096},{"a":"@ミサラギの助","m":"今日こそメンギフ当たるかな？ワクワク:smiling_face:","t":2098},{"a":"@ポン助-q9i","m":"スパチャ投げたいのに投げれない:red_question_mark:なぜ:red_question_mark:","t":2103},{"a":"@マサカリ715","m":"こんろね　平日配信初見ですw","t":2104},{"a":"@おつかれさま","m":"初見さん、ゆっくりしていってね！","t":2114},{"a":"@ごはん処ラピ","m":"「ましろねよりも皆様に愛されている」と噂のあいごきょうかいさんも、早4ヶ月だそうです。","t":2116},{"a":"@夜叉-v5v","m":"こん□10ヶ月おめでとうございます:party_popper::confetti_ball::confetti_ball:","t":2117},{"a":"@ほいみ","m":"あ、頭が痛い…","t":2122},{"a":"@おつかれさま","m":"ないまい！","t":2126},{"a":"@寒村サムソン","m":"ないまい！","t":2129},{"a":"@hiroroろめふれ","m":"なまれい思い出した□","t":2134},{"a":"@氷雨.ヒサメ.-s7u-y2d","m":"こんろね10ヶ月おめでとう:party_popper:メンゲンのイラスト書いてくれてありがとう今日見ました","t":2138},{"a":"@かたっち-h8j","m":"ないまい","t":2140},{"a":"@ブラックギャリア","m":"ギフト待ってます(笑)","t":2142},{"a":"@おつかれさま","m":"ないすぱ！","t":2145},{"a":"@hiroroろめふれ","m":"ナイスパ","t":2149},{"a":"@ブラックギャリア","m":"ないすぱ","t":2152},{"a":"@fia_osake","m":"ないすぱ〜","t":2154},{"a":"@まささま-r2d","m":"初見さんいらっしゃい～","t":2158},{"a":"@かたっち-h8j","m":"ナイスパ","t":2161},{"a":"@extえくすと","m":"ないすぱ","t":2161},{"a":"@hiroroろめふれ","m":"ないまい","t":2168},{"a":"@るーんowo","m":"ないまい！ないすぱ！","t":2179},{"a":"@オオスカシバ-y2w","m":"ないまちないすぱ！","t":2180},{"a":"@extえくすと","m":"もうブリの焼き鮭デストロイヤーでいいか","t":2181},{"a":"@Kei_通りすがり","m":"ナイスパ！","t":2182},{"a":"@寒村サムソン","m":"ないすぱ！","t":2197},{"a":"@心奏ここな-t1p","m":"こん□","t":2206},{"a":"@たろやん-n4v","m":"ないすぱ","t":2223},{"a":"@オオスカシバ-y2w","m":"なまれいとは","t":2258},{"a":"@uchan502","m":"やっほーい！来たよー♡","t":2261},{"a":"@おつかれさま","m":"生霊(なまれい)","t":2278},{"a":"@べらぼう-b4w","m":"こん□ デビュー10か月おめでとう！！□","t":2310},{"a":"@まささま-r2d","m":"いつも通りな気が・・・□","t":2318},{"a":"@クマがクマった球磨熊ーくまくまー","m":"デスろねさん、ましろねーずの精神が試される配信ですねw","t":2321},{"a":"@藤井八雲-k4s","m":"酔っ払ってきてるのかな？","t":2323},{"a":"@ハクスタ","m":"そういえばまだお披露目してなかった","t":2325},{"a":"@noki-k3e","m":"こんばんは～","t":2331},{"a":"@りあチーズケーキ","m":"こんろね〜可愛いぞ","t":2335},{"a":"@ミサラギの助","m":"そろそろビーム浴びすぎて、みんなが□になってまうやろ、、、w","t":2337},{"a":"@高橋伸一-g5j","m":"□□□□","t":2347},{"a":"@おつかれさま","m":"いきりょう だからねw","t":2347},{"a":"@まっつん-UR","m":"なまれいｗ","t":2348},{"a":"@こうさ-c8l","m":"なまれいってw","t":2360},{"a":"@香辛","m":"こん□ですー！10か月おめでとうございますー！！□","t":2385},{"a":"@おつかれさま","m":"ないすぱ！","t":2391},{"a":"@hiroroろめふれ","m":"ナイスパ","t":2391},{"a":"@寒村サムソン","m":"ないすぱ！","t":2391},{"a":"@夜叉-v5v","m":"なまれい","t":2392},{"a":"@Kei_通りすがり","m":"ナイスパ！","t":2399},{"a":"@おつかれさま","m":"ギフト当たるかなワクワク！","t":2401},{"a":"@ふぃぐれむ","m":"どっか漏れてたワンカップ開封はお披露目されてる・・・□","t":2402},{"a":"@まささま-r2d","m":"現在御披露目、ワンカップのみ□","t":2403},{"a":"@まっつん-UR","m":"ないすぱぁ","t":2404},{"a":"@HAL_KRPS-13","m":"ないすぱー","t":2405},{"a":"@ミサラギの助","m":"ないすぱ！","t":2406},{"a":"@ブラックギャリア","m":"きたゃー！","t":2410},{"a":"@フレミングno右手","m":"こんろね〜□デビュー10ヶ月おめでとう〜:party_popper:","t":2413},{"a":"@のざわ豆アジ","m":"ナイスパ","t":2417},{"a":"@たろやん-n4v","m":"ないすぱ","t":2418},{"a":"@夜叉-v5v","m":"ないすぱ","t":2420},{"a":"@ミサラギの助","m":"ワンカップ開封お披露目じゃないの？□□","t":2428},{"a":"@オオスカシバ-y2w","m":"わかったなまれいで□","t":2428},{"a":"@高橋伸一-g5j","m":"□□□□□","t":2431},{"a":"@かたっち-h8j","m":"真白猫さん緊張してるならお酒飲んで飲んで〜","t":2435},{"a":"@まささま-r2d","m":"んないすぱ～□","t":2435},{"a":"@フレミングno右手","m":":party_popper::party_popper::party_popper::party_popper::party_popper:","t":2439},{"a":"@寒村サムソン","m":"ないまい！","t":2446},{"a":"@おつかれさま","m":"ないまい！","t":2448},{"a":"@shisonoha","m":"当たるといいなギフト:sparkles:","t":2450},{"a":"@ミサラギの助","m":"ないまい！","t":2453},{"a":"@hiroroろめふれ","m":"ないまい","t":2453},{"a":"@extえくすと","m":"ないまい","t":2455},{"a":"@Kei_通りすがり","m":"ないまい！","t":2456},{"a":"@オオスカシバ-y2w","m":"ないまい！","t":2458},{"a":"@shisonoha","m":"ないまい！","t":2459},{"a":"@勇気ポンコツ","m":"こん□","t":2460},{"a":"@かたっち-h8j","m":"ないまい","t":2465},{"a":"@たろやん-n4v","m":"ないまい","t":2467},{"a":"@まささま-r2d","m":"ないまい□","t":2468},{"a":"@uchan502","m":"ギフト、わくわく:smiling_face:","t":2469},{"a":"@川崎ミライ","m":"こんろね～、ワンカップだ！","t":2470},{"a":"@ほいみ","m":"ははぁ～んさては既に相当呑んでるな","t":2472},{"a":"@まっつん-UR","m":"ないまい","t":2474},{"a":"@extえくすと","m":"今思ったけどコメ欄ほぼメンバーやね□","t":2476},{"a":"@おつかれさま","m":"□□□","t":2481},{"a":"@高橋伸一-g5j","m":"□□□□","t":2498},{"a":"@えぴ-e5h","m":"当たった...？","t":2505},{"a":"@まささま-r2d","m":"当たった□","t":2505},{"a":"@Natu7214","m":"こうして耳のてっぺんからしっぽの先まで酒浸りな猫が完成していく...","t":2513},{"a":"@spherer7129","m":"当たりました□","t":2520},{"a":"@かたっち-h8j","m":"当たれ～","t":2520},{"a":"@寒村サムソン","m":"ワンカップ当たりますように！","t":2521},{"a":"@えぴ-e5h","m":"ワンカップ当選おめでとうございます！","t":2522},{"a":"@フレミングno右手","m":":clapping_hands::clapping_hands::clapping_hands::clapping_hands::clapping_hands:","t":2534},{"a":"@まささま-r2d","m":"□□□","t":2535},{"a":"@オオスカシバ-y2w","m":"ワンカップあたりましたぁ！","t":2539},{"a":"@川崎ミライ","m":"当選者の方おめでとうございます～","t":2541},{"a":"@Kei_通りすがり","m":"□□□□","t":2541},{"a":"@おつかれさま","m":"当たらなかった！？","t":2542},{"a":"@3106osamu","m":"外れたー(","t":2542},{"a":"@たろやん-n4v","m":"□□□","t":2542},{"a":"@lippy_youtube","m":"□□□□□","t":2543},{"a":"@勇気ポンコツ","m":"□□□□","t":2543},{"a":"@えぴ-e5h","m":"□□□□□","t":2544},{"a":"@shisonoha","m":"□□□","t":2544},{"a":"@まっつん-UR","m":"□□□□","t":2545},{"a":"@おつかれさま","m":"□□□","t":2545},{"a":"@こうさ-c8l","m":"ないぎふぅ！","t":2546},{"a":"@hiroroろめふれ","m":"□□□","t":2546},{"a":"@extえくすと","m":"□□□","t":2549},{"a":"@ブラックギャリア","m":"あるぇ？","t":2549},{"a":"@ふぇいと-n5s","m":"□□□","t":2549},{"a":"@こうさ-c8l","m":"□□□□□","t":2552},{"a":"@spherer7129","m":"□□□","t":2553},{"a":"@えぴ-e5h","m":"当たらなかったぴえん","t":2553},{"a":"@暖簾のれんカツカレー","m":"□□□□","t":2553},{"a":"@つよし-s9z","m":"□□□□","t":2554},{"a":"@夜叉-v5v","m":"□□□","t":2556},{"a":"@fia_osake","m":"当たった人おめでと〜□□□","t":2556},{"a":"@アグ-f4j","m":"おめでとー、ワンカップいいなあ","t":2556},{"a":"@hiroroろめふれ","m":"ないぎふ","t":2557},{"a":"@寒村サムソン","m":"ないぎふ！:clapping_hands:","t":2557},{"a":"@AyaOhkura","m":"□□□","t":2557},{"a":"@おつかれさま","m":"ないぎふ！","t":2558},{"a":"@ミサラギの助","m":"ないぎふ！&お歌ないすぅー□□□□","t":2558},{"a":"@かたっち-h8j","m":"おめでとう:confetti_ball:","t":2560},{"a":"@高橋伸一-g5j","m":"□□□□□□□","t":2561},{"a":"@3106osamu","m":"□□□□□","t":2561},{"a":"@川崎ミライ","m":"□□□","t":2563},{"a":"@ごはん処ラピ","m":"やったーーー！！メンギフだぁぁぁ！！ありがとーーー！！(まぼろし)","t":2566},{"a":"@クマがクマった球磨熊ーくまくまー","m":"ありがとうございます！","t":2569},{"a":"@アポーーンス","m":"ないぎふ","t":2569},{"a":"@べらぼう-b4w","m":"くそう！外れた～～～！","t":2573},{"a":"@寒村サムソン","m":"ないぎふ！","t":2573},{"a":"@藤井八雲-k4s","m":":clapping_hands::clapping_hands::clapping_hands::clapping_hands::clapping_hands:","t":2575},{"a":"@extえくすと","m":"ないぎふ","t":2576},{"a":"@Kei_通りすがり","m":"ナイギフ！","t":2578},{"a":"@たろやん-n4v","m":"ないぎふ","t":2578},{"a":"@オオスカシバ-y2w","m":"□□□□□","t":2578},{"a":"@hiroroろめふれ","m":"ないぎふ","t":2579},{"a":"@ミサラギの助","m":"ないぎふ！","t":2583},{"a":"@かたっち-h8j","m":"ないぎふ","t":2586},{"a":"@えぴ-e5h","m":"ワンカップなら当たったんだがなぁ...","t":2586},{"a":"@まささま-r2d","m":"ワンカップはこれから投げるのかな？□","t":2588},{"a":"@lippy_youtube","m":"ないぎふ！","t":2592},{"a":"@おつかれさま","m":"ないぎふ！","t":2593},{"a":"@extえくすと","m":"ないぎふ","t":2594},{"a":"@かたっち-h8j","m":"ないぎふ","t":2595},{"a":"@ミサラギの助","m":"ないぎふ！","t":2595},{"a":"@フレミングno右手","m":"ないギフ！","t":2597},{"a":"@ShinKa331","m":"ないぎふ！","t":2597},{"a":"@おつかれさま","m":"ないぎふ！","t":2600},{"a":"@まささま-r2d","m":"ないぎふ～□","t":2601},{"a":"@たろやん-n4v","m":"ないぎふ","t":2602},{"a":"@ブラックギャリア","m":"ないぎふ","t":2604},{"a":"@おつかれさま","m":"ないぎふ！","t":2604},{"a":"@寒村サムソン","m":"ないぎふ！","t":2605},{"a":"@teruteru666","m":"俺も誰からかもらってたww","t":2605},{"a":"@かたっち-h8j","m":"ないぎふ","t":2606},{"a":"@lippy_youtube","m":"ギフト祭りktkr","t":2606},{"a":"@shisonoha","m":"ないぎふ！","t":2607},{"a":"@フレミングno右手","m":"ないギフ！","t":2611},{"a":"@fia_osake","m":"ないぎふ！","t":2611},{"a":"@hiroroろめふれ","m":"ないぎふ","t":2615},{"a":"@Kei_通りすがり","m":"ナイギフ！","t":2616},{"a":"@ミサラギの助","m":"ギフト祭りw緑化が進む進むw","t":2618},{"a":"@寒村サムソン","m":"ないぎふ！","t":2623},{"a":"@fia_osake","m":"ないぎふ！","t":2623},{"a":"@おつかれさま","m":"ないぎふ！","t":2624},{"a":"@ミサラギの助","m":"ないぎふ！","t":2625},{"a":"@ふぃぐれむ","m":"またログに殴られる主・・・","t":2626},{"a":"@こうさ-c8l","m":"ないぎふぅぅぅぅぅ！","t":2629},{"a":"@まささま-r2d","m":"酔っぱらいには厳しいか□","t":2631},{"a":"@たろやん-n4v","m":"ないぎふ","t":2632},{"a":"@勇気ポンコツ","m":"デビュー10ヶ月おめでとう:party_popper::party_popper::party_popper:","t":2634},{"a":"@extえくすと","m":"ないぎふ","t":2634},{"a":"@hiroroろめふれ","m":"ないぎふ","t":2635},{"a":"@ハクスタ","m":"便乗ギフトだー！！","t":2636},{"a":"@RexRayEX","m":"こん□□□□","t":2638},{"a":"@teruteru666","m":"□□□□□□□","t":2639},{"a":"@おつかれさま","m":"ないすぱ！","t":2640},{"a":"@まささま-r2d","m":"んないすぱ～□","t":2642},{"a":"@寒村サムソン","m":"ないすぱ！ないぎふ！","t":2647},{"a":"@おつかれさま","m":"ないぎふ！","t":2647},{"a":"@extえくすと","m":"ないすぱ","t":2647},{"a":"@hiroroろめふれ","m":"ナイスパ　ないぎふ","t":2649},{"a":"@ミサラギの助","m":"ないすぱ！","t":2649},{"a":"@extえくすと","m":"ないぎふ","t":2651},{"a":"@fia_osake","m":"ないすぱ！ないぎふ！","t":2652},{"a":"@はてにゃん-u9i","m":"こんばんは 初見です","t":2652},{"a":"@ミサラギの助","m":"ないぎふ！","t":2656},{"a":"@たろやん-n4v","m":"ないぎふ","t":2658},{"a":"@おつかれさま","m":"初見さん、ゆっくりしていってね！","t":2660},{"a":"@fia_osake","m":"初見さんいらっしゃい〜","t":2660},{"a":"@ミサラギの助","m":"初見さんいらっしゃーい！","t":2665},{"a":"@まっつん-UR","m":"初見様いらっしゃ～い","t":2666},{"a":"@Kei_通りすがり","m":"初見さんいらっしゃい","t":2667},{"a":"@まささま-r2d","m":"初見さんいらっしゃい～","t":2667},{"a":"@ほいみ","m":"ナイギフ□","t":2669},{"a":"@たろやん-n4v","m":"初見さんいらっしゃい","t":2669},{"a":"@hiroroろめふれ","m":"初見さんいらっしゃい","t":2674},{"a":"@おつかれさま","m":"ないぎふ！","t":2675},{"a":"@寒村サムソン","m":"ないぎふ！","t":2676},{"a":"@まささま-r2d","m":"ないぎふ～□","t":2676},{"a":"@かたっち-h8j","m":"初見さんいらっしゃい","t":2677},{"a":"@fia_osake","m":"ないぎふ〜","t":2678},{"a":"@ミサラギの助","m":"ないぎふ！","t":2678},{"a":"@中野三玖-y3x","m":"戻ってきた","t":2680},{"a":"@寒村サムソン","m":"初見さんいらっしゃい","t":2683},{"a":"@暖簾のれんカツカレー","m":"ないぎふ！","t":2686},{"a":"@hiroroろめふれ","m":"ないぎふ","t":2686},{"a":"@ほいみ","m":"ナイギフ□","t":2687},{"a":"@アポーーンス","m":"ないぎふ","t":2695},{"a":"@extえくすと","m":"止まらないギフト□","t":2696},{"a":"@たろやん-n4v","m":"ないぎふ","t":2707},{"a":"@ミサラギの助","m":"すごいなー大草原w","t":2707},{"a":"@fia_osake","m":"ましろねは追いつくことが出来るのか□","t":2715},{"a":"@Kei_通りすがり","m":"ナイギフ！","t":2720},{"a":"@おつかれさま","m":"ないぎふ！","t":2724},{"a":"@寒村サムソン","m":"ないぎふ！","t":2725},{"a":"@fia_osake","m":"ないぎふ！","t":2725},{"a":"@ミサラギの助","m":"ないぎふ！","t":2728},{"a":"@たろやん-n4v","m":"ないぎふ","t":2734},{"a":"@暖簾のれんカツカレー","m":"ないぎふ！","t":2736},{"a":"@まささま-r2d","m":"ギフトの数はのんびりしてない□","t":2736},{"a":"@かたっち-h8j","m":"ないぎふがたくさんだー","t":2736},{"a":"@高橋伸一-g5j","m":"初見さん、いらっしゃい□","t":2739},{"a":"@hiroroろめふれ","m":"ないぎふ","t":2741},{"a":"@アポーーンス","m":"ないぎふ","t":2749},{"a":"@spherer7129","m":"なかなか配信背景にいけない□□□","t":2756},{"a":"@ミサラギの助","m":"ましろね追いつける、、、か？","t":2760},{"a":"@ハクスタ","m":"緑化がすごいんよ□","t":2778},{"a":"@中野三玖-y3x","m":"戻ってきたけど…そろそろ寝ます､最後まで見れなくてごめんね…おやすみ:blue_heart:","t":2799},{"a":"@ごはん処ラピ","m":"みんなメンギフ貰って嬉しいねぇ(さもみんな白かったみたいな言い方)","t":2801},{"a":"@まっつん-UR","m":"これが本当のみどりの日","t":2810},{"a":"@HAL_KRPS-13","m":"ないぎふ祭り","t":2819},{"a":"@ハクスタ","m":"緑化が進むチャット欄□","t":2823},{"a":"@ミサラギの助","m":"確かに緑の日だなぁw","t":2832},{"a":"@hiroroろめふれ","m":"ないまい","t":2832},{"a":"@Kei_通りすがり","m":"ないまい！","t":2836},{"a":"@かたっち-h8j","m":"ないまい","t":2836},{"a":"@寒村サムソン","m":"ないまい！","t":2836},{"a":"@おつかれさま","m":"ないまい！","t":2839},{"a":"@ミサラギの助","m":"ないまい！","t":2842},{"a":"@extえくすと","m":"ないまい","t":2848},{"a":"@m猫です","m":"ないまい","t":2852},{"a":"@オオスカシバ-y2w","m":"ないまい！","t":2853},{"a":"@まっつん-UR","m":"ないまい","t":2857},{"a":"@寒村サムソン","m":"3分でメンバー40人増えたなぁ:clapping_hands:","t":2858},{"a":"@まささま-r2d","m":"ましろねおじたん、読み上げがんばえ～□","t":2860},{"a":"@えぴ-e5h","m":"コメ欄が忙しいw","t":2861},{"a":"@つばさ箱","m":"デビュー10ヵ月おめ□","t":2882},{"a":"@おつかれさま","m":"ないまい！","t":2894},{"a":"@寒村サムソン","m":"ないまい！","t":2895},{"a":"@hiroroろめふれ","m":"ないまい","t":2896},{"a":"@m猫です","m":"ないまい","t":2897},{"a":"@まささま-r2d","m":"ないまい～","t":2899},{"a":"@かたっち-h8j","m":"ないまい","t":2900},{"a":"@Kei_通りすがり","m":"ないまい！","t":2904},{"a":"@フレミングno右手","m":"灰色はいねぇか〜？","t":2904},{"a":"@オオスカシバ-y2w","m":"ないまい！","t":2906},{"a":"@たろやん-n4v","m":"ないまい","t":2913},{"a":"@まっつん-UR","m":"ないまい","t":2913},{"a":"@空白kuuhaku","m":"すみませんギフトありがとうございます。","t":2915},{"a":"@寒村サムソン","m":"ないぎふ！","t":2922},{"a":"@まささま-r2d","m":"ないぎふ～□","t":2925},{"a":"@かたっち-h8j","m":"ないぎふ","t":2925},{"a":"@おつかれさま","m":"ないぎふ！","t":2925},{"a":"@まっつん-UR","m":"ないぎふーｗ","t":2927},{"a":"@hiroroろめふれ","m":"ないぎふ","t":2930},{"a":"@つばさ箱","m":"ないぎふと言われた気がしたので□□","t":2930},{"a":"@Kei_通りすがり","m":"ナイギフ！","t":2930},{"a":"@たろやん-n4v","m":"ないぎふ","t":2933},{"a":"@オオスカシバ-y2w","m":"ないぎふ！","t":2933},{"a":"@ShinKa331","m":"ないぎふ～","t":2934},{"a":"@ミサラギの助","m":"ないぎふ！","t":2935},{"a":"@m猫です","m":"ナイギフ！","t":2935},{"a":"@フレミングno右手","m":"ないギフ〜","t":2940},{"a":"@HAL_KRPS-13","m":"灰色がいないぎふー","t":2951},{"a":"@spherer7129","m":"緑が増えればスタンプ枠増えるから…","t":2952},{"a":"@ブラックギャリア","m":"１０ヶ月おめでとう","t":2952},{"a":"@寒村サムソン","m":"ないまい！","t":2958},{"a":"@Kei_通りすがり","m":"ないまい！","t":2961},{"a":"@まささま-r2d","m":"ないまい～","t":2962},{"a":"@hiroroろめふれ","m":"ないまい","t":2964},{"a":"@extえくすと","m":"もうここにいる人ほとんどメンバーやな","t":2966},{"a":"@たろやん-n4v","m":"ないまい","t":2968},{"a":"@m猫です","m":"ないまい！","t":2969},{"a":"@extえくすと","m":"ないまい","t":2969},{"a":"@ミサラギの助","m":"ないまい！","t":2970},{"a":"@まっつん-UR","m":"ないまい","t":2972},{"a":"@かたっち-h8j","m":"ないまい","t":2973},{"a":"@fia_osake","m":"ないまい","t":2979},{"a":"@ミサラギの助","m":"中々お披露目に進めないましろねであったw","t":2984},{"a":"@九条暗月-k5h","m":":face-red-heart-shape::face-red-heart-shape::face-red-heart-shape:","t":2985},{"a":"@おつかれさま","m":"新スタンプワクワク！","t":2990},{"a":"@とっし-v9q","m":"こんろね□□","t":2994},{"a":"@まっつん-UR","m":"なんて？ｗ","t":2996},{"a":"@3106osamu","m":"なんだって？","t":2997},{"a":"@hiroroろめふれ","m":"あじょぺぇ□□□","t":3002},{"a":"@extえくすと","m":"落ち着くんや□","t":3004},{"a":"@MOGER865","m":"こん□□","t":3006},{"a":"@まささま-r2d","m":"酔ってきた？","t":3006},{"a":"@えぴ-e5h","m":"いまなんて？","t":3006},{"a":"@おつかれさま","m":"あちょぷれ〜w","t":3006},{"a":"@空白kuuhaku","m":"ましろね酔ってる？","t":3007},{"a":"@とっし-v9q","m":"メンギフありがとです□","t":3008},{"a":"@つばさ箱","m":"10ヵ月おめでとうご祝儀です□□","t":3010},{"a":"@fia_osake","m":"疲れて滑舌が死んできてるw","t":3015},{"a":"@空白kuuhaku","m":"ナイスパ〜□□","t":3017},{"a":"@Kei_通りすがり","m":"ナイスパ！","t":3019},{"a":"@寒村サムソン","m":"ないすぱ！","t":3019},{"a":"@おつかれさま","m":"ないすぱ！","t":3019},{"a":"@かたっち-h8j","m":"ないぎふ","t":3019},{"a":"@まささま-r2d","m":"んないすぱ～□","t":3021},{"a":"@たろやん-n4v","m":"ないすぱ","t":3022},{"a":"@hiroroろめふれ","m":"ナイスパ","t":3025},{"a":"@m猫です","m":"ナイスパ！","t":3025},{"a":"@まっつん-UR","m":"ないすぱ！","t":3025},{"a":"@かたっち-h8j","m":"ナイスパ","t":3027},{"a":"@ほいみ","m":"ナイスパ□","t":3028},{"a":"@fia_osake","m":"ないすぱ！","t":3032},{"a":"@暖簾のれんカツカレー","m":"ないすぱ！","t":3035},{"a":"@えぴ-e5h","m":"疲れなのか酔いなのかw","t":3037},{"a":"@HAL_KRPS-13","m":"呼ばれてない(呼ばれた)","t":3037},{"a":"@アグ-f4j","m":"疲れてるのでは","t":3042},{"a":"@フレミングno右手","m":"ないスパ！","t":3042},{"a":"@まささま-r2d","m":"１５％だからね～","t":3052},{"a":"@こねこね-kone5ne","m":"こん□です～□","t":3065},{"a":"@えぴ-e5h","m":"深呼吸してワンカップ","t":3070},{"a":"@おつかれさま","m":"お披露目いえ〜い！□□","t":3079},{"a":"@fia_osake","m":"お披露目だ〜！□□□","t":3090},{"a":"@とても眠い人-w2f","m":"おはろーねー□□□□□□10ヶ月おめでと□□","t":3090},{"a":"@ハクスタ","m":"□□","t":3091},{"a":"@えぴ-e5h","m":"お酒大量に並んだ冷蔵庫の中予想","t":3097},{"a":"@MOGER865","m":"□□","t":3100},{"a":"@まささま-r2d","m":"背景が酒じゃないことを祈る□","t":3100},{"a":"@lippy_youtube","m":"□□","t":3104},{"a":"@OA_オーエー","m":"おじろね出てるよ","t":3104},{"a":"@空白kuuhaku","m":"新しい背景はダジャレ会場かな？","t":3105},{"a":"@かたっち-h8j","m":"お披露目まで□□","t":3110},{"a":"@あまつ_そら","m":"こん□～10か月おめでとう！","t":3114},{"a":"@lippy_youtube","m":"停電？！？！□","t":3117},{"a":"@ブラックギャリア","m":"すまんな、明日仕事やから、早めに寝ないとあかんから、お先におつろね～","t":3118},{"a":"@えぴ-e5h","m":"！？","t":3119},{"a":"@空白kuuhaku","m":"ちびろね〜:red_exclamation_mark:","t":3119},{"a":"@spherer7129","m":"□□","t":3123},{"a":"@fia_osake","m":"停電w","t":3124},{"a":"@寒村サムソン","m":"新背景は驚きの黒さ！","t":3124},{"a":"@ほいみ","m":"ワロタ","t":3126},{"a":"@ふぃぐれむ","m":"ちびろねどっかいったから作業もどりますね（ぇ","t":3127},{"a":"@hiroroろめふれ","m":"□□","t":3128},{"a":"@こねこね-kone5ne","m":"いきなり真っ暗□","t":3128},{"a":"@オオスカシバ-y2w","m":"びっくりしたw","t":3129},{"a":"@えぴ-e5h","m":"新背景は真っ暗か","t":3132},{"a":"@chiinii2nd","m":"コンバンハ:crescent_moon:","t":3148},{"a":"@fia_osake","m":"ちびろねを返せ〜w","t":3149},{"a":"@つよし-s9z","m":"ちび□！？","t":3153},{"a":"@ほいみ","m":"解散","t":3157},{"a":"@えぴ-e5h","m":"ちびろねだけは助けてください","t":3158},{"a":"@BOTAMOCHISAMA","m":"ちびろね(「・ω・)ドコ？","t":3166},{"a":"@空白kuuhaku","m":"癒やしのちびろねいなくなっちゃった……悲しいからまたね〜","t":3173},{"a":"@まっつん-UR","m":"ちびろね目当てのリスナー多くて草","t":3181},{"a":"@とっし-v9q","m":"おでんつまみつつワンカップ飲んで、半分くらいになったらおでんの汁をカップに注いで七味ひと振りして飲んでみて□","t":3181},{"a":"@spherer7129","m":"ちびろね推し多いのに…","t":3188},{"a":"@かふぇいん-u2b","m":"こんばんは~","t":3194},{"a":"@BOTAMOCHISAMA","m":"#俺たちのちびろねを返して","t":3194},{"a":"@天城シナノ","m":"こん□です～10か月おめでとうございます。ちびろねちゃんが足りないようですね、見つけてうちで保護しておきますね","t":3208},{"a":"@extえくすと","m":"愛されちびろね","t":3215},{"a":"@えぴ-e5h","m":"#俺たちのちびろねを返して","t":3216},{"a":"@extえくすと","m":"わたわた","t":3227},{"a":"@オオスカシバ-y2w","m":"#俺ちび","t":3234},{"a":"@まささま-r2d","m":"なんか□の匂いがする・・・","t":3240},{"a":"@空白kuuhaku","m":"メインがちびろねだからね","t":3253},{"a":"@ごはん処ラピ","m":"ちびろねあいごきょうかい…:thinking_face:","t":3262},{"a":"@桜華Oka","m":"こんろね～　10ヶ月おめでとう～","t":3291},{"a":"@ハクスタ","m":"ドラムロール待機:drum:","t":3293},{"a":"@おつかれさま","m":"黒から入るんだw","t":3298},{"a":"@lippy_youtube","m":"(*・ω・*)wkwk","t":3305},{"a":"@空白kuuhaku","m":"ドラムロールくるか？","t":3308},{"a":"@vysphc","m":"こんばんは～！おめでとうございます〜","t":3309},{"a":"@高橋伸一-g5j","m":"□□□","t":3311},{"a":"@とっし-v9q","m":"□□□","t":3312},{"a":"@cdab6040","m":"地獄の背景とか？血の池地獄とか","t":3315},{"a":"@fia_osake","m":"ドラムロールしよう！","t":3317},{"a":"@オオスカシバ-y2w","m":"ﾃﾞｹﾃﾞｹﾃﾞｹﾃﾞｹﾃﾞｹﾃﾞｹ…","t":3323},{"a":"@ゲーム大好きytk","m":"こん□　10ヶ月おめでとう□","t":3328},{"a":"@高橋伸一-g5j","m":"□□□□","t":3335},{"a":"@空白kuuhaku","m":"下手なドラムロール助かる","t":3353},{"a":"@3106osamu","m":"あらかわいい","t":3354},{"a":"@かたっち-h8j","m":"お披露目新背景:㊗:□□:party_popper::party_popper:","t":3355},{"a":"@ShinKa331","m":"おおお～！","t":3356},{"a":"@天城シナノ","m":":clapping_hands::clapping_hands::clapping_hands::clapping_hands::clapping_hands:","t":3356},{"a":"@lippy_youtube","m":"□□□□□□□","t":3358},{"a":"@べらぼう-b4w","m":":waving_hand::waving_hand::waving_hand::waving_hand::waving_hand::waving_hand::waving_hand::waving_hand:","t":3358},{"a":"@こねこね-kone5ne","m":"□□□□□","t":3358},{"a":"@かきみーらorz","m":":clapping_hands::clapping_hands::clapping_hands::clapping_hands::clapping_hands::clapping_hands::clapping_hands::clapping_hands::clapping_hands:","t":3358},{"a":"@まっつん-UR","m":"うおおおおお","t":3359},{"a":"@ぺとらんち","m":"かわよ","t":3361},{"a":"@ミサラギの助","m":"□□□□","t":3361},{"a":"@AyaOhkura","m":"□□□□□","t":3362},{"a":"@とっし-v9q","m":"かわいいーー□□□","t":3362},{"a":"@つよし-s9z","m":"□□□□","t":3362},{"a":"@空白kuuhaku","m":":clapping_hands::clapping_hands::clapping_hands::clapping_hands::clapping_hands:","t":3362},{"a":"@ゲーム大好きytk","m":"□□□□","t":3363},{"a":"@おつかれさま","m":"□□□","t":3363},{"a":"@まささま-r2d","m":"お～□□□","t":3363},{"a":"@まっつん-UR","m":"□□□□□","t":3364},{"a":"@ShinKa331","m":"□□□□□□","t":3364},{"a":"@たろやん-n4v","m":"□□□□□□□","t":3366},{"a":"@Kei_通りすがり","m":"□□□□□□","t":3367},{"a":"@spherer7129","m":"□□□","t":3367},{"a":"@野良犬屋敷","m":"□□□□□□□","t":3367},{"a":"@空白kuuhaku","m":"□□□□","t":3367},{"a":"@extえくすと","m":"□□□","t":3367},{"a":"@暖簾のれんカツカレー","m":"□□□□□","t":3368},{"a":"@こねこね-kone5ne","m":"涼しげなお部屋！","t":3368},{"a":"@高橋伸一-g5j","m":"□□□□□□□□□□□□□□□□","t":3368},{"a":"@vysphc","m":"□□□","t":3370},{"a":"@chiinii2nd","m":":clapping_hands::clapping_hands::clapping_hands:","t":3372},{"a":"@mosamosa-magic","m":"かわいいな！","t":3372},{"a":"@hiroroろめふれ","m":"ドラムロール目覚ましにしたいな□","t":3372},{"a":"@ナナシ名前","m":"おおー","t":3372},{"a":"@寒村サムソン","m":"ましろねダジャレで凍った部屋かな？:clapping_hands:","t":3375},{"a":"@アポーーンス","m":":clapping_hands::clapping_hands::clapping_hands:","t":3376},{"a":"@ふぇいと-n5s","m":"□□□","t":3376},{"a":"@mosamosa-magic","m":"□□□□□","t":3376},{"a":"@ごはん処ラピ","m":"□□□□□□□","t":3377},{"a":"@つばさ箱","m":"□□□□□□","t":3377},{"a":"@のざわ豆アジ","m":"□□□□□","t":3378},{"a":"@hiroroろめふれ","m":"□□□□□□","t":3378},{"a":"@ほいみ","m":"□□□□□□","t":3378},{"a":"@天城シナノ","m":"驚きの白さ！ｗ","t":3382},{"a":"@BOTAMOCHISAMA","m":"□□□□□","t":3385},{"a":"@extえくすと","m":"水色基調の部屋めっちゃ可愛いね","t":3385},{"a":"@まっつん-UR","m":"かわいいいいいい","t":3386},{"a":"@アグ-f4j","m":"あー、真っ白だ","t":3386},{"a":"@オオスカシバ-y2w","m":"おおおお！夏によきです","t":3388},{"a":"@HAL_KRPS-13","m":"かわよい","t":3390},{"a":"@十兵衛-10b","m":"□□","t":3391},{"a":"@MOGER865","m":"めっちゃ可愛い □□□□□","t":3392},{"a":"@ハクスタ","m":"へたっぴドラムロールとクセのつよいカウントダウン□","t":3393},{"a":"@かたっち-h8j","m":"新背景かわいいいいいー","t":3395},{"a":"@えぴ-e5h","m":"黒から白で目ないなった","t":3397},{"a":"@空白kuuhaku","m":"可愛〜:red_exclamation_mark::red_exclamation_mark::red_exclamation_mark:","t":3397},{"a":"@fia_osake","m":"おー！！！青基調できれい！","t":3397},{"a":"@ナナシ名前","m":"かわいいー","t":3401},{"a":"@高橋伸一-g5j","m":"□□□□□□□□□□□□□□□□","t":3402},{"a":"@つよし-s9z","m":"背景かわいい〜","t":3402},{"a":"@まささま-r2d","m":"アタックか！□","t":3409},{"a":"@えぴ-e5h","m":"ドラムロールたすかる","t":3413},{"a":"@アグ-f4j","m":"いや、真っ白というか水色に近いやつか","t":3420},{"a":"@おつかれさま","m":"新しいお部屋おめっと～□□","t":3426},{"a":"@フレミングno右手","m":"□□□□□","t":3430},{"a":"@まささま-r2d","m":"んないすぱ～□","t":3434},{"a":"@ハクスタ","m":"白と水色すきっていってたもんね","t":3436},{"a":"@空白kuuhaku","m":"部屋が綺麗だぞ！？","t":3436},{"a":"@ミサラギの助","m":"ないすぱ！","t":3439},{"a":"@spherer7129","m":"リボン多くない？","t":3442},{"a":"@アポーーンス","m":"ないすぱ","t":3444},{"a":"@ShinKa331","m":"可愛いお部屋□","t":3446},{"a":"@えぴ-e5h","m":"水色ミミィ","t":3449},{"a":"@たろやん-n4v","m":"ないすぱ","t":3449},{"a":"@ShinKa331","m":"ないすぱ！","t":3451},{"a":"@Kei_通りすがり","m":"ナイスパ！","t":3459},{"a":"@寒村サムソン","m":"ないすぱ！","t":3461},{"a":"@オオスカシバ-y2w","m":"良きおみあし…","t":3462},{"a":"@フレミングno右手","m":"ないスパ！","t":3463},{"a":"@ゲーム大好きytk","m":"ないすぱ","t":3466},{"a":"@空白kuuhaku","m":"ナイスパ〜□","t":3472},{"a":"@オオスカシバ-y2w","m":"ないすぱ！","t":3474},{"a":"@クマがクマった球磨熊ーくまくまー","m":"新しい部屋やったー！","t":3474},{"a":"@おつかれさま","m":"耳カーソルたすかるw","t":3491},{"a":"@extえくすと","m":"ましろねの新しい部屋が豪邸や","t":3494},{"a":"@スーパーノヴァブルーベリー朧月DI","m":"可愛い","t":3500},{"a":"@アグ-f4j","m":"夜もあると？","t":3503},{"a":"@hiroroろめふれ","m":"涼しげでいいね□","t":3504},{"a":"@オオスカシバ-y2w","m":"住みたい","t":3505},{"a":"@寒村サムソン","m":"サンシャインぐらい？(難聴)","t":3512},{"a":"@えぴ-e5h","m":"お酒こぼさないようにね","t":3515},{"a":"@ごはん処ラピ","m":"あと8047匹ぐらい並べなきゃね、ましろねーず(みたいな子):thinking_face:","t":3518},{"a":"@まささま-r2d","m":"この部屋は酒を飲む感じではないね～□","t":3519},{"a":"@まっつん-UR","m":"朝Verだって！？","t":3520},{"a":"@fia_osake","m":"こだわりいっぱいだね！","t":3520},{"a":"@かきみーらorz","m":"涼し気だね～","t":3520},{"a":"@HAL_KRPS-13","m":"爽やか","t":3521},{"a":"@まささま-r2d","m":"時報？","t":3540},{"a":"@空白kuuhaku","m":"夜だね","t":3543},{"a":"@ゲーム大好きytk","m":"10:00からやっと夜になる□","t":3554},{"a":"@まっつん-UR","m":"おおおおおお","t":3563},{"a":"@mosamosa-magic","m":"かわいいー！","t":3566},{"a":"@lippy_youtube","m":"うおおおおお□□","t":3567},{"a":"@えぴ-e5h","m":"めっちゃきれい！！！","t":3567},{"a":"@おつかれさま","m":"おーなるほど〜","t":3569},{"a":"@extえくすと","m":"おー！！！！","t":3570},{"a":"@空白kuuhaku","m":"凄い:red_exclamation_mark::red_exclamation_mark:","t":3570},{"a":"@ゲーム大好きytk","m":"□□□","t":3571},{"a":"@mosamosa-magic","m":"□□□□□","t":3572},{"a":"@フレミングno右手","m":"おーーーー□□□","t":3572},{"a":"@こねこね-kone5ne","m":"おぉーー□□□","t":3572},{"a":"@たろやん-n4v","m":"おお〜□□□□□","t":3573},{"a":"@オオスカシバ-y2w","m":"□□□□□□","t":3573},{"a":"@Kei_通りすがり","m":"□□□□□","t":3573},{"a":"@3106osamu","m":"夜の方が良いな","t":3573},{"a":"@アポーーンス","m":"めっちゃ良いですね","t":3574},{"a":"@ミサラギの助","m":"おぉ！□□□","t":3574},{"a":"@MOGER865","m":"□□□□□","t":3574},{"a":"@まささま-r2d","m":"□□□","t":3574},{"a":"@ShinKa331","m":"□□□□","t":3575},{"a":"@おつかれさま","m":"□□□","t":3575},{"a":"@すいのみ","m":"10か月おめでとう　画面右下と左下の子かわ…いないやん","t":3576},{"a":"@かたっち-h8j","m":"夜バージョン:night_with_stars:□□","t":3577},{"a":"@空白kuuhaku","m":"□□□□","t":3578},{"a":"@AyaOhkura","m":"□□","t":3578},{"a":"@アグ-f4j","m":"わお","t":3579},{"a":"@hiroroろめふれ","m":"おー□□□□","t":3579},{"a":"@つよし-s9z","m":"□□□","t":3579},{"a":"@暖簾のれんカツカレー","m":"□□□□","t":3580},{"a":"@えぴ-e5h","m":"深海の中みたい","t":3581},{"a":"@オオスカシバ-y2w","m":"雰囲気すこ","t":3584},{"a":"@lippy_youtube","m":"夜ver.助かる","t":3585},{"a":"@extえくすと","m":"夜バージョンめっちゃいいね□□","t":3585},{"a":"@まっつん-UR","m":"□□□□□","t":3587},{"a":"@望月薫-96","m":"おぉ～おリボンいっぱいだぁ","t":3587},{"a":"@のざわ豆アジ","m":"□□□□□","t":3588},{"a":"@寒村サムソン","m":":clapping_hands::clapping_hands::clapping_hands:","t":3589},{"a":"@あまつ_そら","m":"□□□□","t":3590},{"a":"@空白kuuhaku","m":"夜が良いね〜","t":3590},{"a":"@まささま-r2d","m":"確かに□","t":3591},{"a":"@fia_osake","m":"おー！ライトもついて幻想的な雰囲気や〜","t":3610},{"a":"@とっし-v9q","m":"お酒が捗りそう","t":3618},{"a":"@つばさ箱","m":"熟睡できそうな落ち着いた色合い□□","t":3618},{"a":"@のざわ豆アジ","m":"夜は雰囲気あっていいよね","t":3622},{"a":"@たろやん-n4v","m":"夜バージョン、雰囲気バッチリ□","t":3623},{"a":"@ハクスタ","m":"ASMR配信に合いそうですね(誘導)","t":3625},{"a":"@まっつん-UR","m":"幻想的やなぁー","t":3629},{"a":"@HAL_KRPS-13","m":"なんかエ◯い","t":3632},{"a":"@ゲーム大好きytk","m":"夜配信見たこと無いなまだ","t":3637},{"a":"@extえくすと","m":"こんな凄い部屋にいてダジャレ言うの信じられないぞ","t":3638},{"a":"@えぴ-e5h","m":"この部屋にはお酒こぼさないでくださいね...","t":3639},{"a":"@おつかれさま","m":"こっちもさわやかでいいですな〜","t":3673},{"a":"@とっし-v9q","m":"上目遣いたすかる□","t":3676},{"a":"@アポーーンス","m":"ヒーリング効果バツグンですね","t":3679},{"a":"@extえくすと","m":"これはこれで見やすいね","t":3681},{"a":"@まっつん-UR","m":"チラチラましろね可愛い","t":3696},{"a":"@星咲さくら","m":"こんばんは＼(^▽^)／！私も夜配信見たことがないかも。朝は見たことがあるけれど。","t":3697},{"a":"@fia_osake","m":"こっちの方が朝っぽい感じがするね","t":3702},{"a":"@つよし-s9z","m":"目にやさしい色","t":3705},{"a":"@かたっち-h8j","m":"新背景にしたら真白猫さんの衣装も新しくする予定ありますか？","t":3710},{"a":"@たろやん-n4v","m":"夜配信はお初です","t":3711},{"a":"@MOGER865","m":"私も初めてです","t":3713},{"a":"@lippy_youtube","m":"夜ver.でASMR配信……:thinking_face:","t":3715},{"a":"@ふぃぐれむ","m":"大丈夫、岩おじが終わるわけ無いから早速使えるね・・・□","t":3720},{"a":"@ゲーム大好きytk","m":"夜勤サボってるときに見れると良いんだけど…","t":3721},{"a":"@まささま-r2d","m":"朝活のイメージだよね","t":3727},{"a":"@えぴ-e5h","m":"ましろねASMRまじ？","t":3732},{"a":"@mosamosa-magic","m":"朝と夜で使い分けできるのいいね♪","t":3735},{"a":"@ポン助-q9i","m":"寒そうな部屋ですね","t":3746},{"a":"@まっつん-UR","m":"猫じゃらしがあるｗ","t":3773},{"a":"@mosamosa-magic","m":"見慣れたベッド","t":3775},{"a":"@fia_osake","m":"窓からの光の差し込みいい感じ〜□","t":3777},{"a":"@とっし-v9q","m":"寝相大丈夫？階段から転落しない？","t":3780},{"a":"@クマがクマった球磨熊ーくまくまー","m":"夜のましろねさん。えっt","t":3783},{"a":"@おつかれさま","m":"2の味噌汁が似合わないか･･･","t":3783},{"a":"@寒村サムソン","m":"ここで朝から熱燗をキメるのか……","t":3813},{"a":"@るーんowo","m":"かわいい〜〜〜","t":3813},{"a":"@extえくすと","m":"めっちゃ可愛い〜","t":3823},{"a":"@まささま-r2d","m":"もう、カフェオレ一択やろ□","t":3823},{"a":"@neo_nazo0828","m":"こんばんわ。","t":3825},{"a":"@えぴ-e5h","m":"この部屋は白湯しか勝たん","t":3825},{"a":"@空白kuuhaku","m":"こんなに素敵な部屋なのにダジャレが飛び交うのか〜","t":3826},{"a":"@hiroroろめふれ","m":"ましろねーずが2人いる□","t":3829},{"a":"@えぴ-e5h","m":"？？？？","t":3829},{"a":"@ゲーム大好きytk","m":"ワンカップが似合うのはおっさんの部屋です…","t":3833},{"a":"@ハクスタ","m":"せめてワインかな…w","t":3837},{"a":"@オオスカシバ-y2w","m":"さては後ろの棚に並んでる瓶は酒だな！？","t":3844},{"a":"@fia_osake","m":"□とっても良い感じ□□","t":3844},{"a":"@えぴ-e5h","m":"ちなみに右のましろねーずは俺","t":3850},{"a":"@かたっち-h8j","m":"新しいましろねーずちゃんの名前決めよー","t":3853},{"a":"@とっし-v9q","m":"ワンカップのおでんの出し汁割り:oden:","t":3860},{"a":"@のざわ豆アジ","m":"夜の部屋はカクテルが似合いそうだね～","t":3860},{"a":"@空白kuuhaku","m":"前のも好きだったけど新しいお部屋も良いね","t":3868},{"a":"@HAL_KRPS-13","m":"マカロンしか食べれない部屋","t":3868},{"a":"@おつかれさま","m":"□□□","t":3876},{"a":"@まささま-r2d","m":"□□□","t":3877},{"a":"@寒村サムソン","m":":clapping_hands::clapping_hands::clapping_hands:","t":3879},{"a":"@たろやん-n4v","m":"□□□","t":3883},{"a":"@鋼屋-Haganeya","m":"こんばんは〜□","t":3911},{"a":"@extえくすと","m":"仕立ててくれた方に感謝〜","t":3916},{"a":"@寒村サムソン","m":"素晴らしい:clapping_hands::clapping_hands::clapping_hands::clapping_hands::clapping_hands:","t":3919},{"a":"@まっつん-UR","m":"□□□□□","t":3919},{"a":"@おつかれさま","m":"なになに？","t":3919},{"a":"@hiroroろめふれ","m":"□□□","t":3921},{"a":"@つよし-s9z","m":"□□□□","t":3929},{"a":"@まささま-r2d","m":"□□□","t":3929},{"a":"@るーんowo","m":"素晴らしい□□","t":3930},{"a":"@空白kuuhaku","m":"□□□□","t":3930},{"a":"@おつかれさま","m":"□□□","t":3935},{"a":"@藤井八雲-k4s","m":"□□□","t":3945},{"a":"@lippy_youtube","m":"□□□","t":3952},{"a":"@ハクスタ","m":"こういうデザインできるお仕事の方ほんと尊敬します:sparkles:","t":3957},{"a":"@えぴ-e5h","m":"□□□□□□","t":3962},{"a":"@ミサラギの助","m":"□□□","t":3965},{"a":"@夜叉-v5v","m":"□□□","t":3965},{"a":"@まっつん-UR","m":"大丈夫よ:thumbs_up:","t":3967},{"a":"@fia_osake","m":"感謝□□□","t":3968},{"a":"@空白kuuhaku","m":"来月には床にお酒の缶が並んでそう","t":3978},{"a":"@えぴ-e5h","m":"右のましろねーずは僕ですこれからよろしくお願いします（？）","t":3989},{"a":"@寒村サムソン","m":"すごいなぁ……","t":3990},{"a":"@そー茶_0214","m":"こんろね〜","t":4006},{"a":"@アポーーンス","m":"澪（っていう青いビンのお酒）置いたら似合いそうですね","t":4016},{"a":"@matagu405","m":"後ろの窓から誰かのぞいてる…？","t":4020},{"a":"@extえくすと","m":"ましろね感がめっちゃ出てていいよね","t":4024},{"a":"@ユウゴ2","m":"こん□初めてこの時間帯に来たな","t":4037},{"a":"@ゲーム大好きytk","m":"後ろの椅子の上とか？","t":4038},{"a":"@ゲーム大好きytk","m":"部屋に並べるようのストゼロ素材欲しいね","t":4064},{"a":"@寒村サムソン","m":"この背景でましろねのお気に入りポイントもっと紹介してくださいな","t":4069},{"a":"@まっつん-UR","m":"お掃除えらい！","t":4080},{"a":"@lippy_youtube","m":"やっぱ夜ver.でASMR良さそう□","t":4083},{"a":"@ハクスタ","m":"ましろねはオシャンなワインしか飲みませんですわよ:wine_glass:","t":4095},{"a":"@ポン助-q9i","m":"久しぶりに親子ケンカ疲れたぜ:red_exclamation_mark:フゥ〜","t":4095},{"a":"@西條冬雪-SaijoFuyuki","m":"おはろね....じゃなかった。こんばんは","t":4097},{"a":"@ソールドアウトにょん","m":"こんろねです！","t":4106},{"a":"@オオスカシバ-y2w","m":"わかる","t":4121},{"a":"@高橋伸一-g5j","m":"ミミィちゃん、チラチラショート","t":4126},{"a":"@こませる","m":"こん□□立ってるとこ初めて見たきゃわぃぃ！□□□","t":4154},{"a":"@寒村サムソン","m":"おぉ、なるほど！……酒臭ぇ！","t":4159},{"a":"@おつかれさま","m":"膝小僧たすかる〜","t":4160},{"a":"@おつかれさま","m":"□□□","t":4175},{"a":"@オオスカシバ-y2w","m":"□□□□□","t":4175},{"a":"@まっつん-UR","m":"□□□□","t":4181},{"a":"@ハクスタ","m":"□□□","t":4185},{"a":"@寒村サムソン","m":":clapping_hands::clapping_hands::clapping_hands::clapping_hands::clapping_hands:","t":4188},{"a":"@たろやん-n4v","m":"□□□□","t":4188},{"a":"@Kei_通りすがり","m":"□□□","t":4194},{"a":"@高橋伸一-g5j","m":"□□□□□","t":4195},{"a":"@つよし-s9z","m":"□□□","t":4198},{"a":"@空白kuuhaku","m":"肘【ひじ】って言わなくて安心したよ","t":4201},{"a":"@空白kuuhaku","m":"□□□□","t":4206},{"a":"@こませる","m":":clapping_hands: :👏🏻: :👏🏼: :👏🏽: :👏🏾: :👏🏿:","t":4209},{"a":"@えぴ-e5h","m":"この部屋でワンカップ飲んでるの面白すぎるな....","t":4223},{"a":"@夜叉-v5v","m":"□□□","t":4227},{"a":"@寒村サムソン","m":"ましろねの耳とリボン再現してるんやなぁ","t":4255},{"a":"@ユウゴ2","m":"細かいな□□□","t":4260},{"a":"@extえくすと","m":"最高やね","t":4261},{"a":"@まっつん-UR","m":"すごいなぁ","t":4262},{"a":"@mikiyam1264","m":"こんばんは。デビュー10か月おめでとうございます","t":4272},{"a":"@fia_osake","m":"全身立ち絵だしてこの背景良い感じにマッチするな","t":4289},{"a":"@ハクスタ","m":"一応…□","t":4312},{"a":"@空白kuuhaku","m":"飼い猫だったの？","t":4322},{"a":"@えぴ-e5h","m":"飼い主はちびろねですか？","t":4326},{"a":"@ミサラギの助","m":"飼い猫だと、、！？","t":4327},{"a":"@むりくり-x5l","m":"こん□〜、夜勤中だからちょっと覗くだけ〜","t":4328},{"a":"@ぺとらんち","m":"かちこちに緊張してるティザーPV！","t":4335},{"a":"@アグ-f4j","m":"そういえばそうだった…完全に忘れてた","t":4349},{"a":"@空白kuuhaku","m":"飼われた家でワンカップか……","t":4350},{"a":"@extえくすと","m":"でも今ひとり暮らしやもんね","t":4356},{"a":"@fia_osake","m":"一人暮らし(飼い猫)","t":4369},{"a":"@ユウゴ2","m":"まさか飼い主がいたのか……","t":4373},{"a":"@えぴ-e5h","m":"買ってくれた綺麗な部屋でワンカップこぼすんですねわかります","t":4376},{"a":"@ゲーム大好きytk","m":"一人暮らしの飼猫とは？","t":4380},{"a":"@アグ-f4j","m":"という事飼われた家で酒が転がってると","t":4383},{"a":"@ポン助-q9i","m":"気分が落ち着かないのでおつろね〜□","t":4390},{"a":"@オオスカシバ-y2w","m":"おうち内独り立ち…","t":4421},{"a":"@ハクスタ","m":"一文で矛盾を生み出していく猫","t":4421},{"a":"@ゲーム大好きytk","m":"今までは、飼い主を尻目に酒かっ喰らってたのか","t":4423},{"a":"@ちんまさ〆age48","m":"おつろね〜:cat2:もう10カ月ですか:eyes::sparkles:おめでと〜:㊗:","t":4434},{"a":"@むりくり-x5l","m":"ないすぱ！","t":4445},{"a":"@ゲーム大好きytk","m":"ないすぱ","t":4446},{"a":"@hiroroろめふれ","m":"ナイスパ","t":4448},{"a":"@ミサラギの助","m":"ないすぱ！","t":4448},{"a":"@寒村サムソン","m":"ないすぱ！","t":4449},{"a":"@かたっち-h8j","m":"ナイスパ","t":4450},{"a":"@空白kuuhaku","m":"ナイスパ〜□□","t":4450},{"a":"@まささま-r2d","m":"んないすぱ～□","t":4450},{"a":"@オオスカシバ-y2w","m":"ないすぱ！","t":4451},{"a":"@クマがクマった球磨熊ーくまくまー","m":"一人立ちした飼い猫…？戸惑いが止まらないw","t":4452},{"a":"@まっつん-UR","m":"ないすぱぁ","t":4454},{"a":"@fia_osake","m":"ないすぱ〜","t":4454},{"a":"@Kei_通りすがり","m":"ナイスパ！","t":4457},{"a":"@空白kuuhaku","m":"余計にタチが悪いわ","t":4478},{"a":"@不幸なジン","m":"こんろね〜","t":4483},{"a":"@ミサラギの助","m":"新しいお部屋は何ヶ月ぐらいで、お酒のカヲリが染みつくかな？","t":4483},{"a":"@fia_osake","m":"どこから持ってきたんやその酒w","t":4487},{"a":"@ゲーム大好きytk","m":"飼い主さんのささやかな楽しみである酒を隠れて勝手に飲んでたのか。なんて、ひどい猫なんだ","t":4497},{"a":"@kekeの毛っ毛0v0","m":"こん□ですぅ","t":4505},{"a":"@空白kuuhaku","m":"飼い猫が一人暮らししたらそれはもう野良猫なんよ","t":4550},{"a":"@kekeの毛っ毛0v0","m":"水色基調のお部屋素敵ですね:sparkles:","t":4560},{"a":"@ta-isan","m":"こんろねー","t":4583},{"a":"@extえくすと","m":"全身助かる","t":4594},{"a":"@ハクスタ","m":"厚めのガーゼ可愛い！","t":4597},{"a":"@不幸なジン2","m":"10ヶ月おめでとやで〜","t":4605},{"a":"@すしまる1129","m":"こんばんはデビュー10ヶ月おめでとうございます","t":4606},{"a":"@むりくり-x5l","m":"ないすぱ！","t":4613},{"a":"@hiroroろめふれ","m":"ナイスパ","t":4615},{"a":"@Kei_通りすがり","m":"ナイスパ！","t":4621},{"a":"@kekeの毛っ毛0v0","m":"ないすぱ！","t":4623},{"a":"@HAL_KRPS-13","m":"シンプルに掃除大変そうって思ってしまった…","t":4628},{"a":"@kekeの毛っ毛0v0","m":"ちいちゃいのぉ","t":4629},{"a":"@寒村サムソン","m":"ないすぱ！","t":4629},{"a":"@ゲーム大好きytk","m":"ないすぱ","t":4633},{"a":"@カキツバ-t9p","m":"こん□１０カ月おめでとうございます！","t":4633},{"a":"@まささま-r2d","m":"んないすぱ～□","t":4633},{"a":"@ちんまさ〆age48","m":"ないすぱ！","t":4635},{"a":"@えぴ-e5h","m":"今更だけど笑った後に出る「はぁー↓」癖になるくらいすき","t":4635},{"a":"@ハクスタ","m":"ないすぱあ","t":4638},{"a":"@空白kuuhaku","m":"ナイスパ〜□","t":4639},{"a":"@えぴ-e5h","m":"ないすぱ！","t":4639},{"a":"@まっつん-UR","m":"ないすぱぁ","t":4641},{"a":"@るーんowo","m":"ないすぱ！","t":4646},{"a":"@カキツバ-t9p","m":"出遅れてる間に真白猫さんが引っ越してる！？可愛い:smiling_face_with_heart_eyes:","t":4668},{"a":"@かたっち-h8j","m":"新背景の真白猫さんスクショ〜:camera_with_flash:","t":4669},{"a":"@ちんまさ〆age48","m":"久々の全身や(*´Д｀*)ﾊｧﾊｧ","t":4673},{"a":"@たまもんn","m":"お足だ、わーい:raising_hands:□","t":4676},{"a":"@不幸なジン","m":"部屋かわいい","t":4680},{"a":"@Cinis-Eques_Lynx_SX","m":"掃除･･･、いっぱいいろいろ壊しそう","t":4682},{"a":"@空白kuuhaku","m":"全力で掃除……不安だ","t":4685},{"a":"@HAL_KRPS-13","m":"ほな大丈夫か","t":4686},{"a":"@るーんowo","m":"スクショが止まらん□","t":4691},{"a":"@matagu405","m":"ベッドの上にツマミの食べ残しが…","t":4695},{"a":"@るーんowo","m":"記者会見？","t":4721},{"a":"@ミサラギの助","m":"ぱしゃりん、、ちょ、、、？","t":4725},{"a":"@えぴ-e5h","m":":camera_with_flash::camera_with_flash::camera_with_flash:","t":4728},{"a":"@かたっち-h8j","m":":camera_with_flash::camera_with_flash:","t":4728},{"a":"@kekeの毛っ毛0v0","m":":camera_with_flash::camera_with_flash::camera_with_flash:口でパシャパシャたすかる","t":4734},{"a":"@オオスカシバ-y2w","m":"パシャリんちょしました","t":4734},{"a":"@えぴ-e5h","m":"ぱしゃりんちょとは","t":4737},{"a":"@空白kuuhaku","m":"新しいお部屋での初ダジャレお願いします:red_exclamation_mark:","t":4740},{"a":"@まささま-r2d","m":"パシャリンチョは初耳□","t":4740},{"a":"@ハクスタ","m":"ましろねオノマトペシリーズでしか得られない栄養があるぅ…(定期)","t":4748},{"a":"@ふぃぐれむ","m":"後片付けがちびろね（るんば）のお仕事になるんですね□","t":4762},{"a":"@ゲーム大好きytk","m":":camera_with_flash::sparkles:","t":4762},{"a":"@extえくすと","m":"スクショは撮りまくった□","t":4776},{"a":"@空白kuuhaku","m":"謝罪会見だったか……","t":4784},{"a":"@鋼屋-Haganeya","m":"俺も引っ越し当初は掃除頑張っていたさ…","t":4785},{"a":"@hiroroろめふれ","m":"写真とるよーぱしゃりんちょ！□","t":4787},{"a":"@uchan502","m":"良いね良いねー:camera_with_flash:","t":4788},{"a":"@まっつん-UR","m":":camera_with_flash::camera_with_flash::camera_with_flash:","t":4793},{"a":"@ゲーム大好きytk","m":"たぶん、やらかすね","t":4799},{"a":"@えぴ-e5h","m":"引越し記念謝罪会見とは...","t":4803},{"a":"@ミサラギの助","m":"謝罪会見ですか？w","t":4808},{"a":"@kekeの毛っ毛0v0","m":"すいませーん、目線お願いしまーす:raised_hand::camera_with_flash::camera_with_flash::camera_with_flash:","t":4812},{"a":"@ハクスタ","m":"本当にやらかした時用にとっておこう","t":4813},{"a":"@寒村サムソン","m":"なるほど、わからん","t":4815},{"a":"@マサ夫","m":"こん□","t":4816},{"a":"@マサ夫","m":"言いません","t":4826},{"a":"@fia_osake","m":"無理するときっと□やらかすなw","t":4829},{"a":"@アグ-f4j","m":"言わないな・・・","t":4832},{"a":"@ゲーム大好きytk","m":"ましろねさんの擬音は独特だから、個性だよ","t":4833},{"a":"@えぴ-e5h","m":"これから使っていきますね","t":4837},{"a":"@空白kuuhaku","m":"パシャリンチョ初めて聴いたよ","t":4840},{"a":"@ミサラギの助","m":"パシャりんちょは初めて聞いたわー","t":4845},{"a":"@むりくり-x5l","m":"ぱしゃりんちょ、は言わないかな〜？w","t":4846},{"a":"@マサ夫","m":"やめてもろて","t":4857},{"a":"@kekeの毛っ毛0v0","m":"パシャリんちょ！！！:camera_with_flash::camera_with_flash::camera_with_flash:","t":4860},{"a":"@extえくすと","m":"助かる〜可愛い〜","t":4861},{"a":"@えぴ-e5h","m":"キラキラ目好きだからたすかる","t":4864},{"a":"@Kei_通りすがり","m":":camera_with_flash::camera_with_flash::camera_with_flash:","t":4870},{"a":"@寒村サムソン","m":"草","t":4873},{"a":"@fia_osake","m":"可愛いけどねw","t":4874},{"a":"@3106osamu","m":"ジー　助かる","t":4875},{"a":"@ミサラギの助","m":"やべぇ逃げないと、、","t":4877},{"a":"@たまもんn","m":":eyes:ジー…","t":4878},{"a":"@まっつん-UR","m":"可愛いｗ","t":4878},{"a":"@hiroroろめふれ","m":"□□","t":4882},{"a":"@まささま-r2d","m":"足首も・・・掴んでいます□","t":4883},{"a":"@uchan502","m":"怖いのー:face-blue-wide-eyes:","t":4884},{"a":"@空白kuuhaku","m":"ちょっと怖いです","t":4886},{"a":"@えぴ-e5h","m":"怒られた:loudly_crying_face::loudly_crying_face::loudly_crying_face:","t":4895},{"a":"@つなな-e6y","m":"しいたけ目すこです","t":4898},{"a":"@kekeの毛っ毛0v0","m":"足首はここに置いていく！","t":4900},{"a":"@かたっち-h8j","m":"新背景の記念に真白猫さんダジャレお願いします","t":4937},{"a":"@オオスカシバ-y2w","m":"我々がましろねを覗く時、ましろねもまた我々を覗いているのだ…","t":4952},{"a":"@まっつん-UR","m":"しいたけ目＝キラキラ目:sparkles:","t":4957},{"a":"@extえくすと","m":"久しぶりにスクショめっちゃ撮ったわ","t":4960},{"a":"@えぴ-e5h","m":"みどころきたー！","t":4960},{"a":"@fia_osake","m":"コレ？って言いながら目閉じたまま(笑顔)なのよw","t":4961},{"a":"@kekeの毛っ毛0v0","m":":clapping_hands::clapping_hands::clapping_hands::clapping_hands::clapping_hands:","t":4968},{"a":"@3106osamu","m":"真っ白猫きちゃー","t":4970},{"a":"@ハクスタ","m":"え？","t":4970},{"a":"@かきみーらorz","m":"□□□□□□□","t":4970},{"a":"@高橋伸一-g5j","m":"かわいいショートがたくさんありがとうございます","t":4971},{"a":"@マサ夫","m":"どっかーーーーん","t":4971},{"a":"@カキツバ-t9p","m":"鉄板ネタきたーー！！","t":4974},{"a":"@つなな-e6y","m":"＼ドッ／","t":4977},{"a":"@まささま-r2d","m":"部屋が凍った？","t":4978},{"a":"@fia_osake","m":"まっしろねー！□□□","t":4982},{"a":"@ミサラギの助","m":"新しいダジャ、、、レ、、、？","t":4984},{"a":"@オオスカシバ-y2w","m":"夏にぴったりなダジャレですね！","t":4988},{"a":"@nature_nano","m":"こん□□","t":4989},{"a":"@夜叉-v5v","m":"う〜〜〜ん","t":4989},{"a":"@マサ夫","m":"しーーんとすな！","t":4989},{"a":"@3106osamu","m":"□□□□□","t":4990},{"a":"@hiroroろめふれ","m":"まっしろねー頂きました□□□","t":4990},{"a":"@つよし-s9z","m":"□□□□","t":4990},{"a":"@lippy_youtube","m":"今日の夜寝やすくなったかもしれない□","t":4992},{"a":"@高橋伸一-g5j","m":"□□□□□","t":4992},{"a":"@HAL_KRPS-13","m":"楽しそうで何より","t":4993},{"a":"@つばさ箱","m":"□□□□","t":4993},{"a":"@ShinKa331","m":"□□□","t":4994},{"a":"@kekeの毛っ毛0v0","m":"部屋は真っ青ね□□□□","t":4998},{"a":"@cdab6040","m":"新作は？","t":4998},{"a":"@uchan502","m":"お…おぅ！","t":5000},{"a":"@空白kuuhaku","m":"□□□","t":5004},{"a":"@たまもんn","m":"□□□","t":5006},{"a":"@Kei_通りすがり","m":"□□□","t":5007},{"a":"@べらぼう-b4w","m":"あれ、今ぐるったかな？","t":5013},{"a":"@寒村サムソン","m":"パチパチまでの時間差よw","t":5020},{"a":"@まっつん-UR","m":"そこは寝ろねやろｗ","t":5024},{"a":"@fia_osake","m":"新背景に免じて許してあげよう□","t":5027},{"a":"@nature_nano","m":"10か月おめでとうございます□□□","t":5028},{"a":"@しろるん-v8x","m":"こんろね〜久しぶり〜！！","t":5029},{"a":"@えぴ-e5h","m":"スー好き","t":5034},{"a":"@しろるん-v8x","m":"10ヶ月おめでと！！","t":5041},{"a":"@まささま-r2d","m":"ないなら無理しないでも・・・","t":5050},{"a":"@kekeの毛っ毛0v0","m":"今考えてしまう⋯⋯","t":5053},{"a":"@ミサラギの助","m":"ロード中長いなw","t":5053},{"a":"@ゲーム大好きytk","m":"さて新作って何回いったでしょう□","t":5053},{"a":"@カキツバ-t9p","m":"あれ…？ルンバろねちゃんがいない…？","t":5054},{"a":"@ハクスタ","m":"お題だれかあげたげてー！","t":5057},{"a":"@ちんまさ〆age48","m":"草","t":5059},{"a":"@fia_osake","m":"やめときwろくなことにならんw","t":5059},{"a":"@オオスカシバ-y2w","m":"□","t":5060},{"a":"@おつかれさま","m":"□□□","t":5064},{"a":"@しろるん-v8x","m":"ドイツと言ったのはどこのどいつや！！","t":5065},{"a":"@まっつん-UR","m":"ｗｗｗ","t":5065},{"a":"@fia_osake","m":"草w","t":5066},{"a":"@tundra1204","m":"こん□□","t":5072},{"a":"@しろるん-v8x","m":"どうですか！！ましろね","t":5072},{"a":"@kekeの毛っ毛0v0","m":"それこそ謝罪会見では:camera_with_flash::camera_with_flash::camera_with_flash:","t":5072},{"a":"@Kei_通りすがり","m":"□□□","t":5074},{"a":"@夜叉-v5v","m":"さっきのが全力かな","t":5074},{"a":"@ゲーム大好きytk","m":"□□□","t":5074},{"a":"@extえくすと","m":"諦め□","t":5075},{"a":"@cdab6040","m":"どんまい:winking_face:","t":5075},{"a":"@hiroroろめふれ","m":"あわわ、ましろねさんが、何処かに行きそうだった、、□□","t":5077},{"a":"@まささま-r2d","m":"ましろね先生の次回作にご期待ください□","t":5084},{"a":"@べらぼう-b4w","m":"もはや潔いまであるｗ","t":5093},{"a":"@tomo-jx4fv","m":"こんろね〜","t":5105},{"a":"@高橋伸一-g5j","m":"□□□□□","t":5107},{"a":"@ふぃぐれむ","m":"水色ログ待機してたのに…","t":5108},{"a":"@cdab6040","m":"アル中□発動！","t":5108},{"a":"@ゲーム大好きytk","m":"酒を飲んでダジャレがないと叫ぶ□","t":5116},{"a":"@えぴ-e5h","m":"このオシャレな部屋でワンカップ飲んでるの面白すぎる","t":5117},{"a":"@空白kuuhaku","m":"素直でよろしい♪","t":5117},{"a":"@ミサラギの助","m":"ないすぱ！","t":5117},{"a":"@hiroroろめふれ","m":"ナイスパ","t":5119},{"a":"@しろるん-v8x","m":"ないふぱ","t":5121},{"a":"@寒村サムソン","m":"もし言ったとしても地獄の未来しか想像できない","t":5122},{"a":"@むりくり-x5l","m":"ないすぱ！","t":5123},{"a":"@kekeの毛っ毛0v0","m":"ないすぱ","t":5123},{"a":"@fia_osake","m":"ないすぱ〜","t":5125},{"a":"@空白kuuhaku","m":"ナイスパ〜□□","t":5125},{"a":"@まささま-r2d","m":"んないすぱ～□","t":5125},{"a":"@Kei_通りすがり","m":"ナイスパ！","t":5125},{"a":"@かたっち-h8j","m":"ナイスパ","t":5127},{"a":"@寒村サムソン","m":"ないすぱ！","t":5128},{"a":"@アポーーンス","m":"ないすぱ","t":5132},{"a":"@ちんまさ〆age48","m":"ないスパ！","t":5133},{"a":"@夜叉-v5v","m":"ないすぱ","t":5134},{"a":"@えぴ-e5h","m":"ないすぱ","t":5144},{"a":"@えぴ-e5h","m":"ぱしゃりんちょ！ぱしゃりんちょ！","t":5162},{"a":"@hiroroろめふれ","m":"□□□","t":5172},{"a":"@kekeの毛っ毛0v0","m":"パシャリんちょ！:camera_with_flash::camera_with_flash:Σp:camera:ω･´)","t":5174},{"a":"@つなな-e6y","m":":camera::camera::camera:","t":5177},{"a":"@lippy_youtube","m":"ぱしゃりんちょ","t":5179},{"a":"@まささま-r2d","m":"酒飲んだ後の「あ～」がおっさんなんよな～□","t":5180},{"a":"@オオスカシバ-y2w","m":"ぱしゃりんちょ！","t":5183},{"a":"@ゲーム大好きytk","m":"ないすぱ","t":5185},{"a":"@まっつん-UR","m":":camera_with_flash::camera_with_flash::camera_with_flash::camera_with_flash:","t":5187},{"a":"@高橋伸一-g5j","m":":camera_with_flash:","t":5190},{"a":"@ミサラギの助","m":"夜勤用の晩御飯買う時に、ノンアル買うか本気で迷った、、","t":5200},{"a":"@ハクスタ","m":"がぶがぶがぶりんちょとおなじノリね□","t":5201},{"a":"@空白kuuhaku","m":"パシャリンチョ！パシャリンチョ:red_exclamation_mark:","t":5208},{"a":"@米良智史","m":"ましろねさんこんろね夜かつお疲れ様美人かわいい素敵飲み過ぎ注意:clinking_beer_mugs:","t":5209},{"a":"@kekeの毛っ毛0v0","m":"本日謝罪多めやな〜","t":5211},{"a":"@高橋伸一-g5j","m":":camera_with_flash::camera_with_flash::camera_with_flash::camera_with_flash:","t":5214},{"a":"@しろるん-v8x","m":"ましろね、ましろね、素晴らしい提案をしよう。","t":5218},{"a":"@ゲーム大好きytk","m":":camera_with_flash::sparkles:","t":5230},{"a":"@えぴ-e5h","m":"3歳ならしょーがない（定期）","t":5231},{"a":"@cdab6040","m":"ぴちぴちの3歳と240ヶ月やもんな","t":5243},{"a":"@kekeの毛っ毛0v0","m":"それはガブリチューやないのか？","t":5254},{"a":"@眠兎-ミント","m":"こんろね～","t":5255},{"a":"@fia_osake","m":"ぴち...ぴち...？","t":5258},{"a":"@マサ夫","m":"ペロりんちょ」くらいかな","t":5261},{"a":"@ハクスタ","m":"たぶんパックンチョじゃない？w","t":5263},{"a":"@オオスカシバ-y2w","m":"ガブリチュウは聞いたことある…","t":5266},{"a":"@音幻","m":"□□□","t":5267},{"a":"@cdab6040","m":"ドンドンガバチョみたいなもんやね","t":5274},{"a":"@かたっち-h8j","m":"ぱしゃりんちょの口癖になりそう","t":5276},{"a":"@しろるん-v8x","m":"ダジャレの提案になります。星が逃げたよ、すたーこらさっさー ……どうでしょう。","t":5280},{"a":"@ミサラギの助","m":"血の涙流しながら控えたよ、、","t":5284},{"a":"@ゲーム大好きytk","m":"ピチピチってましろねさん跳ね回ってるのか","t":5288},{"a":"@しろるん-v8x","m":"なっつ","t":5298},{"a":"@えぴ-e5h","m":"がぶりちゅう懐かしい","t":5299},{"a":"@ギリギリ好きな螽斯","m":"おはようございます□","t":5305},{"a":"@るーんowo","m":"ガブリンチョ はキョウリュウジャーかな□","t":5318},{"a":"@kekeの毛っ毛0v0","m":"ハイチュウと並んで歯の詰め物が取れるやつやな！","t":5321},{"a":"@fia_osake","m":"ガブリチュウ懐かしい！","t":5347},{"a":"@えぴ-e5h","m":"がぶりちゅう最近見ない気がする","t":5353},{"a":"@えぴ-e5h","m":"キョウリュウ...","t":5365},{"a":"@カキツバ-t9p","m":"真白猫さんの新居で焼肉焼こうぜ！","t":5367},{"a":"@ミサラギの助","m":"きょうりゅうじゃ？","t":5367},{"a":"@るーんowo","m":"恐竜...","t":5373},{"a":"@ゲーム大好きytk","m":"夜バージョンにしたまま、朝活始めるんですね。自分分かります","t":5374},{"a":"@空白kuuhaku","m":"恐竜だよ","t":5374},{"a":"@kekeの毛っ毛0v0","m":"きゅうりゅう？","t":5375},{"a":"@えぴ-e5h","m":"きょうりゅう","t":5377},{"a":"@オオスカシバ-y2w","m":"キょウリュウジャー…","t":5378},{"a":"@寒村サムソン","m":"カタカナが読めない……だと……？","t":5378},{"a":"@まっつん-UR","m":"キュウリュウ？ｗ","t":5387},{"a":"@extえくすと","m":"もうダメかな今日","t":5391},{"a":"@fia_osake","m":"恐竜も読めんのか！！！？","t":5391},{"a":"@ハクスタ","m":"ガブリチュウ＋パックンチョ＝がぶりんちょの連想になった説","t":5393},{"a":"@mosamosa-magic","m":"恐竜が飲めないだと！？","t":5397},{"a":"@高橋伸一-g5j","m":"□□□□","t":5399},{"a":"@ゲーム大好きytk","m":"ましろねは素面でも変わらないでしょ","t":5401},{"a":"@空白kuuhaku","m":"とうとうカタカナすらも……","t":5402},{"a":"@まささま-r2d","m":"何度読み返しても□□","t":5403},{"a":"@えぴ-e5h","m":"なるべくひらがなにしよう！！！","t":5405},{"a":"@寒村サムソン","m":"草","t":5409},{"a":"@しろるん-v8x","m":"ましろね……ついに、片仮名がだめになったw","t":5410},{"a":"@ハクスタ","m":"うせやろ","t":5411},{"a":"@kekeの毛っ毛0v0","m":"□もここまで来ると、もう⋯ストゼロ梅は禁止かな？","t":5412},{"a":"@天城シナノ","m":"ましろね・・・あなた・・・","t":5413},{"a":"@アグ-f4j","m":"とうとうカタカナまで読めなくなったのか・・・・","t":5415},{"a":"@えぴ-e5h","m":"3歳ならしゃーない（定期）","t":5418},{"a":"@空白kuuhaku","m":"カタカナどうフリガナすればいいんだ…","t":5427},{"a":"@鋼屋-Haganeya","m":"（悲報）ましろねさん、カタカナ読めない","t":5430},{"a":"@ゲーム大好きytk","m":"いつもどおりでは□","t":5433},{"a":"@カキツバ-t9p","m":"うちの娘と一緒に学研に通います？","t":5436},{"a":"@アポーーンス","m":"←これ読めますか？","t":5443},{"a":"@fia_osake","m":"いつもは:cross_mark:いつも通りです！！！！！","t":5451},{"a":"@眠兎-ミント","m":"いwじwらwれwすwぎw","t":5455},{"a":"@空白kuuhaku","m":"#真白猫カタカナ読めない","t":5462},{"a":"@ハクスタ","m":"ましろねはカタカナ(かたかな)が読めないぽんの子(こ)です になってしまう","t":5471},{"a":"@ふぃぐれむ","m":"読み方職人さん仕事増えてますね・・・□","t":5474},{"a":"@かたっち-h8j","m":"お酒のせいにしとくか","t":5482},{"a":"@fia_osake","m":"嘘だ！！！！！","t":5484},{"a":"@オオスカシバ-y2w","m":"楽しいから良きです","t":5484},{"a":"@まささま-r2d","m":"深呼吸な□","t":5485},{"a":"@まっつん-UR","m":"ましろね、落ち着くんや！落ち着けばカタカナも読める！","t":5487},{"a":"@つよし-s9z","m":"WWW","t":5488},{"a":"@空白kuuhaku","m":"ナイスパ〜□","t":5501},{"a":"@しろるん-v8x","m":"ないすぱ","t":5503},{"a":"@寒村サムソン","m":"ないすぱ！","t":5503},{"a":"@まささま-r2d","m":"んないすぱ～□","t":5505},{"a":"@ゲーム大好きytk","m":"ないすぱ","t":5507},{"a":"@Kei_通りすがり","m":"ナイスパ！","t":5510},{"a":"@fia_osake","m":"ないすぱ！","t":5512},{"a":"@hiroroろめふれ","m":"緊張してるなら、、ねぇ仕方ない□","t":5512},{"a":"@しろるん-v8x","m":"( ⁎ᵕᴗᵕ⁎ )ﾎｯ","t":5513},{"a":"@extえくすと","m":"ないすぱ","t":5517},{"a":"@hiroroろめふれ","m":"ナイスパ","t":5517},{"a":"@寒村サムソン","m":"ワンカップに謝って","t":5522},{"a":"@かたっち-h8j","m":"ナイスパ","t":5523},{"a":"@kekeの毛っ毛0v0","m":"ナイスパ！","t":5525},{"a":"@extえくすと","m":"一旦チル","t":5527},{"a":"@米良智史","m":"ポンコツ、うわ〜ん清楚なましろねさんが:loudly_crying_face:","t":5529},{"a":"@オオスカシバ-y2w","m":"ないすぱあ！","t":5530},{"a":"@空白kuuhaku","m":"これだから真白猫の配信がやめられないんだよww","t":5534},{"a":"@天城シナノ","m":"ましろねの□とかけまして、湿気の多い場所と説きます、その心はどちらもカナ(金)ものがダメでしょう・・・・","t":5545},{"a":"@不幸なジン","m":"緊張してる？酒飲む？","t":5560},{"a":"@えぴ-e5h","m":"3歳（さんさい）だからかたかなよめなくてもしょうがないんやで","t":5570},{"a":"@extえくすと","m":"チルは短いやろ□□","t":5574},{"a":"@オオスカシバ-y2w","m":"フッィシュ","t":5574},{"a":"@kekeの毛っ毛0v0","m":"まぁまぁ、まだセーフ判定できなくもない⋯か？","t":5582},{"a":"@しろるん-v8x","m":"ましろね、次ポン出したらストゼロ禁ね？","t":5586},{"a":"@しろるん-v8x","m":"（）","t":5588},{"a":"@fia_osake","m":"チルの2文字でドヤられてもw□","t":5600},{"a":"@夜叉-v5v","m":"ﾀﾞｲｼﾞｮﾌﾞﾃﾞｽｶ","t":5601},{"a":"@空白kuuhaku","m":"キュウリュウで「えっ？」ってなった後に笑いが止まらなくなったww","t":5605},{"a":"@アルテミス-v8i","m":"セウト?","t":5613},{"a":"@不幸なジン","m":"疑惑のセーフ判定で草","t":5625},{"a":"@米良智史","m":"サブトン10まい","t":5625},{"a":"@kekeの毛っ毛0v0","m":"笑いを提供してくれた部分はセーフかな","t":5631},{"a":"@空白kuuhaku","m":"流石にセーフ判定はキツイんじゃない？","t":5632},{"a":"@しろるん-v8x","m":"全会一致でセーフになりません。","t":5651},{"a":"@やまもといちろう-y5d","m":"コンバンハ","t":5655},{"a":"@かたっち-h8j","m":"真白猫さんは早口言葉とか言えますか？","t":5657},{"a":"@天城シナノ","m":"あいごきょうかいさんのフォローが無い・・・これはもしかしてとうとう匙を・・・・","t":5664},{"a":"@るーんowo","m":"ましろねちゃんごめんね...まさかキョウリュウジャーでこんなことになるなんて思わなかったんだ...","t":5686},{"a":"@kekeの毛っ毛0v0","m":"初めての配信背景で、ワイが来てから4回ほど謝罪してる気がする","t":5704},{"a":"@風呂カラ親父44","m":"お酒でおねむになっちゃったかな?","t":5706},{"a":"@アポーーンス","m":"カタカナって、細め目で見たら似たようなやつありますしね（無理ある？）","t":5706},{"a":"@夜叉-v5v","m":"カタカナ読める様になりましたね！良かった","t":5714},{"a":"@fia_osake","m":"笑顔と話題が常に提供されるましろねの雑談配信！□","t":5715},{"a":"@thecoolmiregoji784","m":"Good evening","t":5718},{"a":"@天城シナノ","m":"ましろねの□のインパクトで部屋の謎かけが消し飛びました・・・ｗ","t":5721},{"a":"@空白kuuhaku","m":"誰も予想できないわなww","t":5723},{"a":"@ハクスタ","m":"謝罪配信用の背景も用意してもろて…","t":5732},{"a":"@寒村サムソン","m":"ましろねの□の所為(せい)でまったりできないw","t":5734},{"a":"@アルテミス-v8i","m":"あまりに酷いと匙よ月まで届けになりそう","t":5736},{"a":"@えぴ-e5h","m":"今日謝罪多いですね笑","t":5739},{"a":"@不幸なジン","m":"まさか謝罪会見の背景…？？","t":5741},{"a":"@ミサラギの助","m":"やっぱ謝罪会見しとく？","t":5745},{"a":"@空白kuuhaku","m":"カタカナでGO制作してくれんかな～","t":5758},{"a":"@しろるん-v8x","m":"ましろねさん、ましろねーずに謝罪会見をお願い致します。","t":5770},{"a":"@クマがクマった球磨熊ーくまくまー","m":"記念謝罪配信w","t":5781},{"a":"@kekeの毛っ毛0v0","m":"ァ、マシロネサン、オヘヤ、トテモ、チュテキデツネ","t":5791},{"a":"@空白kuuhaku","m":"いつも通りで安心だよww","t":5801},{"a":"@ギリギリ好きな螽斯","m":"ソとリとンは書く人によっては区別つかない","t":5806},{"a":"@まささま-r2d","m":"ここから立て直しお願いします□","t":5812},{"a":"@寒村サムソン","m":"カ(か)と力(ちから)とか見分け付かないもんね！カタカナしょうがないね！","t":5812},{"a":"@アルテミス-v8i","m":"謝罪会見会場だったのかここ","t":5814},{"a":"@ミサラギの助","m":"仕事中なのにつっこまずにはいられない、、、ましろねやるなw","t":5820},{"a":"@thecoolmiregoji784","m":"You’re bad with words?","t":5820},{"a":"@高橋伸一-g5j","m":"気合い入れる:red_exclamation_mark:","t":5825},{"a":"@天城シナノ","m":"いつも通りと言いたいところだが、流石にカタカナは・・・・","t":5827},{"a":"@えぴ-e5h","m":"！？","t":5827},{"a":"@fia_osake","m":"謝罪会見用の背景と机素材用意しようか","t":5831},{"a":"@しろるん-v8x","m":"ﾊﾟｼｬｯ! Σp[【◎】]ω･´)","t":5832},{"a":"@kekeの毛っ毛0v0","m":":camera_with_flash::camera_with_flash::camera_with_flash::camera_with_flash::camera_with_flash::camera_with_flash:","t":5843},{"a":"@えぴ-e5h","m":"ぱしゃりんちょ！ぱしゃりんちょ！","t":5848},{"a":"@ギリギリ好きな螽斯","m":":camera_with_flash::camera_with_flash::camera_with_flash::camera_with_flash::camera_with_flash::camera_with_flash:","t":5851},{"a":"@えぴ-e5h","m":":camera_with_flash::camera_with_flash::camera_with_flash:","t":5856},{"a":"@空白kuuhaku","m":"キュウリュウって沖縄にありそうなイメージなんだよな～","t":5857},{"a":"@かたっち-h8j","m":":camera_with_flash::camera_with_flash::camera:´-","t":5858},{"a":"@高橋伸一-g5j","m":":camera_with_flash::camera_with_flash::camera_with_flash::camera_with_flash::camera_with_flash:","t":5858},{"a":"@クマがクマった球磨熊ーくまくまー","m":":camera_with_flash::camera_with_flash::camera_with_flash::camera_with_flash::camera_with_flash::camera_with_flash:","t":5861},{"a":"@Kei_通りすがり","m":":camera_with_flash::camera_with_flash::camera_with_flash::camera_with_flash::camera_with_flash:","t":5863},{"a":"@まささま-r2d","m":"パシャパシャリパシャリンチョ:camera_with_flash::camera_with_flash:","t":5865},{"a":"@オオスカシバ-y2w","m":"どっちかって言うとヤンデレ背景","t":5866},{"a":"@空白kuuhaku","m":":camera_with_flash::camera_with_flash::camera_with_flash::camera_with_flash::camera_with_flash::camera_with_flash::camera_with_flash::camera_with_flash::camera_with_flash:","t":5869},{"a":"@クマがクマった球磨熊ーくまくまー","m":":camera::camera::camera::camera::camera:","t":5873},{"a":"@アポーーンス","m":"背景が黒だと本当の謝罪会見みたいですね、、","t":5873},{"a":"@kekeの毛っ毛0v0","m":":camera_with_flash::camera_with_flash:反省がみえませんよ！？？","t":5873},{"a":"@ギリギリ好きな螽斯","m":":camera::camera::camera::camera::camera::camera::camera:","t":5878},{"a":"@えぴ-e5h","m":"キラキラ目くださーい","t":5879},{"a":"@夜叉-v5v","m":":camera_with_flash::camera_with_flash::camera_with_flash::camera_with_flash::camera_with_flash:","t":5880},{"a":"@やまもといちろう-y5d","m":":camera:","t":5881},{"a":"@オクナミ","m":"来たら謝罪会見だったw","t":5881},{"a":"@hiroroろめふれ","m":"ぱしゃ　ぱしゃ　ぱしゃりんちょ","t":5882},{"a":"@かたっち-h8j","m":"ぱしゃりんちょぱしゃりんちょ:camera:が","t":5884},{"a":"@るーんowo","m":"口じゃなくて頭が回ってなかったような...？","t":5884},{"a":"@まっつん-UR","m":":camera::camera::camera::camera::camera::camera::camera:","t":5890},{"a":"@tundra1204","m":"Σp:camera:ω･´)Σp:camera:ω･´)Σp:camera:ω･´)","t":5892},{"a":"@Kei_通りすがり","m":":camera::camera::camera::camera::camera:","t":5893},{"a":"@まささま-r2d","m":"いつもは違うんでしょうか？:studio_microphone:","t":5899},{"a":"@高橋伸一-g5j","m":":video_camera::video_camera::video_camera::video_camera:","t":5900},{"a":"@クマがクマった球磨熊ーくまくまー","m":":movie_camera::movie_camera::movie_camera::movie_camera::movie_camera:","t":5900},{"a":"@pastel5737","m":"ところで左側のちびろねさんは帰ってこないのでしょうか？","t":5905},{"a":"@kekeの毛っ毛0v0","m":":camera_with_flash::collision:","t":5911},{"a":"@しろるん-v8x","m":"今回の記事。ましろね、片仮名が読めなくなる。……これで決まりです","t":5912},{"a":"@ハクスタ","m":"真っ黒背景で配信始まったら多分めっちゃ嫌な意味でドキッとしちゃうw","t":5926},{"a":"@ミサラギの助","m":"□□□□","t":5927},{"a":"@kekeの毛っ毛0v0","m":":video_camera:●REC","t":5931},{"a":"@クマがクマった球磨熊ーくまくまー","m":"ウソヲツクナー！","t":5933},{"a":"@えぴ-e5h","m":"キラキラ目くださーい","t":5940},{"a":"@夜叉-v5v","m":"ましろねさんこちらにも一枚お願いします:camera_with_flash::camera_with_flash::camera_with_flash:","t":5941},{"a":"@アルテミス-v8i","m":"グダグダにならないように頑張れー","t":5943},{"a":"@fia_osake","m":"ルンバろねは早急にかえしてもろて！","t":5959},{"a":"@寒村サムソン","m":"ｷｬｰ!ﾁﾋﾞﾛﾈｻｰﾝ!","t":5963},{"a":"@lippy_youtube","m":"ちびろねたすかる","t":5963},{"a":"@高橋伸一-g5j","m":"□□□□","t":5964},{"a":"@kekeの毛っ毛0v0","m":"インサイダー取引ですか！？","t":5965},{"a":"@cdab6040","m":"本体消したらアカンやん","t":5965},{"a":"@まささま-r2d","m":"おお□□□","t":5965},{"a":"@空白kuuhaku","m":":warning:今回の謝罪会見は【キョウリュウジャー】を【キュウリュウジャー】と読んでしまった事に対しての謝罪会見になっております。","t":5973},{"a":"@天城シナノ","m":"ましろねーず新聞明日の朝刊の一面『衝撃！！！ましろね！ついにカタカナも誤読！！！』","t":5975},{"a":"@しろるん-v8x","m":"ｷｬｰ!!ﾙﾝﾊﾞﾛﾈﾖｰ!!","t":5976},{"a":"@hiroroろめふれ","m":"ちび□□□□","t":5987},{"a":"@クマがクマった球磨熊ーくまくまー","m":"冗談！？","t":5993},{"a":"@ごはん処ラピ","m":"『そしてそしきされたのが、［ちびろねあいごきょうかい］である。ちびろねあいごきょうかいでは、きょうかいいんさんをぼしゅうしています。』","t":5998},{"a":"@fia_osake","m":"ルンバろねお帰り！","t":6004},{"a":"@しろるん-v8x","m":"ん？冗談？","t":6005},{"a":"@kekeの毛っ毛0v0","m":"きたーーーーー！","t":6008},{"a":"@まささま-r2d","m":"全然まったりしなかったね□","t":6008},{"a":"@ゆのっち-p3s","m":"こん□□","t":6009},{"a":"@寒村サムソン","m":"ないすぱ！","t":6009},{"a":"@空白kuuhaku","m":"ナイスパ〜□","t":6011},{"a":"@しろるん-v8x","m":"ないすぱ","t":6011},{"a":"@ミサラギの助","m":"ないすぱ！","t":6013},{"a":"@アポーーンス","m":"ないすぱ","t":6014},{"a":"@Kei_通りすがり","m":"ナイスパ！","t":6015},{"a":"@かたっち-h8j","m":"ナイスパ","t":6015},{"a":"@ShinKa331","m":"ないすぱ～！","t":6019},{"a":"@kekeの毛っ毛0v0","m":"ナイスパ","t":6020},{"a":"@まささま-r2d","m":"んないすぱ～□","t":6020},{"a":"@カキツバ-t9p","m":"このまま朝活でしょ？","t":6022},{"a":"@まっつん-UR","m":"ないすぱ","t":6024},{"a":"@ハクスタ","m":"どこまでが冗談だったんだろう()","t":6024},{"a":"@hiroroろめふれ","m":"ナイスパ","t":6025},{"a":"@天城シナノ","m":"ないすぱ","t":6032},{"a":"@kekeの毛っ毛0v0","m":"お掃除♡","t":6049},{"a":"@空白kuuhaku","m":"頭の上にする？","t":6051},{"a":"@カキツバ-t9p","m":"ルンバろね…返して…返して…","t":6053},{"a":"@ShinKa331","m":"ルンバ□□","t":6058},{"a":"@アスラ-jp","m":"こん□","t":6064},{"a":"@夜叉-v5v","m":"朝ゆっくり見れないけど夜ならこんなましろねさんも見れるとは有り難い","t":6081},{"a":"@ごはん処ラピ","m":"ルンバろねあいごきょうかいもそしきするかぁ","t":6082},{"a":"@まささま-r2d","m":"ルンバ□ちゃんを真ん中にして、ましろねが端に行っては？","t":6089},{"a":"@しろるん-v8x","m":"冗談……？ましろね、全会一致で冗談とは思えないという方針ですが……（？）","t":6092},{"a":"@fia_osake","m":"ルンバろねあいごきょうかい会員です！","t":6119},{"a":"@アルテミス-v8i","m":"その結果が謝罪会見・・・","t":6134},{"a":"@しろるん-v8x","m":"ポンろねあいごきょうかい","t":6149},{"a":"@カキツバ-t9p","m":"させねーよ！","t":6149},{"a":"@まささま-r2d","m":"寝坊しないように・・□","t":6158},{"a":"@空白kuuhaku","m":"このまま朝活まで配信じゃないの？","t":6161},{"a":"@寒村サムソン","m":"今日はちゃんと早く寝るんやでー","t":6163},{"a":"@mosamosa-magic","m":"どういたしまして〜♪","t":6179},{"a":"@空白kuuhaku","m":"やっぱり酔ってるよね？","t":6182},{"a":"@しろるん-v8x","m":"え？すやすや枠じゃないの？","t":6184},{"a":"@ミサラギの助","m":"そうやね、、、遅くなるとまた大記録を出しちゃうからねw","t":6186},{"a":"@ハクスタ","m":"ましろねはいつも真面目にがんばってるよ□","t":6190},{"a":"@extえくすと","m":"感謝でいつもニヤニヤするましろね□","t":6190},{"a":"@るーんowo","m":"ゆっくり休んでね□","t":6190},{"a":"@kekeの毛っ毛0v0","m":"いつも早起きお疲れちゃんデス","t":6190},{"a":"@かきみーらorz","m":"朝まで記念枠？","t":6195},{"a":"@mosamosa-magic","m":"ましろねの配信が楽しいから来ちゃうんだよな〜♪","t":6195},{"a":"@まささま-r2d","m":"ましろね、寝ろね□","t":6196},{"a":"@アポーーンス","m":"日課になってるんで助かります","t":6198},{"a":"@ごはん処ラピ","m":"寝ずにやれば、寝坊「は」しないよっ:victory_hand:","t":6201},{"a":"@ふぃぐれむ","m":"ポン酒耐性そこまで高くない感じなきがする","t":6206},{"a":"@空白kuuhaku","m":"記念配信で謝罪会見ww","t":6211},{"a":"@アルテミス-v8i","m":"寝坊フラグ建ててる?","t":6215},{"a":"@クマがクマった球磨熊ーくまくまー","m":"明日の朝も謝罪かーw","t":6215},{"a":"@Natu7214","m":"寝坊しないためにオールすれば解決","t":6220},{"a":"@夜叉-v5v","m":"ゆっくり休んで","t":6221},{"a":"@ミサラギの助","m":"シラフは飲んでる時点で無理やろw","t":6226},{"a":"@空白kuuhaku","m":"改めておめでとうございます:party_popper:","t":6229},{"a":"@音幻","m":"□□□","t":6246},{"a":"@しろるん-v8x","m":"(⑉>ᴗ<ﾉﾉﾞﾊﾟﾁﾊﾟﾁﾊﾟﾁ~","t":6250},{"a":"@カキツバ-t9p","m":"泣ける…:crying_face:","t":6251},{"a":"@kekeの毛っ毛0v0","m":"10ヶ月おめでとうございます。毎朝お声聞けて助かってます","t":6258},{"a":"@つよし-s9z","m":"お疲れ様でした〜","t":6260},{"a":"@るーんowo","m":"寝坊してもそれはそれで楽しいからじゃんじゃん寝坊してもろて！","t":6262},{"a":"@まささま-r2d","m":"ええ話や□","t":6264},{"a":"@hiroroろめふれ","m":"こちらこそ宜しくお願い致します□□","t":6265},{"a":"@寒村サムソン","m":":clapping_hands::clapping_hands::clapping_hands::clapping_hands::clapping_hands:","t":6270},{"a":"@オオスカシバ-y2w","m":"改めてこれからもよろ□です！","t":6272},{"a":"@ミサラギの助","m":"ましろねの配信は生き甲斐だよw","t":6293},{"a":"@ハクスタ","m":"ちょっと早めにおつ□！明日もよろしくねえ","t":6295},{"a":"@るーんowo","m":"こちらこそこれからもよろしくね□","t":6297},{"a":"@しろるん-v8x","m":"これからもよろしく！！","t":6299},{"a":"@fia_osake","m":"改めて10ヶ月と新背景本当におめでとう！新規さんも増えて嬉しいね！１周年に向けて頑張ってね！","t":6300},{"a":"@クマがクマった球磨熊ーくまくまー","m":"無理せずにしっかり毎日ポンを届けて偉い！","t":6301},{"a":"@るーんowo","m":"ないすぱ！","t":6309},{"a":"@しろるん-v8x","m":"ないふぱ！！","t":6309},{"a":"@kekeの毛っ毛0v0","m":"ナイスパ！","t":6309},{"a":"@まささま-r2d","m":"んないすぱ～□□□","t":6310},{"a":"@空白kuuhaku","m":"ナイスパ〜□□","t":6310},{"a":"@寒村サムソン","m":"ないす赤スパ！","t":6312},{"a":"@Kei_通りすがり","m":"改めてデビュー10ヶ月おめでとうございます:party_popper:まだまだ新参者ですがこれからもよろしくお願いします！","t":6312},{"a":"@かたっち-h8j","m":"ナイスパ","t":6314},{"a":"@ごはん処ラピ","m":"まぁ確かに、あいごきょうかい定期ないと、みんなの朝が始まらないよなぁ(ちがう)","t":6316},{"a":"@夜叉-v5v","m":"いつも癒やしボイスで心が洗われてます","t":6316},{"a":"@hiroroろめふれ","m":"ナイスパ","t":6316},{"a":"@ShinKa331","m":"ナイスパ！","t":6317},{"a":"@寒村サムソン","m":"ないすぱ！","t":6318},{"a":"@るーんowo","m":"ないすぱ！","t":6319},{"a":"@しろるん-v8x","m":"ないふぱ","t":6319},{"a":"@空白kuuhaku","m":"ナイスパ〜□□","t":6319},{"a":"@天城シナノ","m":"ないすぱー","t":6320},{"a":"@extえくすと","m":"ないすぱ","t":6320},{"a":"@かたっち-h8j","m":"ナイスパ","t":6320},{"a":"@まささま-r2d","m":"んないすぱ～□","t":6320},{"a":"@ミサラギの助","m":"ないすぱ！","t":6323},{"a":"@アポーーンス","m":"ないすぱ","t":6323},{"a":"@kekeの毛っ毛0v0","m":"ないすぱ□□","t":6325},{"a":"@ふぃぐれむ","m":"ポン酒（ぽんしゅ）、ないすぱ","t":6329},{"a":"@夜叉-v5v","m":"ないすぱ","t":6329},{"a":"@まっつん-UR","m":"ないスパ","t":6330},{"a":"@オオスカシバ-y2w","m":"ないすぱ！！","t":6330},{"a":"@ゆのっち-p3s","m":"ないすぱー","t":6331},{"a":"@アルテミス-v8i","m":"ナイスパー","t":6332},{"a":"@高橋伸一-g5j","m":"いつも感謝しています、楽しかったよ:sparkles:","t":6340},{"a":"@Kei_通りすがり","m":"ナイ赤スパ！","t":6342},{"a":"@まささま-r2d","m":"最後いい感じにまとまった、やるな□","t":6360},{"a":"@天城シナノ","m":"ましろねは本気でやってて□が出てくるから応援したくなるんよなぁ","t":6375},{"a":"@えぴ-e5h","m":"いつも楽しませてもらてます！本当にありがとうございます！","t":6383},{"a":"@しろるん-v8x","m":"こちらこそ！！いつもありがと！！","t":6403},{"a":"@空白kuuhaku","m":"テレてる真白猫カワイイよ～","t":6407},{"a":"@kekeの毛っ毛0v0","m":"夜配信はお酒で舌がなめらかになるからいい話が聞ける","t":6413},{"a":"@しろるん-v8x","m":"最後にいいポンが見れたねぇ","t":6416},{"a":"@クマがクマった球磨熊ーくまくまー","m":"読み間違い定期w","t":6419},{"a":"@ごはん処ラピ","m":"ま し ろ ね 、 寝 ろ ね ！ (大 声)","t":6421},{"a":"@風呂カラ親父44","m":"こちらこそ、いつもありがとう〜","t":6423},{"a":"@ミサラギの助","m":"やっぱり□で始まり、□で〆るのかw","t":6433},{"a":"@空白kuuhaku","m":"いつも楽しい配信ありがとう□","t":6448},{"a":"@3106osamu","m":"寝ろ猫　いただきました","t":6452},{"a":"@fia_osake","m":"いつも通り最初と最後は□","t":6454},{"a":"@アルテミス-v8i","m":"とりあえず寝坊しないように頑張れー","t":6458},{"a":"@kekeの毛っ毛0v0","m":"さ、再度□が出る前に寝るべ寝るべ","t":6466},{"a":"@寒村サムソン","m":"ましろねの朝活を楽しみにしてくれてる人がたくさんおるのも忘れずになー！","t":6466},{"a":"@しろるん-v8x","m":"おつろねさまでした〜","t":6475},{"a":"@まささま-r2d","m":"おつ□","t":6481},{"a":"@ミサラギの助","m":"いつもが長いのよ？w","t":6481},{"a":"@ごはん処ラピ","m":"おつ□","t":6485},{"a":"@extえくすと","m":"おつ□□","t":6485},{"a":"@空白kuuhaku","m":"おつ□□","t":6486},{"a":"@かたっち-h8j","m":"おつ□","t":6492},{"a":"@kekeの毛っ毛0v0","m":"おつ□□","t":6492},{"a":"@アルテミス-v8i","m":"おつ□","t":6495},{"a":"@hiroroろめふれ","m":"おつ□□□","t":6496},{"a":"@寒村サムソン","m":"おつろね","t":6499},{"a":"@mosamosa-magic","m":"おつ□□","t":6499},{"a":"@どこにでもいるよっちゃん","m":"おつ□","t":6500},{"a":"@るーんowo","m":"おつろねー□また明日ね〜！","t":6500},{"a":"@つよし-s9z","m":"おつ□でした！","t":6501},{"a":"@ミサラギの助","m":"おつ□","t":6501},{"a":"@クマがクマった球磨熊ーくまくまー","m":"おつ□〜:bear:ﾉｼ","t":6502},{"a":"@nature_nano","m":"おつ□□","t":6504},{"a":"@ヴィル-v7v","m":"真白猫おはようおわんのか","t":6504},{"a":"@Kei_通りすがり","m":"おつ□","t":6505},{"a":"@ぺとらんち","m":"おつ□□□","t":6507},{"a":"@fia_osake","m":"おつ□〜","t":6509},{"a":"@ShinKa331","m":"おつ□□","t":6510},{"a":"@Natu7214","m":"おつろね","t":6511},{"a":"@オオスカシバ-y2w","m":"おつ□でした~","t":6512},{"a":"@かきみーらorz","m":"おつ□□","t":6514},{"a":"@ゆのっち-p3s","m":"おつろね～□□","t":6514},{"a":"@flytora","m":"otsukare","t":6515},{"a":"@フレミングno右手","m":"おつ□□","t":6515},{"a":"@バッサー-s9q","m":"おつろね〜","t":6516},{"a":"@shisonoha","m":"おつ□でした","t":6518},{"a":"@夜叉-v5v","m":"おつ□良かったねいい勉強になって","t":6518},{"a":"@pastel5737","m":"おつ□□","t":6518},{"a":"@ふぃぐれむ","m":"おつ（ちび）□□","t":6518},{"a":"@AyaOhkura","m":"おつ□です","t":6519},{"a":"@アグ-f4j","m":"おーつろねー","t":6519},{"a":"@ナナシ名前","m":"おつろねー","t":6521},{"a":"@そー茶_0214","m":"おつろね〜","t":6523},{"a":"@風呂カラ親父44","m":"お疲れ様です、いつもありがとう〜楽しかったよ〜おつろね～(^^)ｂ","t":6532},{"a":"@寒村サムソン","m":"朝活短め(昼まで)","t":6540},{"a":"@望月薫-96","m":"おつろね〜","t":6540},{"a":"@つばさ箱","m":"おつ□□□","t":6540},{"a":"@高橋伸一-g5j","m":"ミミィちゃん□□おつ□□□□□","t":6542},{"a":"@べらぼう-b4w","m":"おつ□□","t":6545},{"a":"@まっつん-UR","m":"おつ□□","t":6550},{"a":"@アポーーンス","m":"おつろねです","t":6553},{"a":"@3106osamu","m":"おつ□","t":6557},{"a":"@suzumiya322","m":"おつ□","t":6565},{"a":"@lippy_youtube","m":"おつ□□やっぱ夜ver.のASMRの夢が諦めきれません□","t":6593},{"a":"@えぴ-e5h","m":"おつ□でした！10ヶ月おめでとうございます！いつも配信で元気もらってます！これからも応援していきます！","t":6595},{"a":"@LilySnowdrop.","m":"おつろね～","t":6623},{"a":"@高橋伸一-g5j","m":"ミミィちゃん:sparkles:配信お疲れさまです:sparkles:いろいろありがとうございます:four_leaf_clover:","t":6623},{"a":"@寒村サムソン","m":"ちゃんと寝てしっかり休んで、明日の朝に備えてくださいな","t":6623},{"a":"@空白kuuhaku","m":"これからも楽しんでいこうね〜","t":6628},{"a":"@不幸なジン","m":"おつろね〜","t":6645},{"a":"@fia_osake","m":"ましろねの朝配信は本当に癒しだから続けてくれい□","t":6649},{"a":"@takasa_shin","m":"おつ□□□","t":6653},{"a":"@HAL_KRPS-13","m":"おつろねー","t":6678},{"a":"@天城シナノ","m":"おつ□でした～最後に、ましろねとかけまして、スタックした車と説きます、その心はどちらも全力で「おし(推し/押し)」すでしょう","t":6690},{"a":"@クマがクマった球磨熊ーくまくまー","m":"ASMRと言う名のささやき配信とかどうだろう？","t":6789},{"a":"@chihiro5h","m":"おつろね〜","t":6790},{"a":"@むりくり-x5l","m":"おつ□□","t":6792},{"a":"@のうのうSnow_know","m":"こんばんはー","t":6810},{"a":"@のうのうSnow_know","m":"おつ","t":6820},{"a":"@ポリカなす","m":"こんばんは〜","t":6821},{"a":"@cdab6040","m":"おつ□□","t":6828},{"a":"@ミサラギの助","m":"おすでしょうじゃ、、、おしす？w","t":6859},{"a":"@天城シナノ","m":"誤字りました・・・ｗ","t":6875},{"a":"@まささま-r2d","m":"ましろねはゲラだからな～□","t":6878},{"a":"@fia_osake","m":"いつものマイクで近くで囁いてみるは挑戦いつかしてみてな","t":6896},{"a":"@空白kuuhaku","m":"お願いします:person_bowing:","t":6896},{"a":"@kekeの毛っ毛0v0","m":"こちらこそ宜しくお願いします(∩´∀｀＠)⊃","t":6900},{"a":"@寒村サムソン","m":"ﾉｼ","t":6915},{"a":"@クマがクマった球磨熊ーくまくまー","m":"ばいばーい","t":6916},{"a":"@むりくり-x5l","m":"ばいばーい","t":6917},{"a":"@まささま-r2d","m":"ばいば～い□","t":6918},{"a":"@3106osamu","m":"ばいばーい","t":6918},{"a":"@kekeの毛っ毛0v0","m":"ばいばいー","t":6918},{"a":"@天城シナノ","m":"おやすみなさいまし～","t":6919},{"a":"@extえくすと","m":"ばいばーい","t":6920},{"a":"@高橋伸一-g5j","m":"バイバイ:waving_hand:","t":6920},{"a":"@オオスカシバ-y2w","m":"ばいばーい","t":6921},{"a":"@空白kuuhaku","m":"バイバ〜イ","t":6921},{"a":"@るーんowo","m":"おやすみー","t":6922},{"a":"@つよし-s9z","m":"ばいばーい","t":6925},{"a":"@hiroroろめふれ","m":"ばはーいおやすみ","t":6926},{"a":"@ミサラギの助","m":"ばいばーい","t":6926},{"a":"@ShinKa331","m":"ばいば～い","t":6926},{"a":"@Kei_通りすがり","m":"ばいばーい","t":6930},{"a":"@まっつん-UR","m":"おやすみー□","t":6930},{"a":"@鋼屋-Haganeya","m":"寝落ちしてたら、終わってた（笑）おつろね","t":6932},{"a":"@chihiro5h","m":"ばいば〜い","t":6933},{"a":"@高橋伸一-g5j","m":"お休み:relieved_face::night_with_stars::zzz:なさい:four_leaf_clover:","t":6934},{"a":"@夜叉-v5v","m":"バイバイ〜","t":6934},{"a":"@空白kuuhaku","m":"おやすみなさい","t":6935},{"a":"@fia_osake","m":"これからもよろしくね！ばいば〜い！","t":6936},{"a":"@lippy_youtube","m":"おやすみみい","t":6942},{"a":"@ミサラギの助","m":"いい夢みろよー！","t":6942},{"a":"@mashi_rone","m":"みんな来てくれてありがとう:cherry_blossom:これからもよろしくお願いします...:white_exclamation_mark:","t":6942},{"a":"@ポリカなす","m":"おやすみなさい〜","t":6944},{"a":"@高橋伸一-g5j","m":"バイバイ:waving_hand:","t":6947},{"a":"@こねこね-kone5ne","m":"おやすみなさいー","t":6948},{"a":"@Kei_通りすがり","m":"おやすみなさい","t":6951},{"a":"@あまつ_そら","m":"おつ□ー","t":6956},{"a":"@まささま-r2d","m":"よろしく～□","t":6960},{"a":"@mashi_rone","m":"おやすみなさい:first_quarter_moon:","t":6962},{"a":"@つよし-s9z","m":"おやすみなさい〜","t":6962},{"a":"@高橋伸一-g5j","m":"お休み:relieved_face::night_with_stars::zzz:なさい:four_leaf_clover:","t":6964}]